Workbook
Name AbilityList: [1]Math!$A$48:$A$98
Name AbilityListNoAttributes: [1]Math!$A$48:$A$79
Name AbilityRating: [1]Math!$D$48:$D$98
Name AbilityStatus: [1]Math!$B$105:$B$129
Name AbilityTypeFinal: [1]Math!$J$36:$J$39
Name AbilityTypeSplat: [1]Math!$N$47:$N$63
Name AbilityTypeTable: [1]Math!$O$47:$Q$63
Name AltChargen: [1]Character!$U$2
Name Anima: [1]Data!$D$11:$D$14
Name ArmorStats: [1]Data!$O$21:$S$27
Name ArmorTags: [1]Data!$M$6:$M$10
Name ArmorTypes: [1]Data!$L$2:$M$4
Name AttributeDexterity: [1]Math!$D$86
Name AttributePerception: [1]Math!$D$91
Name AttributeStamina: [1]Math!$D$87
Name AttributeStrength: [1]Math!$D$85
Name AttributeTypeFinal: [1]Math!$K$36:$K$38
Name AttributeTypeSplat: [1]Math!$K$27:$N$27
Name AttributeTypeTable: [1]Math!$K$28:$N$31
Name AttributeWits: [1]Math!$D$93
Name BGDrillType: [1]Data!$Q$37:$Q$39
Name BGMightAttack: [1]Data!$R$41:$R$44
Name BGMightDamage: [1]Data!$S$41:$S$44
Name BGMightDefense: [1]Data!$T$41:$T$44
Name BGMightValue: [1]Data!$Q$41:$Q$44
Name BPCostSplat: [1]Data!$W$27:$AG$27
Name BPCostTable: [1]Data!$W$28:$AG$41
Name BPCostType: [1]Data!$V$28:$V$41
Name CasAttributeFlag: [1]Math!$K$33
Name Caste: [1]Character!$O$3
Name CasteCount: [1]Math!$O$46
Name CasteLookup: [1]Data!$G$29:$H$37
Name Castes: [1]Data!$G$23:$G$27
Name CharacterMerits: [1]Character!$A$26:$H$57
Name ChargenAmount: [2]Data!$V$3:$AL$13
Name ChargenDropdown: [1]Data!$X$44:$X$51
Name ChargenHeader: [2]Data!$V$2:$AL$2
Name CharmData: '[1]Charm List'!$A$2:$L$3453
Name CharmDataAbility: '[1]Charm List'!$H$2:$H$4004
Name CharmDataAbilPreq: '[1]Charm List'!$I$2:$I$4004
Name CharmDataAspect: '[1]Charm List'!$K$2:$K$4004
Name CharmDataCost: '[1]Charm List'!$B$2:$B$4004
Name CharmDataDesc: '[1]Charm List'!$F$2:$F$4004
Name CharmDataDuration: '[1]Charm List'!$E$2:$E$4004
Name CharmDataEssPreq: '[1]Charm List'!$J$2:$J$4004
Name CharmDataKeyword: '[1]Charm List'!$D$2:$D$4004
Name CharmDataName: '[1]Charm List'!$A$2:$A$4004
Name CharmDataPage: '[1]Charm List'!$G$2:$G$4004
Name CharmDataType: '[1]Charm List'!$C$2:$C$4004
Name CharmSelectionCategory: [2]Charms!$A$3:$A$202
Name CharmSelectionEssence: [2]Charms!$J$3:$J$202
Name CharmSelectionName: [2]Charms!$B$3:$B$202
Name CustomCharmCategory: [2]Data!$R$47:$R$79
Name CustomCharmCategoryDropdown: [1]Data!$R$47:$R$79
Name DataCharmsAll: Solarlist!$B:$M
Name DataCharmsAll: Siderial!$B:$S
Name DataCharmsAllType: Solarlist!$A:$A
Name DataCharmsAllType: Siderial!$A:$A
Name DataSpellHeader: [1]Spells!$B$1:$H$1
Name DataSpellInfo: [1]Spells!$B:$H

Sheet timeline
A1: Event | B1: First Age | C1: Autochthonia | D1: Realm
A2: History begins | B2: 0 | C2: -121 | D2: -4448
A3: Autochthon leaves Creation | B3: 121 | C3: 0 | D3: -4327 | E3: =D3-B3 -> -4448
A4: Start of Time of Cascading Years | B4: 2325 | C4: 2204 | D4: -2123 | E4: =D4-B4 -> -4448
A5: End of Time of Cascading Years | B5: 2543 | C5: 2204 | D5: -1906 | E5: =D5-B5 -> -4449 | H5: что | I5: прошло
A6: The "present" for Dreams of the First Age campaigns | B6: 3516 | D6: -933 | E6: =D6-B6 -> -4449 | G6: 1807 | H6: ДР Ингоша СебКогти | I6: =$B$10-G6 -> 3410
A7: usurpation | B7: =4449+D7 -> 3699 | D7: -750 | G7: 3255 | H7: Левиафан | I7: =$B$10-G7 -> 1962
A8: shogunate | B8: =4449+D8 -> 3749 | D8: -700 | G8: 1 | H8: Чейоп Кеджак | I8: =$B$10-G8 -> 5216
A9: Realm Begins | B9: 4449 | C9: 4110 | D9: 0 | E9: =D9-B9 -> -4449 | I9: =$B$10-G9 -> 5217
A10: Present | B10: 5217 | C10: 4878 | D10: 768 | E10: =D10-B10 -> -4449 | G10: 3475 | I10: =$B$10-G10 -> 1742
I11: =$B$10-G11 -> 5217

Sheet solar tabs
A1: Type | B1: Solar | T1: Type | U1: Solar
A2: Ess. Min | B2: 1 | T2: Ess. Min | U2: (Все)
A4: Названия строк | B4: Количество по полю Name | T4: Aspect Space | U4: Ability | X4: dawn | Y4: zenith | Z4: twilight | AA4: night | AB4: eclipse | AD4: Aspect Space | AE4: Ability
A5: Archery | B5: 7 | T5: dawn | U5: Archery | V5: 1 | W5: dawn | X5: =IF($W5=X$4,COUNTIF($T:$T,$W5),COUNTIF($T:$T,$W5&", "&X$4)+COUNTIF($T:$T,X$4&", "&$W5)) -> 4 | Y5: =IF($W5=Y$4,COUNTIF($T:$T,$W5),COUNTIF($T:$T,$W5&", "&Y$4)+COUNTIF($T:$T,Y$4&", "&$W5)) -> 2 | Z5: =IF($W5=Z$4,COUNTIF($T:$T,$W5),COUNTIF($T:$T,$W5&", "&Z$4)+COUNTIF($T:$T,Z$4&", "&$W5)) -> 0 | AA5: =IF($W5=AA$4,COUNTIF($T:$T,$W5),COUNTIF($T:$T,$W5&", "&AA$4)+COUNTIF($T:$T,AA$4&", "&$W5)) -> 2 | AB5: =IF($W5=AB$4,COUNTIF($T:$T,$W5),COUNTIF($T:$T,$W5&", "&AB$4)+COUNTIF($T:$T,AB$4&", "&$W5)) -> 0 | AD5: dawn | AE5: Archery | AF5: 1 | AG5: =CONCATENATE("|",AE6,"|","cfs","|",5,"|","3+2b|") -> |Athletics|cfs|5|3+2b|
A6: 2 | B6: 1 | T6: dawn | U6: Brawl | V6: 2 | W6: zenith | X6: =IF($W6=X$4,COUNTIF($T:$T,$W6),COUNTIF($T:$T,$W6&", "&X$4)+COUNTIF($T:$T,X$4&", "&$W6)) -> 2 | Y6: =IF($W6=Y$4,COUNTIF($T:$T,$W6),COUNTIF($T:$T,$W6&", "&Y$4)+COUNTIF($T:$T,Y$4&", "&$W6)) -> 2 | Z6: =IF($W6=Z$4,COUNTIF($T:$T,$W6),COUNTIF($T:$T,$W6&", "&Z$4)+COUNTIF($T:$T,Z$4&", "&$W6)) -> 2 | AA6: =IF($W6=AA$4,COUNTIF($T:$T,$W6),COUNTIF($T:$T,$W6&", "&AA$4)+COUNTIF($T:$T,AA$4&", "&$W6)) -> 1 | AB6: =IF($W6=AB$4,COUNTIF($T:$T,$W6),COUNTIF($T:$T,$W6&", "&AB$4)+COUNTIF($T:$T,AB$4&", "&$W6)) -> 1 | AD6: zenith, night | AE6: Athletics | AF6: 13 | AG6: =CONCATENATE("|",AE7,"|","cfs","|",5,"|","3+2b|") -> |Awareness|cfs|5|3+2b|
A7: Wise Arrow | B7: 1 | T7: dawn | U7: Melee | V7: 3 | W7: twilight | X7: =IF($W7=X$4,COUNTIF($T:$T,$W7),COUNTIF($T:$T,$W7&", "&X$4)+COUNTIF($T:$T,X$4&", "&$W7)) -> 0 | Y7: =IF($W7=Y$4,COUNTIF($T:$T,$W7),COUNTIF($T:$T,$W7&", "&Y$4)+COUNTIF($T:$T,Y$4&", "&$W7)) -> 2 | Z7: =IF($W7=Z$4,COUNTIF($T:$T,$W7),COUNTIF($T:$T,$W7&", "&Z$4)+COUNTIF($T:$T,Z$4&", "&$W7)) -> 2 | AA7: =IF($W7=AA$4,COUNTIF($T:$T,$W7),COUNTIF($T:$T,$W7&", "&AA$4)+COUNTIF($T:$T,AA$4&", "&$W7)) -> 1 | AB7: =IF($W7=AB$4,COUNTIF($T:$T,$W7),COUNTIF($T:$T,$W7&", "&AB$4)+COUNTIF($T:$T,AB$4&", "&$W7)) -> 3 | AD7: dawn, night | AE7: Awareness | AF7: 7 | AG7: =CONCATENATE("|",AE8,"|","cfs","|",5,"|","3+2b|") -> |Brawl|cfs|5|3+2b|
A8: 3 | B8: 3 | T8: dawn | U8: Thrown | V8: 4 | W8: night | X8: =IF($W8=X$4,COUNTIF($T:$T,$W8),COUNTIF($T:$T,$W8&", "&X$4)+COUNTIF($T:$T,X$4&", "&$W8)) -> 2 | Y8: =IF($W8=Y$4,COUNTIF($T:$T,$W8),COUNTIF($T:$T,$W8&", "&Y$4)+COUNTIF($T:$T,Y$4&", "&$W8)) -> 1 | Z8: =IF($W8=Z$4,COUNTIF($T:$T,$W8),COUNTIF($T:$T,$W8&", "&Z$4)+COUNTIF($T:$T,Z$4&", "&$W8)) -> 1 | AA8: =IF($W8=AA$4,COUNTIF($T:$T,$W8),COUNTIF($T:$T,$W8&", "&AA$4)+COUNTIF($T:$T,AA$4&", "&$W8)) -> 1 | AB8: =IF($W8=AB$4,COUNTIF($T:$T,$W8),COUNTIF($T:$T,$W8&", "&AB$4)+COUNTIF($T:$T,AB$4&", "&$W8)) -> 3 | AD8: dawn | AE8: Brawl | AF8: 2 | AG8: =CONCATENATE("|",AE9,"|","cfs","|",5,"|","3+2b|") -> |Bureaucr.|cfs|5|3+2b|
A9: Phantom Arrow Technique | B9: 1 | T9: dawn, zenith | U9: Resistan. | V9: 5 | W9: eclipse | X9: =IF($W9=X$4,COUNTIF($T:$T,$W9),COUNTIF($T:$T,$W9&", "&X$4)+COUNTIF($T:$T,X$4&", "&$W9)) -> 0 | Y9: =IF($W9=Y$4,COUNTIF($T:$T,$W9),COUNTIF($T:$T,$W9&", "&Y$4)+COUNTIF($T:$T,Y$4&", "&$W9)) -> 1 | Z9: =IF($W9=Z$4,COUNTIF($T:$T,$W9),COUNTIF($T:$T,$W9&", "&Z$4)+COUNTIF($T:$T,Z$4&", "&$W9)) -> 3 | AA9: =IF($W9=AA$4,COUNTIF($T:$T,$W9),COUNTIF($T:$T,$W9&", "&AA$4)+COUNTIF($T:$T,AA$4&", "&$W9)) -> 3 | AB9: =IF($W9=AB$4,COUNTIF($T:$T,$W9),COUNTIF($T:$T,$W9&", "&AB$4)+COUNTIF($T:$T,AB$4&", "&$W9)) -> 1 | AD9: twilight, eclipse | AE9: Bureaucr. | AF9: 17 | AG9: =CONCATENATE("|",AE10,"|","cfs","|",5,"|","3+2b|") -> |Craft|cfs|5|3+2b|
A10: Sight Without Eyes | B10: 1 | T10: dawn, zenith | U10: War | V10: 6 | AD10: twilight | AE10: Craft | AF10: 15 | AG10: =CONCATENATE("|",AE11,"|","cfs","|",5,"|","3+2b|") -> |Dodge|cfs|5|3+2b|
A11: Trance of Unhesitating Speed | B11: 1 | T11: dawn, night | U11: Awareness | V11: 7 | AD11: dawn, night | AE11: Dodge | AF11: 8 | AG11: =CONCATENATE("|",AE12,"|","cfs","|",5,"|","3+2b|") -> |Integrity|cfs|5|3+2b|
A12: 4 | B12: 3 | T12: dawn, night | U12: Dodge | V12: 8 | AD12: zenith, twilight | AE12: Integrity | AF12: 11 | AG12: =CONCATENATE("|",AE13,"|","cfs","|",5,"|","3+2b|") -> |Investig.|cfs|5|3+2b|
A13: Blood Without Balance | B13: 1 | T13: zenith | U13: Perform. | V13: 9 | AD13: twilight, night | AE13: Investig. | AF13: 20 | AG13: =CONCATENATE("|",AE14,"|","cfs","|",5,"|","3+2b|") -> |Larceny|cfs|5|3+2b|
A14: Fiery Arrow Attack | B14: 1 | T14: zenith | U14: Survival | V14: 10 | AD14: night, eclipse | AE14: Larceny | AF14: 22 | AG14: =CONCATENATE("|",AE15,"|","cfs","|",5,"|","3+2b|") -> |Linguistics|cfs|5|3+2b|
A15: Force Without Fire | B15: 1 | T15: zenith, twilight | U15: Integrity | V15: 11 | AD15: twilight, eclipse | AE15: Linguistics | AF15: 18 | AG15: =CONCATENATE("|",AE16,"|","cfs","|",5,"|","3+2b|") -> |Lore|cfs|5|3+2b|
A16: Athletics | B16: 12 | T16: zenith, twilight | U16: Lore | V16: 12 | AD16: zenith, twilight | AE16: Lore | AF16: 12 | AG16: =CONCATENATE("|",AE17,"|","cfs","|",5,"|","3+2b|") -> |Martial Arts|cfs|5|3+2b|
A17: 1 | B17: 1 | T17: zenith, night | U17: Athletics | V17: 13 | AD17: - | AE17: Martial Arts | AF17: 26 | AG17: =CONCATENATE("|",AE18,"|","cfs","|",5,"|","3+2b|") -> |Medicine|cfs|5|3+2b|
A18: Graceful Crane Stance | B18: 1 | T18: zenith, eclipse | U18: Presence | V18: 14 | AD18: twilight | AE18: Medicine | AF18: 16 | AG18: =CONCATENATE("|",AE19,"|","cfs","|",5,"|","3+2b|") -> |Melee|cfs|5|3+2b|
A19: 2 | B19: 2 | T19: twilight | U19: Craft | V19: 15 | AD19: dawn | AE19: Melee | AF19: 3 | AG19: =CONCATENATE("|",AE20,"|","cfs","|",5,"|","3+2b|") -> |Occult|cfs|5|3+2b|
A20: Foe-Vaulting Method | B20: 1 | T20: twilight | U20: Medicine | V20: 16 | AD20: twilight, eclipse | AE20: Occult | AF20: 19 | AG20: =CONCATENATE("|",AE21,"|","cfs","|",5,"|","3+2b|") -> |Perform.|cfs|5|3+2b|
A21: Monkey Leap Technique | B21: 1 | T21: twilight, eclipse | U21: Bureaucr. | V21: 17 | AD21: zenith | AE21: Perform. | AF21: 9 | AG21: =CONCATENATE("|",AE22,"|","cfs","|",5,"|","3+2b|") -> |Presence|cfs|5|3+2b|
A22: 3 | B22: 5 | T22: twilight, eclipse | U22: Linguistics | V22: 18 | AD22: zenith, eclipse | AE22: Presence | AF22: 14 | AG22: =CONCATENATE("|",AE23,"|","cfs","|",5,"|","3+2b|") -> |Resistan.|cfs|5|3+2b|
A23: Feather Foot Style | B23: 1 | T23: twilight, eclipse | U23: Occult | V23: 19 | AD23: dawn, zenith | AE23: Resistan. | AF23: 5 | AG23: =CONCATENATE("|",AE24,"|","cfs","|",5,"|","3+2b|") -> |Ride|cfs|5|3+2b|
A24: Increasing Strength Exercise | B24: 1 | T24: twilight, night | U24: Investig. | V24: 20 | AD24: night, eclipse | AE24: Ride | AF24: 23 | AG24: =CONCATENATE("|",AE25,"|","cfs","|",5,"|","3+2b|") -> |Sail|cfs|5|3+2b|
A25: Lightning Speed | B25: 1 | T25: night | U25: Stealth | V25: 21 | AD25: eclipse | AE25: Sail | AF25: 25 | AG25: =CONCATENATE("|",AE26,"|","cfs","|",5,"|","3+2b|") -> |Socialize|cfs|5|3+2b|
A26: Soaring Crane Leap | B26: 1 | T26: night, eclipse | U26: Larceny | V26: 22 | AD26: night, eclipse | AE26: Socialize | AF26: 24 | AG26: =CONCATENATE("|",AE27,"|","cfs","|",5,"|","3+2b|") -> |Stealth|cfs|5|3+2b|
A27: Thunderbolt Attack Prana | B27: 1 | T27: night, eclipse | U27: Ride | V27: 23 | AD27: night | AE27: Stealth | AF27: 21 | AG27: =CONCATENATE("|",AE28,"|","cfs","|",5,"|","3+2b|") -> |Survival|cfs|5|3+2b|
A28: 4 | B28: 3 | T28: night, eclipse | U28: Socialize | V28: 24 | AD28: zenith | AE28: Survival | AF28: 10 | AG28: =CONCATENATE("|",AE29,"|","cfs","|",5,"|","3+2b|") -> |Thrown|cfs|5|3+2b|
A29: Spider Foot Style | B29: 1 | T29: eclipse | U29: Sail | V29: 25 | AD29: dawn | AE29: Thrown | AF29: 4 | AG29: =CONCATENATE("|",AE30,"|","cfs","|",5,"|","3+2b|") -> |War|cfs|5|3+2b|
A30: Strength-Hying Heave | B30: 1 | T30: Общий итог | AD30: dawn, zenith | AE30: War | AF30: 6 | AG30: =CONCATENATE("|",AE31,"|","cfs","|",5,"|","3+2b|") -> ||cfs|5|3+2b|
A31: Winning Stride Discipline | B31: 1
A32: 5 | B32: 1
A33: Ten Ox Meditation | B33: 1
A34: Awareness | B34: 11
A35: 2 | B35: 1
A36: Sensory Acuity Prana | B36: 1
A37: 3 | B37: 7
A38: Eyeless Harbinger Awareness | B38: 1
A39: Genius Palate Summation | B39: 1
A40: Keen Hearing and Touch Technique | B40: 1
A41: Keen Sight Technique | B41: 1
A42: Keen Taste and Smell Technique | B42: 1
A43: Studied Ear Espial | B43: 1
A44: Surprise Anticipation Method | B44: 1
A45: 4 | B45: 3
A46: Awakening Eye | B46: 1
A47: Foe-Scenting Method | B47: 1
A48: Unswerving Eye Method | B48: 1
A49: Brawl | B49: 12
A50: 1 | B50: 1
A51: Fists of Iron Technique | B51: 1
A52: 3 | B52: 6
A53: Ferocious Jab | B53: 1
A54: Heaven Thunder Hammer | B54: 1
A55: Iron Battle Focus | B55: 1
A56: Thunderclap Rush Attack | B56: 1
A57: Unbreakable Grasp | B57: 1
A58: Vicious Lunge | B58: 1
A59: 4 | B59: 4
A60: Crashing Wave Throw | B60: 1
A61: Falling Hammer Strike | B61: 1
A62: Swift Strike Prana | B62: 1
A63: Wind and Stones Defense | B63: 1
A64: 5 | B64: 1
A65: Devil-Strangling Attitude | B65: 1
A66: Bureaucr. | B66: 11
A67: 1 | B67: 2
A68: Deft Official's Way | B68: 1
A69: Frugal Merchant Method | B69: 1
A70: 2 | B70: 1
A71: Measuring Glance | B71: 1
A72: 3 | B72: 3
A73: Consumer-Evaluating Glance | B73: 1
A74: Enlightened Discourse Method | B74: 1
A75: Insightful Buyer Technique | B75: 1
A76: 4 | B76: 2
A77: All-Seeing Master Procurer | B77: 1
A78: Enigmatic Bureau Understanding | B78: 1
A79: 5 | B79: 3
A80: Bureau-Rectifying Method | B80: 1
A81: Illimitable Master Fence | B81: 1
A82: Speed the Wheels | B82: 1
A83: Craft | B83: 18
A84: 1 | B84: 1
A85: Flawless Handiwork Method | B85: 1
A86: 2 | B86: 2
A87: Tireless Workhorse Method | B87: 1
A88: Triumph-Forging Eye | B88: 1
A89: 3 | B89: 7
A90: Brass Scales Falling | B90: 1
A91: Brass Scales Falling x2 | B91: 1
A92: Crack-Mending Technique | B92: 1
A93: Craftsman Needs No Tools | B93: 1
A94: Efficient Craftsman Technique | B94: 1
A95: Flawless Handiwork Method x2 | B95: 1
A96: Supreme Masterwork Focus | B96: 1
A97: 4 | B97: 2
A98: Arete-Shifting Prana | B98: 1
A99: Red Anvils Ringing | B99: 1
A100: 5 | B100: 6
A101: Blood Diamond Sweat | B101: 1
...

Sheet Solarlist
A1: Type | B1: Name | C1: Cost | D1: Type | E1: Keywords | F1: Duration | G1: Description | H1: Page # | I1: Ability | J1: Abil. Min | K1: Ess. Min | L1: Aspect Space | M1: Prerequisites | N1: Prereq Spec. | P1: w
A2: Solar | B2: Wise Arrow | C2: 1m | D2: Supplemental | E2: Uniform | F2: Instant | G2: Reduce cover by -1, including no cover. After aiming, can hit around full cover, at only +3 defense. | H2: 255 | I2: Archery | J2: 2 | K2: 1 | L2: dawn
A3: Solar | B3: Trance of Unhesitating Speed | C3: 4m, 1wp | D3: Simple | E3: Decisive-only | F3: Instant | G3: Spread init over many attacks, on single or multiple targets. Each 10 on attack gives +1 base damage. Doesn't need to aim. | H3: 256 | I3: Archery | J3: 3 | K3: 1 | L3: dawn | M3: Wise Arrow
A4: Solar | B4: Phantom Arrow Technique | C4: 1m | D4: Reflexive | E4: None | F4: Instant | G4: Fire without ammo. Imbue ammo with an intimacy. At 3ess, arrows are stuck. | H4: 257 | I4: Archery | J4: 3 | K4: 1 | L4: dawn
A5: Solar | B5: Blood Without Balance | C5: 3m | D5: Reflexive | E5: Decisive-only | F5: Instant | G5: After gaining the benefit of a distract gambit and if your new initiative allows you to act immediately, you may fire up to long range without aiming. If <7 initiative, +ess dice base damage. | H5: 256 | I5: Archery | J5: 4 | K5: 1 | L5: dawn | M5: Sight Without Eyes
A6: Solar | B6: Force Without Fire | C6: 3m | D6: Supplemental | E6: Withering-Only | F6: Instant | G6: If damge is at least as much as the target's stamina, don't gain initiative, but target is knocked down and back 1 range band. Can end a rush. | H6: 256 | I6: Archery | J6: 4 | K6: 1 | L6: dawn | M6: Sight Without Eyes
A7: Solar | B7: Fiery Arrow Attack | C7: 2m | D7: Supplemental | E7: Decisive-only | F7: Instant | G7: Set ammo on fire, gives +1 succ to damage. If it does at least 3HL, target is on fire. | H7: 257 | I7: Archery | J7: 4 | K7: 1 | L7: dawn | M7: Phantom Arrow Technique
A8: Solar | B8: Hanging Judgment Arc | C8: 6m | D8: Reflexive | E8: Decisive-only | F8: Instant | H8: MotSE 5 | I8: Archery | J8: 4 | K8: 2 | L8: dawn | M8: Fiery Arrow Attack
A9: Solar | B9: There Is No Wind | C9: 3m | D9: Reflexive | E9: Dual | F9: Instant | G9: Ignore non-visual penalties. Wither accuracy is set to short range. With Awarenesss, can attack from extreme long range. | H9: 257 | I9: Archery | J9: 5 | K9: 2 | L9: dawn | M9: Sight Without Eyes
A10: Solar | B10: Accuracy Without Distance | C10: 1m, 1wp | D10: Reflexive | E10: Decisive-only | F10: Instant | G10: Aim instantly, the +3 bonus is converted into non-charm succ. | H10: 257 | I10: Archery | J10: 5 | K10: 2 | L10: dawn | M10: Force Without Fire
A11: Solar | B11: Arrow Storm Technique | C11: 5m, 1wp | D11: Simple | E11: Decisive-only | F11: Instant | G11: Hit 3x ess targets within medium range of target. | H11: 257 | I11: Archery | J11: 5 | K11: 2 | L11: dawn | M11: Trance of Unhesitating Speed
A12: Solar | B12: Flashing Vengeance Draw | C12: 3m | D12: Supplemental | E12: None | F12: Instant | G12: Add ess succ to Join Battle, if attacking before target, it's unblockable. | H12: 258 | I12: Archery | J12: 5 | K12: 2 | L12: dawn | M12: Trance of Unhesitating Speed
A13: Solar | B13: Hunter's Swift Answer | C13: 5m, 1wp | D13: Reflexive | E13: Uniform | F13: Instant | G13: Extra short or close ranged attack if win a disengage. | H13: 258 | I13: Archery | J13: 5 | K13: 2 | L13: dawn | M13: Flashing Vengeance Draw
A14: Solar | B14: Dazzling Flare Attack | C14: 3m | D14: Reflexive | E14: Decisive-only | F14: Instant | G14: Strengthens ammo from FAA. Creates a bright flare, disrupting shadow cover. | H14: 258 | I14: Archery | J14: 5 | K14: 2 | L14: dawn | M14: Fiery Arrow Attack
A15: Solar | B15: Seven Omens Shot | C15: 3m, 1wp | D15: Simple | E15: Decisive-only | F15: Instant | G15: Aim for 3 rounds to convert the +3 into non-charm succ and extra succ add to raw damage. AWD shortens it by 1 round. Killing gives 1 WP. | H15: 258 | I15: Archery | J15: 5 | K15: 3 | L15: dawn | M15: Accuracy Without Distance
A16: Solar | B16: Revolving Bow Discipline | C16: 6m, 1wp | D16: Simple | E16: Perilous, Withering-Only | F16: Instant | G16: Keeping hitting the same target within short range, until you miss or they crash. | H16: 259 | I16: Archery | J16: 5 | K16: 3 | L16: dawn | M16: Arrow Storm Technique
A17: Solar | B17: Finishing Snipe | C17: 7m | D17: Reflexive | E17: Decisive-only | F17: Instant | G17: Free attack on someone within range if they crash. | H17: 259 | I17: Archery | J17: 5 | K17: 3 | L17: dawn | M17: Hunter's Swift Answer
A18: Solar | B18: Rain of Feathered Death | C18: 3m/copy, 1wp | D18: Simple | E18: Decisive-only | F18: Instant | G18: Make (Dex) hits against a target. | H18: 259 | I18: Archery | J18: 5 | K18: 3 | L18: dawn | M18: Phantom Arrow Technique
A19: Solar | B19: Shadow-Seeking Arrow | C19: 3m, 2i | D19: Reflexive | E19: Uniform | F19: Instant | G19: Free attack when spotting someone, without needing to aim. | H19: 259 | I19: Archery | J19: 5 | K19: 3 | L19: dawn | M19: Dazzling Flare Attack
A20: Solar | B20: Searing Sunfire Interdiction | C20: 4m, 1i, 1wp | D20: Simple | E20: Decisive-only | F20: Instant | G20: Diff 3 gambit without needing to aim. Forces target to delay their turn. Rebuy for lots of extra stuff. | H20: 259 | I20: Archery | J20: 5 | K20: 3 | L20: dawn | M20: Dazzling Flare Attack
... A23: Solar | B23: Heart-Eating Incineration | C23: 3m, 3a | D23: Reflexive | E23: Decisive-only | F23: Instant | G23: When using SS and anima is at bonfire, fires anima to add initiative to SS's raw damage. | H23: 260 | I23: Archery | J23: 5 | K23: 3 | L23: dawn | M23: Solar Spike
A24: Solar | B24: Nova Arrow Attack | C24: 6m, 1wp | D24: Simple | E24: Decisive-only | F24: Instant | H24: MotSE 6 | I24: Archery | J24: 5 | K24: 3 | L24: dawn | M24: Dazzling Flare Attack
A25: Solar | B25: Searing Sunfire Interdiction x3 | C25: 4m, 1i, 1wp | D25: Simple | E25: Decisive-only | F25: Instant | G25: Resets attack if you drop target from high Init to lower | H25: 259 | I25: Archery | J25: 5 | K25: 4 | L25: dawn | M25: Searing Sunfire Interdiction x2
A26: Solar | B26: Dust and Ash Sleight | C26: 3m | D26: Reflexive | E26: Decisive-only | F26: Instant | G26: Shortens the aim action of SOS by 1 round, giving up the non charm successes. Rebuy to gain the succ again. | H26: 260 | I26: Archery | J26: 5 | K26: 4 | L26: dawn | M26: Seven Omens Shot
A27: Solar | B27: Heavens Crash Down | C27: 6m, 2i, 1wp | D27: Reflexive | E27: Clash, Perilous, Withering-Only | F27: Instant | G27: If in -4 HLs, may clash within short range. Gains ess succ and damage roll uses double 9s. Rebuy to use while crashed. | H27: 260 | I27: Archery | J27: 5 | K27: 4 | L27: dawn | M27: Revolving Bow Discipline
A28: Solar | B28: Hell-Heeling Arrow | C28: 13m, 1wp | D28: Simple | E28: Decisive-only | F28: Instant | H28: MotSE 6 | I28: Archery | J28: 5 | K28: 4 | L28: dawn | M28: Nova Arrow Attack, Searing Sunfire Interdiction
A29: Solar | B29: Accuracy Without Distance x2 | C29: 1m, 1wp | D29: Reflexive | E29: Dual | F29: Instant | G29: Can use with withering on a crashed target. Roll damage even if no succ. | H29: 257 | I29: Archery | J29: 5 | K29: 5 | L29: dawn | M29: Accuracy Without Distance
A30: Solar | B30: Searing Sunfire Interdiction x4 | C30: 4m, 1i, 1wp | D30: Simple | E30: Decisive-only | F30: Instant | G30: Can use twice consecutively on the same target, no wp cost on 2nd shot. | H30: 259 | I30: Archery | J30: 5 | K30: 5 | L30: dawn | M30: Searing Sunfire Interdiction x3
A31: Solar | B31: Dust and Ash Sleight x2 | C31: 3m | D31: Reflexive | E31: Decisive-only | F31: Instant | G31: Adds back loss succ to the attack. | H31: 260 | I31: Archery | J31: 5 | K31: 5 | L31: dawn | M31: Dust and Ash Sleight
A32: Solar | B32: Heavens Crash Down x2 | C32: 6m, 2i, 1wp | D32: Reflexive | E32: Clash, Withering-Only | F32: Instant | G32: Can spend 2i cost even when crashed going into further negatives. | H32: 260 | I32: Archery | J32: 5 | K32: 5 | L32: dawn | M32: Heavens Crash Down
A33: Solar | B33: Whispered Prayer of Judgment | C33: 1m | D33: Supplemental | E33: Uniform | F33: Instant | G33: After aiming, add ess damage to the attack. | H33: 261 | I33: Archery | J33: 5 | K33: 5 | L33: dawn | M33: Streaming Arrow Stance
A34: Solar | B34: Solar Judgment Flare | C34: 3m, 1wp and 1m/die | D34: Simple | E34: Decisive-only | F34: Instant | H34: MotSE 6 | I34: Archery | J34: 5 | K34: 5 | L34: dawn | M34: Heart-Eating Incineration, Nova Arrow Attack
A35: Solar | B35: Searing Sunfire Interdiction x5 | C35: 4m, 1i, 1wp | D35: Simple | E35: Decisive-only | F35: Instant | G35: Can use repeatedly on same target if you keep hitting. Ends with miss or when target loses a turn. Gain 1wp if target loses turn. | H35: 259 | I35: Archery | J35: 5 | K35: 6 | L35: dawn | M35: Searing Sunfire Interdiction x4
A36: Solar | B36: Searing Sunfire Interdiction x6 | C36: 4m, 1i, 1wp | D36: Simple | E36: Decisive-only | F36: Instant | G36: Can target new opponent if you drop someone to tick 0 or lower. | H36: 259 | I36: Archery | J36: 5 | K36: 6 | L36: dawn | M36: Searing Sunfire Interdiction x5
A37: Solar | B37: Sight Without Eyes | C37: 1m | D37: Reflexive | E37: None | F37: One Tick | G37: Can fire without penalty due to visual conditions. at 3ess can see through cover. | H37: 255 | I37: Archery | J37: 3 | K37: 1 | L37: dawn | M37: Wise Arrow
A38: Solar | B38: Immaculate Golden Bow | C38: 5m, 1wp | D38: Simple | E38: None | F38: Scene | G38: Create a glowing powerbow from essence. 4m to make heavy cover. Rebuy for evocations. | H38: 258 | I38: Archery | J38: 4 | K38: 2 | L38: dawn | M38: Phantom Arrow Technique
A39: Solar | B39: Streaming Arrow Stance | C39: 6m | D39: Simple | E39: None | F39: Scene | G39: Can shoot a crashed target at medium or long range without aiming. | H39: 260 | I39: Archery | J39: 5 | K39: 4 | L39: dawn | M39: Finishing Snipe
A40: Solar | B40: Dedicated Unerring Ear | C40: 3m/exchange | D40: Reflexive | E40: None | F40: Indefinite | G40: Hear anyone on your plane talking to you. One-way only. | H40: 273 | I40: Awareness | J40: 5 | K40: 4 | L40: dawn, night | M40: Unsurpassed Hearing and Touch Discipline
A41: Solar | B41: Surprise Anticipation Method | C41: - | D41: Reflexive | E41: None | F41: Instant | G41: Every 9 gives 1m, 10 gives 2m for Awarenesss charms, can lower cost retroactively. Also can use Awarenesss charms in sleep. | H41: 267 | I41: Awareness | J41: 3 | K41: 1 | L41: dawn, night | M41: Sensory Acuity Prana
A42: Solar | B42: Genius Palate Summation | C42: 2m | D42: Simple | E42: None | F42: Instant | G42: Autowin read intentions on chef when they made your food. | H42: 269 | I42: Awareness | J42: 3 | K42: 1 | L42: dawn, night | M42: Keen Taste and Smell Technique
A43: Solar | B43: Studied Ear Espial | C43: 1m | D43: Reflexive | E43: None | F43: Instant | G43: When someone moves in stealth +3dice to spot them. | H43: 269 | I43: Awareness | J43: 3 | K43: 1 | L43: dawn, night | M43: Keen Hearing and Touch Technique
A44: Solar | B44: Unswerving Eye Method | C44: 3m | D44: Reflexive | E44: None | F44: Instant | G44: Against stealth, stealing or cheating, -ess of enemy's double successses after they've rolled. | H44: 267 | I44: Awareness | J44: 4 | K44: 1 | L44: dawn, night | M44: Keen Sight Technique
A45: Solar | B45: Foe-Scenting Method | C45: 0m or 2m | D45: Reflexive | E45: None | F45: Instant | G45: Smell how many people are within medium range. Can tell type of creature. | H45: 269 | I45: Awareness | J45: 4 | K45: 1 | L45: dawn, night | M45: Keen Taste and Smell Technique
A46: Solar | B46: Awakening Eye | C46: 5m, 1wp | D46: Supplemental | E46: None | F46: Instant | G46: For Join Battle, add free full excellency and cascading 10s reroll. Each non-succ that became a succ adds +1succ to be used on Awarenesss in this scene. | H46: 270 | I46: Awareness | J46: 4 | K46: 1 | L46: dawn, night
A47: Solar | B47: Knowing Beyond Silence | C47: 2m | D47: Reflexive | E47: None | F47: Instant | G47: Against stealth, enemy's 1s are 10s to you, and their 2s are 9s after they rolled. | H47: 270 | I47: Awareness | J47: 4 | K47: 2 | L47: dawn, night | M47: Studied Ear Espial
A48: Solar | B48: Inner Eye Focus | C48: 4m | D48: Reflexive | E48: None | F48: Instant | G48: Against stealth or larceny, reroll ess non-successes cascading. | H48: 270 | I48: Awareness | J48: 5 | K48: 2 | L48: dawn, night | M48: Unswerving Eye Method
A49: Solar | B49: Scent-Honing Prana | C49: 3m | D49: Reflexive | E49: None | F49: Instant | G49: When detecting intimacies, add +1 succ for minor, +2 for major and +3 for defining. | H49: 270 | I49: Awareness | J49: 5 | K49: 2 | L49: dawn, night | M49: Foe-Scenting Method
A50: Solar | B50: Roused Dragon Detection | C50: 1m, 1wp | D50: Reflexive | E50: None | F50: Instant | G50: Hit hidden enemy within range, forces them to move to a new hiding place. | H50: 271 | I50: Awareness | J50: 5 | K50: 2 | L50: dawn, night | M50: Knowing Beyond Silence, Living Pulse Perception
A51: Solar | B51: Blink | C51: 1wp | D51: Reflexive | E51: None | F51: Instant | G51: Reroll any Awarenesss roll, keeping charm effects and allowing new ones. | H51: 271 | I51: Awareness | J51: 5 | K51: 3 | L51: dawn, night | M51: Inner Eye Focus
A52: Solar | B52: Eye of the Unconquered Sun | C52: 10m, 1wp | D52: Simple | E52: None | F52: One Turn | G52: I CAN SEE FOREVER. | H52: 273 | I52: Awareness | J52: 5 | K52: 4 | L52: dawn, night
A53: Solar | B53: Living Pulse Perception | C53: - | D53: Permanent | E53: None | F53: Permanent | G53: Add +1 succ against hidden character within an enclosed space. | H53: 271 | I53: Awareness | J53: 4 | K53: 2 | L53: dawn, night | M53: Eyeless Harbinger Awareness
A54: Solar | B54: Unsurpassed Sight Discipline | C54: - | D54: Permanent | E54: None | F54: Permanent | G54: Any sight-based charm costs 1m less, minimum 1m. | H54: 271 | I54: Awareness | J54: 5 | K54: 3 | L54: dawn, night | M54: Keen Sight Technique
A55: Solar | B55: Unsurpassed Taste and Smell Discipline | C55: - | D55: Permanent | E55: None | F55: Permanent | G55: Autowin read intention to smell mood. Expand library and index. Smell bleeding characters. | H55: 271 | I55: Awareness | J55: 5 | K55: 3 | L55: dawn, night | M55: Keen Taste and Smell Technique
A56: Solar | B56: Unsurpassed Hearing and Touch Discipline | C56: - | D56: Permanent | E56: None | F56: Permanent | G56: Hear loud noises up to 5x ess miles. Also extra techniques. | H56: 272 | I56: Awareness | J56: 5 | K56: 3 | L56: dawn, night | M56: Keen Hearing and Touch Technique
A57: Solar | B57: Sensory Acuity Prana | C57: 5m | D57: Reflexive | E57: None | F57: Scene | G57: Double 9s, if using Unsurpassed (Sense) Discipline, reroll recurring 6s. | H57: 267 | I57: Awareness | J57: 2 | K57: 1 | L57: dawn, night
A58: Solar | B58: Keen Sight Technique | C58: 3m or 6m, 1wp | D58: Simple | E58: None | F58: Scene | G58: Diff 2 or 3 sight actions don't need a roll. +2 dice to notice hidden things. See clearly in dim light. -1 to fog. | H58: 267 | I58: Awareness | J58: 3 | K58: 1 | L58: dawn, night | M58: Sensory Acuity Prana
A59: Solar | B59: Keen Taste and Smell Technique | C59: 3m or 6m, 1wp | D59: Simple | E59: None | F59: Scene | G59: Add scent library and taste index. | H59: 268 | I59: Awareness | J59: 3 | K59: 1 | L59: dawn, night | M59: Sensory Acuity Prana
A60: Solar | B60: Keen Hearing and Touch Technique | C60: 3m or 6m, 1wp | D60: Simple | E60: None | F60: Scene | G60: Diff 2 sound or touch actions don't need a roll. -1 to harder actions, +1 succ. | H60: 269 | I60: Awareness | J60: 3 | K60: 1 | L60: dawn, night | M60: Sensory Acuity Prana
A61: Solar | B61: Eyeless Harbinger Awareness | C61: 3m | D61: Reflexive | E61: None | F61: Scene | G61: If stealthed character moves within short range on surface touching you, -2 to their roll. | H61: 269 | I61: Awareness | J61: 3 | K61: 1 | L61: dawn, night | M61: Keen Hearing and Touch Technique
A62: Solar | B62: Drifting Leaf Elusion | C62: 1m | D62: Reflexive | E62: None | F62: Instant | G62: Your Evasion wins ties, rather than losing them. | H62: 300 | I62: Dodge | J62: 2 | K62: 1 | L62: dawn, night
A63: Solar | B63: Reed in the Wind | C63: 2i/1 Evasion | D63: Reflexive | E63: Perilous | F63: Instant | G63: Spend Initiative to raise Dodge, breaking the cap. | H63: 299 | I63: Dodge | J63: 3 | K63: 1 | L63: dawn, night
A64: Solar | B64: Reflex Sidestep Technique | C64: 5m | D64: Reflexive | E64: Uniform | F64: Instant | G64: Have Evasion 2+ when ambushed. | H64: 299 | I64: Dodge | J64: 3 | K64: 1 | L64: dawn, night | M64: Reed in the Wind
A65: Solar | B65: Leaping Dodge Method | C65: 1m, 2i | D65: Reflexive | E65: None | F65: Instant | G65: After dodging an effect, move one range band. | H65: 300 | I65: Dodge | J65: 3 | K65: 1 | L65: dawn, night | M65: Reflex Sidestep Technique
A66: Solar | B66: Shadow Over Water | C66: 2m | D66: Reflexive | E66: None | F66: Instant | G66: Remove any penalties to Evasion. | H66: 300 | I66: Dodge | J66: 3 | K66: 1 | L66: dawn, night | M66: Drifting Leaf Elusion
A67: Solar | B67: Dust Motes Whirling | C67: 2m | D67: Supplemental | E67: None | F67: Instant | G67: Disengage with double-9s. | H67: 299 | I67: Dodge | J67: 4 | K67: 1 | L67: dawn, night | M67: Reed in the Wind
A68: Solar | B68: Fleet Dreaming Image | C68: 5m | D68: Reflexive | E68: None | F68: Instant | G68: Disengage while at short range, rather than close. | H68: 300 | I68: Dodge | J68: 5 | K68: 2 | L68: dawn, night | M68: Dust Motes Whirling
A69: Solar | B69: Seven Shadow Evasion | C69: 4m, 1wp | D69: Reflexive | E69: Uniform | F69: Instant | G69: Perfectly dodge any attack. | H69: 300 | I69: Dodge | J69: 5 | K69: 2 | L69: dawn, night | M69: Force-Stealing Feint
A70: Solar | B70: Safety Between Heartbeats | C70: 5m | D70: Reflexive | E70: None | F70: Instant | G70: Opponent loses 1i for each 1 rolled on the attack. | H70: 301 | I70: Dodge | J70: 5 | K70: 2 | L70: dawn, night | M70: Force-Stealing Feint
A71: Solar | B71: Rumor of Form | C71: 3m/-1 | D71: Reflexive | E71: None | F71: Instant | G71: Convert enemy 1s into -1 successes. | H71: 301 | I71: Dodge | J71: 5 | K71: 2 | L71: dawn, night | M71: Shadow Over Water
A72: Solar | B72: Vaporous Division | C72: 4m/damage removed | D72: Reflexive | E72: Decisive-only | F72: Instant | G72: Cancel damage at 4m/success. | H72: 302 | I72: Dodge | J72: 5 | K72: 2 | L72: dawn, night | M72: Rumor of Form
A73: Solar | B73: Sunlight Bleeding Away | C73: 4m, 1wp | D73: Reflexive | E73: None | F73: Instant | G73: Retreat twice after disengaging instead of once. | H73: 302 | I73: Dodge | J73: 5 | K73: 3 | L73: dawn, night | M73: Fleet Dreaming Image
A74: Solar | B74: Thousand Steps' Stillness | C74: 5m | D74: Reflexive | E74: None | F74: Instant | G74: On a successful dodge, gain 1i per 1 or 2 enemy rolls. | H74: 302 | I74: Dodge | J74: 5 | K74: 3 | L74: dawn, night | M74: Safety Between Heartbeats
A75: Solar | B75: Refinement of Flowing Shadows | C75: - | D75: Permanent | E75: Perilous | F75: Instant | G75: After using SSE, gain 1i/round until you are struck or move too far away. | H75: 303 | I75: Dodge | J75: 5 | K75: 5 | L75: dawn, night | M75: Seven Shadow Evasion
... A83: Solar | B83: Unbridled Shade Attitude | C83: - | D83: Permanent | E83: None | F83: Permanent | G83: Gain 1i for every -0 health level you lose. | H83: 303 | I83: Dodge | J83: 5 | K83: 3 | L83: dawn, night | M83: Living Bonds Unburdened
A84: Solar | B84: Fourfold Shiver Binding | C84: 4m | D84: Reflexive | E84: None | F84: Scene | G84: ="+1 non-Charm bonus to Evasion for rest of scene." -> +1 non-Charm bonus to Evasion for rest of scene. | H84: 301 | I84: Dodge | J84: 4 | K84: 2 | L84: dawn, night | M84: Drifting Leaf Elusion
A85: Solar | B85: Flow Like Blood | C85: 5m, 1wp | D85: Reflexive | E85: Perilous | F85: Scene | G85: Ignore all Evasion penalties against enemies with lower Initiative. Cut cost of RitW in half. Gain 1i each round you are at close range and not struck. | H85: 301 | I85: Dodge | J85: 4 | K85: 2 | L85: dawn, night | M85: Shadow Over Water
A86: Solar | B86: Hundred Shadow Ways | C86: 6m | D86: Reflexive | E86: Stackable | F86: Scene | G86: Learn an enemy Charm and become immune to its effects. | H86: 302 | I86: Dodge | J86: 5 | K86: 3 | L86: dawn, night | M86: Vaporous Division
A87: Solar | B87: Living Bonds Unburdened | C87: 3m, 3i +1m, 1i/hl | D87: Simple | E87: None | F87: Scene | G87: Create extra -0 health levels; if hit by an attack that only damages these levels, you count as dodging it. | H87: 303 | I87: Dodge | J87: 5 | K87: 3 | L87: dawn, night | M87: Vaporous Division
A88: Solar | B88: Guarded Thoughts Meditation | C88: 4m | D88: Simple | E88: None | F88: Indefinite | G88: Infinite Socialize Mastery; only applies to boosting Guile. | H88: 396 | I88: Socialize | J88: 5 | K88: 2 | L88: night, eclipse | M88: Shadow Over Day
A89: Solar | B89: Penumbra Self Meditation | C89: 3m/Intimacy | D89: Simple | E89: Stackable | F89: Indefinite | G89: Perfectly conceal an Intimacy. | H89: 397 | I89: Socialize | J89: 5 | K89: 2 | L89: night, eclipse | M89: Guarded Thoughts Meditation
A90: Solar | B90: Motive-Discerning Technique | C90: 3m | D90: Supplemental | E90: Mute | F90: Instant | G90: Read intentions with double-9s. | H90: 393 | I90: Socialize | J90: 3 | K90: 1 | L90: night, eclipse
A91: Solar | B91: Shadow Over Day | C91: 1m or 2m | D91: Reflexive | E91: Mute | F91: Instant | G91: 1m for +1 Guile, or 2m for +2 Guile. | H91: 394 | I91: Socialize | J91: 3 | K91: 1 | L91: night, eclipse
A92: Solar | B92: Motive-Discerning Technique x2 | C92: 3m | D92: Supplemental | E92: Mute | F92: Instant | G92: Player can guess at a related Intimacy, if correct character knows it. | H92: 393 | I92: Socialize | J92: 4 | K92: 1 | L92: night, eclipse | M92: Motive-Discerning Technique
A93: Solar | B93: Humble Servant Approach | C93: 1m | D93: Reflexive | E93: None | F93: Instant | G93: After Reading Intentions of the target while he was talking to someone else, he takes -2 Guile when you Read Intentions while he's talking to you. | H93: 394 | I93: Socialize | J93: 4 | K93: 1 | L93: night, eclipse | M93: Motive-Discerning Technique
A94: Solar | B94: Night Passes Over | C94: 2m | D94: Reflexive | E94: None | F94: Instant | G94: Ignore all penalties to Guile, except wound penalties and the penalty for thinking you're alone. | H94: 394 | I94: Socialize | J94: 4 | K94: 1 | L94: night, eclipse | M94: Shadow Over Day
A95: Solar | B95: Ten Calamities Technique | C95: 5m | D95: Supplemental | E95: Dual | F95: Grapple | G95: Choke out enemy in grapple as savaging attack. Add +2 damage per round for wither, or +1 for decisive, ignoring hardness. | H95: 280 | I95: Brawl | J95: 5 | K95: 3 | L95: dawn | M95: Dragon Coil Technique
A96: Solar | B96: Burning Proof of Authority | C96: 4m | D96: Reflexive | E96: None | F96: Indefinite | G96: Release grapple target with 2 rounds left to mark them. Reflexively grapple them again without a roll to continue the rounds left. | H96: 278 | I96: Brawl | J96: 4 | K96: 2 | L96: dawn | M96: Unbreakable Grasp
A97: Solar | B97: Superior Violent Knowledge | C97: 4m | D97: Reflexive | E97: None | F97: Indefinite | G97: At any time, store up to stamina initiative. When making a decisive attack, convert the initiative into raw damage. | H97: 282 | I97: Brawl | J97: 5 | K97: 3 | L97: dawn | M97: Striving Aftershock Method
A98: Solar | B98: Fists of Iron Technique | C98: 1m | D98: Reflexive | E98: Dual | F98: Instant | G98: Parry lethal with hands. Unarmed does lethal, withering ignores (ess+intimacy) soak. | H98: 273 | I98: Brawl | J98: 1 | K98: 1 | L98: dawn
A99: Solar | B99: Ferocious Jab | C99: 1m | D99: Supplemental | E99: Uniform | F99: Instant | G99: Add your opponent's onslaught as damage dice to your attack. | H99: 274 | I99: Brawl | J99: 3 | K99: 1 | L99: dawn
A100: Solar | B100: Heaven Thunder Hammer | C100: 7m | D100: Reflexive | E100: Decisive-only | F100: Instant | G100: Knock enemies down or further away depending on succ. | H100: 274 | I100: Brawl | J100: 3 | K100: 1 | L100: dawn | M100: Ferocious Jab
A101: Solar | B101: Vicious Lunge | C101: 1m | D101: Supplemental | E101: None | F101: Instant | G101: Add 1 succ to grapple attack and (ess or 3) dice to initiative roll. | H101: 275 | I101: Brawl | J101: 3 | K101: 1 | L101: dawn
A102: Solar | B102: Unbreakable Grasp | C102: 2m/round pres. | D102: Reflexive | E102: None | F102: Instant | G102: Pay 2m when hit to conserve grapple control rounds. | H102: 275 | I102: Brawl | J102: 3 | K102: 1 | L102: dawn | M102: Vicious Lunge
A103: Solar | B103: Thunderclap Rush Attack | C103: 3m | D103: Reflexive | E103: None | F103: Instant | G103: Free move and attack. Uses up turn. | H103: 275 | I103: Brawl | J103: 3 | K103: 1 | L103: dawn
A104: Solar | B104: Wind and Stones Defense | C104: 3m | D104: Reflexive | E104: None | F104: Instant | G104: Add enemy's onslaught to your evasion or parry. | H104: 274 | I104: Brawl | J104: 4 | K104: 1 | L104: dawn | M104: Ferocious Jab
A105: Solar | B105: Crashing Wave Throw | C105: 5m | D105: Reflexive | E105: Uniform | F105: Instant | G105: When ending a grapple to throw, +2 damage per round forfeited. Throw up to short range. | H105: 275 | I105: Brawl | J105: 4 | K105: 1 | L105: dawn | M105: Vicious Lunge
A106: Solar | B106: Falling Hammer Strike | C106: 1m | D106: Supplemental | E106: Uniform | F106: Instant | G106: Enemy's onslaught is extended and builds until they aren't hit by you for 1 round. | H106: 275 | I106: Brawl | J106: 4 | K106: 1 | L106: dawn | M106: Thunderclap Rush Attack
A107: Solar | B107: Swift Strike Prana | C107: 3m, 1wp | D107: Reflexive | E107: Decisive-only | F107: Instant | H107: MotSE 8 | I107: Brawl | J107: 4 | K107: 1 | L107: dawn | M107: Ferocious Jab, Thunderclap Rush Attack
A108: Solar | B108: Devil-Strangling Attitude | C108: - (3m) | D108: Permanent | E108: None | F108: Instant | G108: Use Strength+Brawl to grapple. | H108: 275 | I108: Brawl | J108: 5 | K108: 1 | L108: dawn | M108: Vicious Lunge
A109: Solar | B109: Ox-Stunning Blow | C109: 4m, 1i, 1wp | D109: Simple | E109: Withering-Only | F109: Instant | G109: Add 1 succ to attack and ess dice to damage. Only soaked by stamina. | H109: 277 | I109: Brawl | J109: 3 | K109: 2 | L109: dawn | M109: Fists of Iron Technique
...

Sheet Siderial
A1: Type | B1: Name | C1: Выбор | D1: Фильтрация | E1: Комменты | F1: Дом | G1: Дева | H1: Созвездие | I1: Cost | J1: Type | K1: Keywords | L1: Duration | M1: Description | N1: Page # | O1: Ability | P1: Abil. Min | Q1: Ess. Min | R1: Aspect Space | S1: Prerequisites | T1: Prereq Spec.
A2: Sidereal | B2: Icy Hand | C2: зеленый | D2: возможно | E2: это про Бюро | F2: =VLOOKUP(O2,pearl!$B:$E,4,0) -> ♄ | G2: =VLOOKUP(IF(F2="Дом",H2,F2),pearl!$D$28:$F$32,3,0) -> Сатурн | H2: =VLOOKUP(O2,pearl!$B:$E,3,0) -> ♄Телега с сеном | I2: 1m, 1wp | J2: Simple | K2: Psyche | L2: Indefinite | M2: "нормально делай нормально будет" | N2: Sid 300 | O2: Bureaucracy | P2: 3 | Q2: 1 | R2: 0 | S2: None
A3: Sidereal | B3: Feathered Cloak Trick | C3: зеленый | D3: возможно | E3: цикл на врановых | F3: =VLOOKUP(O3,pearl!$B:$E,4,0) -> ♄ | G3: =VLOOKUP(IF(F3="Дом",H3,F3),pearl!$D$28:$F$32,3,0) -> Сатурн | H3: =VLOOKUP(O3,pearl!$B:$E,3,0) -> ♄Ворон | I3: 4m | J3: Simple | K3: Mute | L3: Indefinite | N3: Sid 296 | O3: Awareness | P3: 4 | Q3: 1 | R3: 0 | S3: None
A4: Sidereal | B4: Reading Dead Eyes | C4: зеленый | D4: возможно | E4: цикл на поствидение | F4: =VLOOKUP(O4,pearl!$B:$E,4,0) -> ♄ | G4: =VLOOKUP(IF(F4="Дом",H4,F4),pearl!$D$28:$F$32,3,0) -> Сатурн | H4: =VLOOKUP(O4,pearl!$B:$E,3,0) -> ♄Ворон | I4: 5m, 1wp | J4: Simple | K4: Mute | L4: Instant | N4: Sid 298 | O4: Awareness | P4: 4 | Q4: 2 | R4: 0 | S4: Feathered Cloak Trick
A5: Sidereal | B5: Expected Pain | C5: зеленый | D5: возможно | E5: цикл на предвидение жопы | F5: =VLOOKUP(O5,pearl!$B:$E,4,0) -> ♄ | G5: =VLOOKUP(IF(F5="Дом",H5,F5),pearl!$D$28:$F$32,3,0) -> Сатурн | H5: =VLOOKUP(O5,pearl!$B:$E,3,0) -> ♄Ворон | I5: - (5m) | J5: Permanent | K5: Divination, Mute, Uniform | L5: Permanent | N5: Sid 295 | O5: Awareness | P5: 3 | Q5: 1 | R5: 0 | S5: Prior Warning
A6: Sidereal | B6: Heavenly Sentinel Eye | C6: зеленый | D6: возможно | E6: цикл на предвидение жопы | F6: =VLOOKUP(O6,pearl!$B:$E,4,0) -> ♄ | G6: =VLOOKUP(IF(F6="Дом",H6,F6),pearl!$D$28:$F$32,3,0) -> Сатурн | H6: =VLOOKUP(O6,pearl!$B:$E,3,0) -> ♄Ворон | I6: 4m | J6: Reflexive | K6: None | L6: Instant | N6: Sid 295 | O6: Awareness | P6: 3 | Q6: 1 | R6: 0 | S6: Prior Warning
A7: Sidereal | B7: Prior Warning | C7: зеленый | D7: возможно | E7: цикл на предвидение жопы | F7: =VLOOKUP(O7,pearl!$B:$E,4,0) -> ♄ | G7: =VLOOKUP(IF(F7="Дом",H7,F7),pearl!$D$28:$F$32,3,0) -> Сатурн | H7: =VLOOKUP(O7,pearl!$B:$E,3,0) -> ♄Ворон | I7: - | J7: Permanent | K7: Divination | L7: Permanent | N7: Sid 294 | O7: Awareness | P7: 1 | Q7: 1 | R7: 0 | S7: None
A8: Sidereal | B8: Someone’s Son Style | C8: синий | D8: возможно | E8: в сияющей судьбе | F8: =VLOOKUP(O8,pearl!$B:$E,4,0) -> Дом | G8: =VLOOKUP(IF(F8="Дом",H8,F8),pearl!$D$28:$F$32,3,0) -> Марс | H8: =VLOOKUP(O8,pearl!$B:$E,3,0) -> ♂ | I8: - | J8: Permanent | K8: None | L8: Permanent | N8: Sid 224 | O8: Battles | P8: 2 | Q8: 1 | R8: 0 | S8: Any three Battles Charms
A9: Sidereal | B9: Favorable Inflection Procedure | C9: синий | D9: возможно | E9: Социалка | F9: =VLOOKUP(O9,pearl!$B:$E,4,0) -> ♄ | G9: =VLOOKUP(IF(F9="Дом",H9,F9),pearl!$D$28:$F$32,3,0) -> Сатурн | H9: =VLOOKUP(O9,pearl!$B:$E,3,0) -> ♄Меч | I9: 5m | J9: Reflexive | K9: Mute | L9: Instant | M9: постоянная планка для Резолва | N9: Sid 307 | O9: Integrity | P9: 2 | Q9: 1 | R9: 0 | S9: None
A10: Sidereal | B10: Shadow-Piercing Needle | C10: синий | D10: возможно | E10: как она дерется | F10: =VLOOKUP(O10,pearl!$B:$E,4,0) -> ☿ | G10: =VLOOKUP(IF(F10="Дом",H10,F10),pearl!$D$28:$F$32,3,0) -> Меркурий | H10: =VLOOKUP(O10,pearl!$B:$E,3,0) -> ☿Чайка | I10: 3m | J10: Supplemental | K10: Dual, Versatile | L10: Instant | N10: Sid 183 | O10: Thrown | P10: 3 | Q10: 1 | R10: 0 | S10: None
A11: Sidereal | B11: In Destiny’s Service | C11: синий | D11: возможно | E11: это про Бюро | F11: =VLOOKUP(O11,pearl!$B:$E,4,0) -> ♄ | G11: =VLOOKUP(IF(F11="Дом",H11,F11),pearl!$D$28:$F$32,3,0) -> Сатурн | H11: =VLOOKUP(O11,pearl!$B:$E,3,0) -> ♄Меч | I11: 5m | J11: Reflexive | K11: None | L11: Instant | M11: призывать свою компетенцию для Резолва | N11: Sid 308 | O11: Integrity | P11: 5 | Q11: 3 | R11: 0 | S11: Minimum Legal Defense Competence
A12: Sidereal | B12: Supernal Awareness (x2) | C12: синий | D12: возможно | E12: усиление по расстоянию | F12: =VLOOKUP(O12,pearl!$B:$E,4,0) -> ♄ | G12: =VLOOKUP(IF(F12="Дом",H12,F12),pearl!$D$28:$F$32,3,0) -> Сатурн | H12: =VLOOKUP(O12,pearl!$B:$E,3,0) -> ♄Ворон | I12: 5m (5m, 1wp) | J12: Simple | K12: Stackable | L12: One scene | N12: Sid 296 | O12: Awareness | P12: 5 | Q12: 3 | R12: 0 | S12: Supernal Awareness
A13: Sidereal | B13: Dark-Winged Watcher | C13: синий | D13: возможно | E13: цикл на врановых | F13: =VLOOKUP(O13,pearl!$B:$E,4,0) -> ♄ | G13: =VLOOKUP(IF(F13="Дом",H13,F13),pearl!$D$28:$F$32,3,0) -> Сатурн | H13: =VLOOKUP(O13,pearl!$B:$E,3,0) -> ♄Ворон | I13: 5m, 1wp | J13: Simple | K13: None | L13: (Essence + Perception) days | N13: Sid 298 | O13: Awareness | P13: 5 | Q13: 2 | R13: 0 | S13: Feathered Cloak Trick, Supernal Awareness
A14: Sidereal | B14: Old Sorrows Reminiscence | C14: синий | D14: возможно | E14: цикл на поствидение | F14: =VLOOKUP(O14,pearl!$B:$E,4,0) -> ♄ | G14: =VLOOKUP(IF(F14="Дом",H14,F14),pearl!$D$28:$F$32,3,0) -> Сатурн | H14: =VLOOKUP(O14,pearl!$B:$E,3,0) -> ♄Ворон | I14: 7m, 1wp | J14: Simple | K14: Divination, Mute | L14: Instant | N14: Sid 298 | O14: Awareness | P14: 5 | Q14: 3 | R14: 0 | S14: Prior Warning, Reading Dead Eyes
A15: Sidereal | B15: Promise of Tomorrow | C15: синий | D15: вполне | E15: надежда | F15: =VLOOKUP(O15,pearl!$B:$E,4,0) -> ♄ | G15: =VLOOKUP(IF(F15="Дом",H15,F15),pearl!$D$28:$F$32,3,0) -> Сатурн | H15: =VLOOKUP(O15,pearl!$B:$E,3,0) -> ♄Меч | I15: 2m | J15: Reflexive | K15: None | L15: Indefinite | M15: работа с связями надежды | N15: Sid 306 | O15: Integrity | P15: 4 | Q15: 1 | R15: 0 | S15: Until Hope's End
A16: Sidereal | B16: Honest Face Spirit | C16: зеленый | D16: вполне | E16: в сияющей судьбе | F16: =VLOOKUP(O16,pearl!$B:$E,4,0) -> Дом | G16: =VLOOKUP(IF(F16="Дом",H16,F16),pearl!$D$28:$F$32,3,0) -> Меркурий | H16: =VLOOKUP(O16,pearl!$B:$E,3,0) -> ☿ | I16: 3m | J16: Reflexive | K16: Mute | L16: One scene | N16: Sid 158 | O16: Journeys | P16: 2 | Q16: 1 | R16: 0 | S16: Any Journeys Charm
A17: Sidereal | B17: Until Hope’s End | C17: синий | D17: вполне | E17: надежда | F17: =VLOOKUP(O17,pearl!$B:$E,4,0) -> ♄ | G17: =VLOOKUP(IF(F17="Дом",H17,F17),pearl!$D$28:$F$32,3,0) -> Сатурн | H17: =VLOOKUP(O17,pearl!$B:$E,3,0) -> ♄Меч | I17: - | J17: Permanent | K17: None | L17: Permanent | M17: работа с связями надежды | N17: Sid 305 | O17: Integrity | P17: 1 | Q17: 1 | R17: 0 | S17: None
A18: Sidereal | B18: Returning Swallow Flight | C18: зеленый | D18: вполне | E18: притягивать вещи | F18: =VLOOKUP(O18,pearl!$B:$E,4,0) -> ☿ | G18: =VLOOKUP(IF(F18="Дом",H18,F18),pearl!$D$28:$F$32,3,0) -> Меркурий | H18: =VLOOKUP(O18,pearl!$B:$E,3,0) -> ☿Чайка | I18: 5m | J18: Supplemental | K18: Decisive-only, Versatile | L18: Instant | N18: Sid 183 | O18: Thrown | P18: 3 | Q18: 1 | R18: 0 | S18: None
A19: Sidereal | B19: Shrike-Roosting Gesture | C19: зеленый | D19: вполне | E19: притягивать вещи | F19: =VLOOKUP(O19,pearl!$B:$E,4,0) -> ☿ | G19: =VLOOKUP(IF(F19="Дом",H19,F19),pearl!$D$28:$F$32,3,0) -> Меркурий | H19: =VLOOKUP(O19,pearl!$B:$E,3,0) -> ☿Чайка | I19: 3m (1m) | J19: Reflexive | K19: None | L19: Instant | N19: Sid 183 | O19: Thrown | P19: 3 | Q19: 1 | R19: 0 | S19: Returning Swallow Flight
A20: Sidereal | B20: Good Worker Spirit | C20: зеленый | D20: вполне | E20: это работа в Бюро | F20: =VLOOKUP(O20,pearl!$B:$E,4,0) -> Дом | G20: =VLOOKUP(IF(F20="Дом",H20,F20),pearl!$D$28:$F$32,3,0) -> Меркурий | H20: =VLOOKUP(O20,pearl!$B:$E,3,0) -> ☿ | I20: 5m | J20: Supplemental | K20: Mute | L20: Instant | N20: Sid 158 | O20: Journeys | P20: 3 | Q20: 1 | R20: 0 | S20: Honest Face Spirit
A21: Sidereal | B21: Forgotten Earth | C21: зеленый | D21: вполне | E21: прыгать вместе с Бангом | F21: =VLOOKUP(O21,pearl!$B:$E,4,0) -> ♄ | G21: =VLOOKUP(IF(F21="Дом",H21,F21),pearl!$D$28:$F$32,3,0) -> Сатурн | H21: =VLOOKUP(O21,pearl!$B:$E,3,0) -> ♄Восходящий Дым | I21: 3m | J21: Reflexive | K21: Mute | L21: Instant | M21: как соларская атлетика | N21: Sid 290 | O21: Athletics | P21: 2 | Q21: 1 | R21: 0 | S21: None
A22: Sidereal | B22: Terminal Sanction | C22: зеленый | D22: вполне | E22: работа с духами | F22: =VLOOKUP(O22,pearl!$B:$E,4,0) -> ♄ | G22: =VLOOKUP(IF(F22="Дом",H22,F22),pearl!$D$28:$F$32,3,0) -> Сатурн | H22: =VLOOKUP(O22,pearl!$B:$E,3,0) -> ♄Телега с сеном | I22: 5m | J22: Simple | K22: None | L22: Instant | M22: принуждение материализоваться | N22: Sid 300 | O22: Bureaucracy | P22: 2 | Q22: 1 | R22: 0 | S22: None
A23: Sidereal | B23: Superior-Entreating Memorial Style | C23: зеленый | D23: вполне | E23: секретные письма в Бюро | F23: =VLOOKUP(O23,pearl!$B:$E,4,0) -> Дом | G23: =VLOOKUP(IF(F23="Дом",H23,F23),pearl!$D$28:$F$32,3,0) -> Сатурн | H23: =VLOOKUP(O23,pearl!$B:$E,3,0) -> ♄ | I23: 1m | J23: Simple | K23: None | L23: Instant | M23: исчезающие письма | N23: Sid 288 | O23: Endings | P23: 1 | Q23: 1 | R23: 0 | S23: Any Endings Charm
A24: Sidereal | B24: Inevitable Pursuit | C24: зеленый | D24: вполне | E24: цикл на слежку | F24: =VLOOKUP(O24,pearl!$B:$E,4,0) -> ♄ | G24: =VLOOKUP(IF(F24="Дом",H24,F24),pearl!$D$28:$F$32,3,0) -> Сатурн | H24: =VLOOKUP(O24,pearl!$B:$E,3,0) -> ♄Ворон | I24: 4m | J24: Simple | K24: None | L24: Instant | N24: Sid 296 | O24: Awareness | P24: 3 | Q24: 1 | R24: 0 | S24: None
A25: Sidereal | B25: Supernal Awareness | C25: зеленый | D25: вполне | E25: цикл на слежку | F25: =VLOOKUP(O25,pearl!$B:$E,4,0) -> ♄ | G25: =VLOOKUP(IF(F25="Дом",H25,F25),pearl!$D$28:$F$32,3,0) -> Сатурн | H25: =VLOOKUP(O25,pearl!$B:$E,3,0) -> ♄Ворон | I25: 5m | J25: Simple | K25: Stackable | L25: One scene | N25: Sid 296 | O25: Awareness | P25: 4 | Q25: 1 | R25: 0 | S25: Inevitable Pursuit
A26: Sidereal | B26: Magpie’s Favorite Bauble | C26: синий | D26: вполне | E26: притягивать вещи | F26: =VLOOKUP(O26,pearl!$B:$E,4,0) -> ☿ | G26: =VLOOKUP(IF(F26="Дом",H26,F26),pearl!$D$28:$F$32,3,0) -> Меркурий | H26: =VLOOKUP(O26,pearl!$B:$E,3,0) -> ☿Чайка | I26: - (+3m) | J26: Permanent | K26: None | L26: Permanent | N26: Sid 186 | O26: Thrown | P26: 5 | Q26: 2 | R26: 0 | S26: Shrike-Roosting Gesture
A27: Sidereal | B27: Water and Fire Treaty | C27: синий | D27: возможно | E27: для путешествий | F27: =VLOOKUP(O27,pearl!$B:$E,4,0) -> ♂ | G27: =VLOOKUP(IF(F27="Дом",H27,F27),pearl!$D$28:$F$32,3,0) -> Марс | H27: =VLOOKUP(O27,pearl!$B:$E,3,0) -> Щит♂ | I27: 1m, 1ahl | J27: Simple | K27: Decisive-only, Stackable | L27: One story | N27: Sid 244 | O27: Presence | P27: 2 | Q27: 1 | R27: 0 | S27: None
A28: Sidereal | B28: Impose Nature | C28: зеленый | D28: вполне | E28: наделить своей чертой | F28: =VLOOKUP(O28,pearl!$B:$E,4,0) -> ♂ | G28: =VLOOKUP(IF(F28="Дом",H28,F28),pearl!$D$28:$F$32,3,0) -> Марс | H28: =VLOOKUP(O28,pearl!$B:$E,3,0) -> Щит♂ | I28: 7m | J28: Simple | K28: Mute, Psyche | L28: Instant | N28: Sid 243 | O28: Presence | P28: 2 | Q28: 1 | R28: 0 | S28: None
A29: Sidereal | B29: Wise Choice | C29: синий | D29: вполне | E29: ясновидение Гранат | F29: =VLOOKUP(O29,pearl!$B:$E,4,0) -> ♄ | G29: =VLOOKUP(IF(F29="Дом",H29,F29),pearl!$D$28:$F$32,3,0) -> Сатурн | H29: =VLOOKUP(O29,pearl!$B:$E,3,0) -> ♄Ворон | I29: 6m | J29: Simple | K29: Divination | L29: Instant | N29: Sid 296 | O29: Awareness | P29: 1 | Q29: 1 | R29: 0 | S29: None
A30: Sidereal | B30: Insatiable Weapon Wanderlust | C30: зеленый | D30: вряд ли | E30: как она дерется | F30: =VLOOKUP(O30,pearl!$B:$E,4,0) -> ☿ | G30: =VLOOKUP(IF(F30="Дом",H30,F30),pearl!$D$28:$F$32,3,0) -> Меркурий | H30: =VLOOKUP(O30,pearl!$B:$E,3,0) -> ☿Чайка | I30: 2m | J30: Supplemental | K30: Uniform, Versatile | L30: Instant | N30: Sid 183 | O30: Thrown | P30: 3 | Q30: 1 | R30: 0 | S30: None
A31: Sidereal | B31: Willful Weapon Method | C31: зеленый | D31: вряд ли | E31: как она дерется | F31: =VLOOKUP(O31,pearl!$B:$E,4,0) -> ☿ | G31: =VLOOKUP(IF(F31="Дом",H31,F31),pearl!$D$28:$F$32,3,0) -> Меркурий | H31: =VLOOKUP(O31,pearl!$B:$E,3,0) -> ☿Чайка | I31: 2m, 1wp | J31: Simple | K31: Decisive-only | L31: Instant | N31: Sid 184 | O31: Thrown | P31: 3 | Q31: 1 | R31: 0 | S31: None
A32: Sidereal | B32: Borrowed Coffin Ploy | C32: зеленый | D32: вряд ли | E32: Социалка | F32: =VLOOKUP(O32,pearl!$B:$E,4,0) -> Дом | G32: =VLOOKUP(IF(F32="Дом",H32,F32),pearl!$D$28:$F$32,3,0) -> Сатурн | H32: =VLOOKUP(O32,pearl!$B:$E,3,0) -> ♄ | I32: 3m | J32: Simple | K32: Mute | L32: Permanent | M32: "да -не- умер в конце Драйва!" | N32: Sid 288 | O32: Endings | P32: 3 | Q32: 1 | R32: 0 | S32: Any three Endings Charms
A33: Sidereal | B33: Holistic Arsenal Methodology | C33: синий | D33: вряд ли | E33: как она дерется | F33: =VLOOKUP(O33,pearl!$B:$E,4,0) -> Дом | G33: =VLOOKUP(IF(F33="Дом",H33,F33),pearl!$D$28:$F$32,3,0) -> Марс | H33: =VLOOKUP(O33,pearl!$B:$E,3,0) -> ♂ | I33: - (2m) | J33: Permanent | K33: None | L33: Permanent | M33: оружие с тегом МА можно использовать другими навыками | N33: Sid 223 | O33: Battles | P33: 1 | Q33: 1 | R33: 0 | S33: None
A34: Sidereal | B34: Sword-Tongue Intensity | C34: синий | D34: вряд ли | E34: как она дерется | F34: =VLOOKUP(O34,pearl!$B:$E,4,0) -> ♂ | G34: =VLOOKUP(IF(F34="Дом",H34,F34),pearl!$D$28:$F$32,3,0) -> Марс | H34: =VLOOKUP(O34,pearl!$B:$E,3,0) -> Щит♂ | I34: 3m | J34: Reflexive | K34: None | L34: Instant | M34: заговор зубов в бою | N34: Sid 244 | O34: Presence | P34: 4 | Q34: 1 | R34: 0 | S34: None
A35: Sidereal | B35: Ascending Serenity Horoscope | C35: зеленый | D35: проблемы с гороскопами | F35: =VLOOKUP(O35,pearl!$B:$E,4,0) -> Дом | G35: =VLOOKUP(IF(F35="Дом",H35,F35),pearl!$D$28:$F$32,3,0) -> Венера | H35: =VLOOKUP(O35,pearl!$B:$E,3,0) -> ♀ | I35: 1m or 3m, 1wp | J35: Simple | K35: Mute, Shaping (Fate), Stackable | L35: One story | M35: благословение или проклятие | N35: Sid 189 | O35: Serenities | P35: 3 | Q35: 1 | R35: 0 | S35: Any three Serenity Charms
A36: Sidereal | B36: Descending Serenity Horoscope | C36: зеленый | D36: проблемы с гороскопами | F36: =VLOOKUP(O36,pearl!$B:$E,4,0) -> Дом | G36: =VLOOKUP(IF(F36="Дом",H36,F36),pearl!$D$28:$F$32,3,0) -> Венера | H36: =VLOOKUP(O36,pearl!$B:$E,3,0) -> ♀ | I36: 1 or 3m, 1wp | J36: Simple | K36: Mute, Shaping (Fate), Stackable | L36: One story | M36: благословение или проклятие | N36: Sid 189 | O36: Serenities | P36: 3 | Q36: 1 | R36: 0 | S36: Any three Serenity Charms
A37: Sidereal | B37: Ascending Endings Horoscope | C37: зеленый | D37: проблемы с гороскопами | E37: ради всей Айни? | F37: =VLOOKUP(O37,pearl!$B:$E,4,0) -> Дом | G37: =VLOOKUP(IF(F37="Дом",H37,F37),pearl!$D$28:$F$32,3,0) -> Сатурн | H37: =VLOOKUP(O37,pearl!$B:$E,3,0) -> ♄ | I37: 1m or 3m, 1wp | J37: Simple | K37: Mute, Shaping (Fate), Stackable, Uniform | L37: One story | M37: благословение или проклятие | N37: Sid 287 | O37: Endings | P37: 3 | Q37: 1 | R37: 0 | S37: Any three Endings Charms
A38: Sidereal | B38: Ascending Secrets Horoscope | C38: оранж | D38: проблемы с гороскопами | F38: =VLOOKUP(O38,pearl!$B:$E,4,0) -> Дом | G38: =VLOOKUP(IF(F38="Дом",H38,F38),pearl!$D$28:$F$32,3,0) -> Юпитер | H38: =VLOOKUP(O38,pearl!$B:$E,3,0) -> ♃ | I38: 1m or 3m, 1wp | J38: Simple | K38: Mute, Shaping (Fate), Stackable | L38: One story | M38: благословение или проклятие | N38: Sid 255 | O38: Secrets | P38: 3 | Q38: 1 | R38: 0 | S38: Any three Secrets Charms
A39: Sidereal | B39: Ascending Journeys Horoscope | C39: синий | D39: проблемы с гороскопами | F39: =VLOOKUP(O39,pearl!$B:$E,4,0) -> Дом | G39: =VLOOKUP(IF(F39="Дом",H39,F39),pearl!$D$28:$F$32,3,0) -> Меркурий | H39: =VLOOKUP(O39,pearl!$B:$E,3,0) -> ☿ | I39: 1m or 3m, 1wp | J39: Simple | K39: Mute, Shaping (Fate), Stackable | L39: One story | M39: благословение или проклятие | N39: Sid 156 | O39: Journeys | P39: 3 | Q39: 1 | R39: 0 | S39: Any three Journeys Charms
A40: Sidereal | B40: Descending Journeys Horoscope | C40: синий | D40: проблемы с гороскопами | F40: =VLOOKUP(O40,pearl!$B:$E,4,0) -> Дом | G40: =VLOOKUP(IF(F40="Дом",H40,F40),pearl!$D$28:$F$32,3,0) -> Меркурий | H40: =VLOOKUP(O40,pearl!$B:$E,3,0) -> ☿ | I40: 1m or 3m, 1wp | J40: Simple | K40: Mute, Shaping (Fate), Stackable | L40: One story | M40: благословение или проклятие | N40: Sid 158 | O40: Journeys | P40: 3 | Q40: 1 | R40: 0 | S40: Any three Journeys Charms
A41: Sidereal | B41: Ox-Body Technique | C41: зеленый | D41: скучно | E41: это для игрока | F41: =VLOOKUP(O41,pearl!$B:$E,4,0) -> ☿ | G41: =VLOOKUP(IF(F41="Дом",H41,F41),pearl!$D$28:$F$32,3,0) -> Меркурий | H41: =VLOOKUP(O41,pearl!$B:$E,3,0) -> ☿Мачта | I41: - | J41: Permanent | K41: None | L41: Permanent | M41: просто хиты | N41: Sid 161 | O41: Resistance | P41: 1 | Q41: 1 | R41: 0 | S41: None
A42: Sidereal | B42: Hero’s Iron Skin | C42: зеленый | D42: скучно | E42: это для игрока | F42: =VLOOKUP(O42,pearl!$B:$E,4,0) -> ♂ | G42: =VLOOKUP(IF(F42="Дом",H42,F42),pearl!$D$28:$F$32,3,0) -> Марс | H42: =VLOOKUP(O42,pearl!$B:$E,3,0) -> Щит♂ | I42: 4m | J42: Reflexive | K42: Withering-only | L42: Instant | M42: дает сок в ослабляющих, особенно против тормозных | N42: Sid 242 | O42: Presence | P42: 2 | Q42: 1 | R42: 0 | S42: None
A43: Sidereal | B43: Red Haze | C43: синий | D43: скучно | E43: как она дерется | F43: =VLOOKUP(O43,pearl!$B:$E,4,0) -> ♂ | G43: =VLOOKUP(IF(F43="Дом",H43,F43),pearl!$D$28:$F$32,3,0) -> Марс | H43: =VLOOKUP(O43,pearl!$B:$E,3,0) -> Щит♂ | I43: 4m, 1wp | J43: Simple | K43: None | L43: One scene | M43: "подсветка" на врагов судьбы | N43: Sid 244 | O43: Presence | P43: 3 | Q43: 1 | R43: 0 | S43: None
A44: Sidereal | B44: Step-Silencing Exercise | C44: оранж | D44: тема не та | E44: забавное, но не | F44: =VLOOKUP(O44,pearl!$B:$E,4,0) -> ♄ | G44: =VLOOKUP(IF(F44="Дом",H44,F44),pearl!$D$28:$F$32,3,0) -> Сатурн | H44: =VLOOKUP(O44,pearl!$B:$E,3,0) -> ♄Восходящий Дым | I44: 3m | J44: Supplemental | K44: Mute | L44: Instant | M44: шаги или твой транспорт БЕСШУМНЫ (автопровал Персепшена на слух) | N44: Sid 292 | O44: Athletics | P44: 4 | Q44: 2 | R44: 0 | S44: Inexorable Advance
A45: Sidereal | B45: Serenity in Blood | C45: оранж | D45: тема не та | E45: как она дерется | F45: =VLOOKUP(O45,pearl!$B:$E,4,0) -> ♂ | G45: =VLOOKUP(IF(F45="Дом",H45,F45),pearl!$D$28:$F$32,3,0) -> Марс | H45: =VLOOKUP(O45,pearl!$B:$E,3,0) -> Копье♂ | I45: 5m | J45: Reflexive | K45: Perilous, Uniform | L45: Instant | M45: Блокируй неблокируемое | N45: Sid 240 | O45: Melee | P45: 5 | Q45: 2 | R45: 0 | S45: Impeding the Flow
A46: Sidereal | B46: Burn Life | C46: оранж | D46: тема не та | E46: как она дерется | F46: =VLOOKUP(O46,pearl!$B:$E,4,0) -> ♄ | G46: =VLOOKUP(IF(F46="Дом",H46,F46),pearl!$D$28:$F$32,3,0) -> Сатурн | H46: =VLOOKUP(O46,pearl!$B:$E,3,0) -> ♄Восходящий Дым | I46: 3m per dot, 1ahl (+1wp) | J46: Simple | K46: Perilous | L46: One scene | M46: сжигаем годы жизни за силищу | N46: Sid 291 | O46: Athletics | P46: 3 | Q46: 1 | R46: 0 | S46: None
A47: Sidereal | B47: Harmony of Blows | C47: синий | D47: тема не та | E47: как она дерется | F47: =VLOOKUP(O47,pearl!$B:$E,4,0) -> ♂ | G47: =VLOOKUP(IF(F47="Дом",H47,F47),pearl!$D$28:$F$32,3,0) -> Марс | H47: =VLOOKUP(O47,pearl!$B:$E,3,0) -> Копье♂ | I47: 1m, 1wp | J47: Reflexive | K47: Uniform, Versatile | L47: Instant | M47: доп атака после Сокрушения | N47: Sid 239 | O47: Melee | P47: 3 | Q47: 1 | R47: 0 | S47: None
A48: Sidereal | B48: Orchestration of Conflict | C48: синий | D48: тема не та | E48: как она дерется | F48: =VLOOKUP(O48,pearl!$B:$E,4,0) -> ♂ | G48: =VLOOKUP(IF(F48="Дом",H48,F48),pearl!$D$28:$F$32,3,0) -> Марс | H48: =VLOOKUP(O48,pearl!$B:$E,3,0) -> Копье♂ | I48: 5m | J48: Supplemental | K48: Uniform, Versatile | L48: Instant | M48: защитный штраф массово | N48: Sid 239 | O48: Melee | P48: 4 | Q48: 1 | R48: 0 | S48: Harmony of Blows
A49: Sidereal | B49: Peaceable Conclusion | C49: синий | D49: тема не та | E49: мертвецы | F49: =VLOOKUP(O49,pearl!$B:$E,4,0) -> ♄ | G49: =VLOOKUP(IF(F49="Дом",H49,F49),pearl!$D$28:$F$32,3,0) -> Сатурн | H49: =VLOOKUP(O49,pearl!$B:$E,3,0) -> ♄Труп | I49: 1m | J49: Simple | K49: None | L49: Instant | M49: insta kill incap or willing; Lethe+no hungy ghost; | N49: Sid 310 | O49: Medicine | P49: 1 | Q49: 1 | R49: 0 | S49: Smooth Transition
A50: Sidereal | B50: Rising Butterfly Prayer | C50: синий | D50: тема не та | E50: мертвецы | F50: =VLOOKUP(O50,pearl!$B:$E,4,0) -> ♄ | G50: =VLOOKUP(IF(F50="Дом",H50,F50),pearl!$D$28:$F$32,3,0) -> Сатурн | H50: =VLOOKUP(O50,pearl!$B:$E,3,0) -> ♄Труп | I50: 5m | J50: Simple | K50: Mute | L50: Instant | M50: rutual on decesead to next happy life | N50: Sid 311 | O50: Medicine | P50: 5 | Q50: 1 | R50: 0 | S50: Peaceable Conclusion
A51: Sidereal | B51: Smooth Transition | C51: синий | D51: тема не та | E51: мертвецы | F51: =VLOOKUP(O51,pearl!$B:$E,4,0) -> ♄ | G51: =VLOOKUP(IF(F51="Дом",H51,F51),pearl!$D$28:$F$32,3,0) -> Сатурн | H51: =VLOOKUP(O51,pearl!$B:$E,3,0) -> ♄Труп | I51: 5m | J51: Simple | K51: Aggravated, Decisive-only | L51: Instant | M51: aggr dmg to undead, may use to banish ghost | N51: Sid 310 | O51: Medicine | P51: 1 | Q51: 1 | R51: 0 | S51: None
A52: Sidereal | B52: Deferred Wounds | C52: синий | D52: тема не та | E52: спецмедик | F52: =VLOOKUP(O52,pearl!$B:$E,4,0) -> ♄ | G52: =VLOOKUP(IF(F52="Дом",H52,F52),pearl!$D$28:$F$32,3,0) -> Сатурн | H52: =VLOOKUP(O52,pearl!$B:$E,3,0) -> ♄Труп | I52: 1m, 1wp | J52: Simple | K52: None | L52: Indefinite | M52: commit to remove Bah and lethal HL | N52: Sid 312 | O52: Medicine | P52: 3 | Q52: 1 | R52: 0 | S52: None
... A54: Sidereal | B54: Terminate Illness | C54: синий | D54: тема не та | E54: спецмедик | F54: =VLOOKUP(O54,pearl!$B:$E,4,0) -> ♄ | G54: =VLOOKUP(IF(F54="Дом",H54,F54),pearl!$D$28:$F$32,3,0) -> Сатурн | H54: =VLOOKUP(O54,pearl!$B:$E,3,0) -> ♄Труп | I54: 8m, 1wp | J54: Simple | K54: None | L54: Instant | M54: instantly anti-disease | N54: Sid 313 | O54: Medicine | P54: 3 | Q54: 1 | R54: 0 | S54: None
A55: Sidereal | B55: Atelier-and-Embassy Auspice | C55: зеленый | F55: =VLOOKUP(O55,pearl!$B:$E,4,0) -> ♀ | G55: =VLOOKUP(IF(F55="Дом",H55,F55),pearl!$D$28:$F$32,3,0) -> Венера | H55: =VLOOKUP(O55,pearl!$B:$E,3,0) -> ♀Павлин | I55: 4m, 1wp | J55: Simple | K55: None | L55: One social interaction or event | N55: Sid 193 | O55: Craft | P55: 3 | Q55: 1 | R55: 0 | S55: None
A56: Sidereal | B56: Creation of Beauty | C56: зеленый | F56: =VLOOKUP(O56,pearl!$B:$E,4,0) -> ♀ | G56: =VLOOKUP(IF(F56="Дом",H56,F56),pearl!$D$28:$F$32,3,0) -> Венера | H56: =VLOOKUP(O56,pearl!$B:$E,3,0) -> ♀Павлин | I56: 2m per die | J56: Supplemental | K56: None | L56: Instant | N56: Sid 193 | O56: Craft | P56: 2 | Q56: 1 | R56: 0 | S56: None
A57: Sidereal | B57: Destiny-Knitting Entanglement | C57: зеленый | F57: =VLOOKUP(O57,pearl!$B:$E,4,0) -> ♀ | G57: =VLOOKUP(IF(F57="Дом",H57,F57),pearl!$D$28:$F$32,3,0) -> Венера | H57: =VLOOKUP(O57,pearl!$B:$E,3,0) -> ♀Павлин | I57: 1m, 1wp | J57: Simple | K57: Shaping (Fate), Stackable | L57: Indefinite | N57: Sid 194 | O57: Craft | P57: 3 | Q57: 1 | R57: 0 | S57: None
A58: Sidereal | B58: Elegant Patterns of Fate | C58: зеленый | F58: =VLOOKUP(O58,pearl!$B:$E,4,0) -> ♀ | G58: =VLOOKUP(IF(F58="Дом",H58,F58),pearl!$D$28:$F$32,3,0) -> Венера | H58: =VLOOKUP(O58,pearl!$B:$E,3,0) -> ♀Павлин | I58: - | J58: Permanent | K58: None | L58: Permanent | N58: Sid 192 | O58: Craft | P58: 1 | Q58: 1 | R58: 0 | S58: None
A59: Sidereal | B59: Elemental Vision | C59: зеленый | F59: =VLOOKUP(O59,pearl!$B:$E,4,0) -> ♀ | G59: =VLOOKUP(IF(F59="Дом",H59,F59),pearl!$D$28:$F$32,3,0) -> Венера | H59: =VLOOKUP(O59,pearl!$B:$E,3,0) -> ♀Павлин | I59: - | J59: Permanent | K59: None | L59: Permanent | N59: Sid 192 | O59: Craft | P59: 1 | Q59: 1 | R59: 0 | S59: None
A60: Sidereal | B60: Predestined Delivery Shaping | C60: зеленый | F60: =VLOOKUP(O60,pearl!$B:$E,4,0) -> ♀ | G60: =VLOOKUP(IF(F60="Дом",H60,F60),pearl!$D$28:$F$32,3,0) -> Венера | H60: =VLOOKUP(O60,pearl!$B:$E,3,0) -> ♀Павлин | I60: 1m, 1wp | J60: Simple | K60: Shaping (Fate) | L60: Until the object arrives | N60: Sid 195 | O60: Craft | P60: 4 | Q60: 2 | R60: 0 | S60: Destiny-Knitting Entanglement
A61: Sidereal | B61: Sword-Queen’s Foretold Blade | C61: зеленый | F61: =VLOOKUP(O61,pearl!$B:$E,4,0) -> ♀ | G61: =VLOOKUP(IF(F61="Дом",H61,F61),pearl!$D$28:$F$32,3,0) -> Венера | H61: =VLOOKUP(O61,pearl!$B:$E,3,0) -> ♀Павлин | I61: 1wp | J61: Simple | K61: Shaping (Fate), Stackable | L61: Indefinite | N61: Sid 195 | O61: Craft | P61: 5 | Q61: 2 | R61: 0 | S61: Elegant Patterns of Fate, Excellent Implementation of Objectives
A62: Sidereal | B62: Warp-and-Weft Handiwork | C62: зеленый | F62: =VLOOKUP(O62,pearl!$B:$E,4,0) -> ♀ | G62: =VLOOKUP(IF(F62="Дом",H62,F62),pearl!$D$28:$F$32,3,0) -> Венера | H62: =VLOOKUP(O62,pearl!$B:$E,3,0) -> ♀Павлин | I62: 5m, 2s/g/wxp | J62: Supplemental | K62: None | L62: Instant | N62: Sid 193 | O62: Craft | P62: 4 | Q62: 1 | R62: 0 | S62: Creation of Beauty
A63: Sidereal | B63: Absent Self | C63: зеленый | F63: =VLOOKUP(O63,pearl!$B:$E,4,0) -> ♀ | G63: =VLOOKUP(IF(F63="Дом",H63,F63),pearl!$D$28:$F$32,3,0) -> Венера | H63: =VLOOKUP(O63,pearl!$B:$E,3,0) -> ♀Кувшин | I63: 2m | J63: Reflexive | K63: Uniform | L63: Instant | N63: Sid 199 | O63: Dodge | P63: 1 | Q63: 1 | R63: 0 | S63: None
A64: Sidereal | B64: Avoidance | C64: зеленый | F64: =VLOOKUP(O64,pearl!$B:$E,4,0) -> ♀ | G64: =VLOOKUP(IF(F64="Дом",H64,F64),pearl!$D$28:$F$32,3,0) -> Венера | H64: =VLOOKUP(O64,pearl!$B:$E,3,0) -> ♀Кувшин | I64: 5m, 1wp | J64: Simple | K64: Perilous, Shaping (Mind) | L64: Instant | N64: Sid 200 | O64: Dodge | P64: 5 | Q64: 1 | R64: 0 | S64: Absent Self
A65: Sidereal | B65: Duck Fate | C65: зеленый | F65: =VLOOKUP(O65,pearl!$B:$E,4,0) -> ♀ | G65: =VLOOKUP(IF(F65="Дом",H65,F65),pearl!$D$28:$F$32,3,0) -> Венера | H65: =VLOOKUP(O65,pearl!$B:$E,3,0) -> ♀Кувшин | I65: 7m | J65: Reflexive | K65: Uniform, Perilous | L65: Instant | N65: Sid 201 | O65: Dodge | P65: 4 | Q65: 2 | R65: 0 | S65: Absent Self
A66: Sidereal | B66: Elusive Object of Desire | C66: зеленый | F66: =VLOOKUP(O66,pearl!$B:$E,4,0) -> ♀ | G66: =VLOOKUP(IF(F66="Дом",H66,F66),pearl!$D$28:$F$32,3,0) -> Венера | H66: =VLOOKUP(O66,pearl!$B:$E,3,0) -> ♀Кувшин | I66: 5m | J66: Reflexive | K66: Counterattack, Mute, Uniform | L66: Instant | N66: Sid 200 | O66: Dodge | P66: 3 | Q66: 1 | R66: 0 | S66: Absent Self
... A101: Sidereal | B101: Without Words, Without the Wordless | C101: синий | F101: =VLOOKUP(O101,pearl!$B:$E,4,0) -> Дом | G101: =VLOOKUP(IF(F101="Дом",H101,F101),pearl!$D$28:$F$32,3,0) -> Венера | H101: =VLOOKUP(O101,pearl!$B:$E,3,0) -> ♀ | I101: 10m, 1wp | J101: Reflexive | K101: Mute, Psyche | L101: Instant | N101: Sid 191 | O101: Serenities | P101: 5 | Q101: 4 | R101: 0 | S101: Abandoned Words Curse
A102: Sidereal | B102: Caught in the Heart’s Wake | C102: зеленый | D102: вполне | E102: Социалка | F102: =VLOOKUP(O102,pearl!$B:$E,4,0) -> ♂ | G102: =VLOOKUP(IF(F102="Дом",H102,F102),pearl!$D$28:$F$32,3,0) -> Марс | H102: =VLOOKUP(O102,pearl!$B:$E,3,0) -> Щит♂ | I102: 1m, 1wp | J102: Simple | K102: Psyche | L102: Instant | N102: Sid 243 | O102: Presence | P102: 3 | Q102: 1 | R102: 0 | S102: Impose Nature
A103: Sidereal | B103: Presence-in-Absence Technique | C103: зеленый | D103: вполне | E103: Социалка | F103: =VLOOKUP(O103,pearl!$B:$E,4,0) -> ♂ | G103: =VLOOKUP(IF(F103="Дом",H103,F103),pearl!$D$28:$F$32,3,0) -> Марс | H103: =VLOOKUP(O103,pearl!$B:$E,3,0) -> Щит♂ | I103: 5m, 1wp | J103: Simple | K103: Mute, Psyche | L103: Until the condition is met | N103: Sid 243 | O103: Presence | P103: 3 | Q103: 1 | R103: 0 | S103: Impose Nature
A104: Sidereal | B104: Beyond the Shattered Wall | C104: синий | D104: возможно | E104: цикл мастермайнда | F104: =VLOOKUP(O104,pearl!$B:$E,4,0) -> ♂ | G104: =VLOOKUP(IF(F104="Дом",H104,F104),pearl!$D$28:$F$32,3,0) -> Марс | H104: =VLOOKUP(O104,pearl!$B:$E,3,0) -> Щит♂ | I104: 10m, 1wp | J104: Simple | K104: None | L104: Instant | N104: Sid 247 | O104: Presence | P104: 5 | Q104: 4 | R104: 0 | S104: Ego-Shattering Reminiscence, Force Decision, Presence-in-Absence Technique
A105: Sidereal | B105: Ego-Shattering Reminiscence | C105: синий | D105: вполне | E105: воспоминния | F105: =VLOOKUP(O105,pearl!$B:$E,4,0) -> ♂ | G105: =VLOOKUP(IF(F105="Дом",H105,F105),pearl!$D$28:$F$32,3,0) -> Марс | H105: =VLOOKUP(O105,pearl!$B:$E,3,0) -> Щит♂ | I105: 4m, 1wp | J105: Simple | K105: Psyche | L105: Instant | N105: Sid 246 | O105: Presence | P105: 5 | Q105: 3 | R105: 0 | S105: Instructive Conviction Aura
A106: Sidereal | B106: Force Decision | C106: синий | D106: возможно | E106: цикл мастермайнда | F106: =VLOOKUP(O106,pearl!$B:$E,4,0) -> ♂ | G106: =VLOOKUP(IF(F106="Дом",H106,F106),pearl!$D$28:$F$32,3,0) -> Марс | H106: =VLOOKUP(O106,pearl!$B:$E,3,0) -> Щит♂ | I106: 2m, 1wp | J106: Reflexive | K106: Psyche | L106: Instant | N106: Sid 245 | O106: Presence | P106: 5 | Q106: 2 | R106: 0 | S106: Impose Nature
A107: Sidereal | B107: Heroic Essence Replenishment | C107: синий | D107: вряд ли | E107: это для игрока | F107: =VLOOKUP(O107,pearl!$B:$E,4,0) -> ♂ | G107: =VLOOKUP(IF(F107="Дом",H107,F107),pearl!$D$28:$F$32,3,0) -> Марс | H107: =VLOOKUP(O107,pearl!$B:$E,3,0) -> Щит♂ | I107: - | J107: Permanent | K107: None | L107: Permanent | M107: моты | N107: Sid 244 | O107: Presence | P107: 3 | Q107: 1 | R107: 0 | S107: None
A108: Sidereal | B108: Seizing the Heart | C108: синий | D108: возможно | E108: цикл мастермайнда | F108: =VLOOKUP(O108,pearl!$B:$E,4,0) -> ♂ | G108: =VLOOKUP(IF(F108="Дом",H108,F108),pearl!$D$28:$F$32,3,0) -> Марс | H108: =VLOOKUP(O108,pearl!$B:$E,3,0) -> Щит♂ | I108: 10m, 1wp (5m, 1wp) | J108: Simple | K108: Psyche | L108: Indefinite | N108: Sid 247 | O108: Presence | P108: 5 | Q108: 3 | R108: 0 | S108: Force Decision
A109: Sidereal | B109: Avoiding-the-Truth Technique | C109: зеленый | F109: =VLOOKUP(O109,pearl!$B:$E,4,0) -> ♃ | G109: =VLOOKUP(IF(F109="Дом",H109,F109),pearl!$D$28:$F$32,3,0) -> Юпитер | H109: =VLOOKUP(O109,pearl!$B:$E,3,0) -> Сокровищница♃ | I109: 3m | J109: Supplemental | K109: Mute | L109: Instant | N109: Sid 272 | O109: Lore | P109: 3 | Q109: 1 | R109: 0 | S109: None
A110: Sidereal | B110: Incite Decorum | C110: зеленый | F110: =VLOOKUP(O110,pearl!$B:$E,4,0) -> ♃ | G110: =VLOOKUP(IF(F110="Дом",H110,F110),pearl!$D$28:$F$32,3,0) -> Юпитер | H110: =VLOOKUP(O110,pearl!$B:$E,3,0) -> Чародей♃ | I110: 5m | J110: Reflexive | K110: Mute | L110: One scene | N110: Sid 276 | O110: Occult | P110: 1 | Q110: 1 | R110: 0 | S110: None
A111: Sidereal | B111: Light of Celestial Revelation | C111: зеленый | F111: =VLOOKUP(O111,pearl!$B:$E,4,0) -> ♃ | G111: =VLOOKUP(IF(F111="Дом",H111,F111),pearl!$D$28:$F$32,3,0) -> Юпитер | H111: =VLOOKUP(O111,pearl!$B:$E,3,0) -> Чародей♃ | I111: - (2m) | J111: Permanent | K111: Mute | L111: Permanent | N111: Sid 276 | O111: Occult | P111: 2 | Q111: 1 | R111: 0 | S111: Mark of Exaltation
A112: Sidereal | B112: Manifestation-Haling Summons | C112: зеленый | F112: =VLOOKUP(O112,pearl!$B:$E,4,0) -> ♃ | G112: =VLOOKUP(IF(F112="Дом",H112,F112),pearl!$D$28:$F$32,3,0) -> Юпитер | H112: =VLOOKUP(O112,pearl!$B:$E,3,0) -> Чародей♃ | I112: Varies | J112: Simple | K112: Mute | L112: Instant | N112: Sid 277 | O112: Occult | P112: 2 | Q112: 1 | R112: 0 | S112: Mark of Exaltation
A113: Sidereal | B113: Mark of Exaltation | C113: зеленый | F113: =VLOOKUP(O113,pearl!$B:$E,4,0) -> ♃ | G113: =VLOOKUP(IF(F113="Дом",H113,F113),pearl!$D$28:$F$32,3,0) -> Юпитер | H113: =VLOOKUP(O113,pearl!$B:$E,3,0) -> Чародей♃ | I113: 4m | J113: Reflexive | K113: None | L113: One scene | N113: Sid 276 | O113: Occult | P113: 1 | Q113: 1 | R113: 0 | S113: None
A114: Sidereal | B114: Prince-of-the-Earth Attitude | C114: зеленый | F114: =VLOOKUP(O114,pearl!$B:$E,4,0) -> ♃ | G114: =VLOOKUP(IF(F114="Дом",H114,F114),pearl!$D$28:$F$32,3,0) -> Юпитер | H114: =VLOOKUP(O114,pearl!$B:$E,3,0) -> Чародей♃ | I114: - | J114: Permanent | K114: None | L114: Permanent | N114: Sid 276 | O114: Occult | P114: 3 | Q114: 1 | R114: 0 | S114: Incite Decorum
A115: Sidereal | B115: Tell-Tale Symphony | C115: зеленый | F115: =VLOOKUP(O115,pearl!$B:$E,4,0) -> ♃ | G115: =VLOOKUP(IF(F115="Дом",H115,F115),pearl!$D$28:$F$32,3,0) -> Юпитер | H115: =VLOOKUP(O115,pearl!$B:$E,3,0) -> Чародей♃ | I115: 3m | J115: Reflexive | K115: None | L115: One scene | N115: Sid 277 | O115: Occult | P115: 2 | Q115: 1 | R115: 0 | S115: Mark of Exaltation
A116: Sidereal | B116: Terrestrial Circle Sorcery | C116: зеленый | F116: =VLOOKUP(O116,pearl!$B:$E,4,0) -> ♃ | G116: =VLOOKUP(IF(F116="Дом",H116,F116),pearl!$D$28:$F$32,3,0) -> Юпитер | H116: =VLOOKUP(O116,pearl!$B:$E,3,0) -> Чародей♃ | I116: - | J116: Permanent | K116: None | L116: Permanent | N116: Sid 281 | O116: Occult | P116: 3 | Q116: 1 | R116: 0 | S116: Any four Secrets Charms
A117: Sidereal | B117: Legend-Dimming Obscurity | C117: зеленый | F117: =VLOOKUP(O117,pearl!$B:$E,4,0) -> ♃ | G117: =VLOOKUP(IF(F117="Дом",H117,F117),pearl!$D$28:$F$32,3,0) -> Юпитер | H117: =VLOOKUP(O117,pearl!$B:$E,3,0) -> Маска♃ | I117: - | J117: Permanent | K117: None | L117: Permanent | N117: Sid 282 | O117: Stealth | P117: 1 | Q117: 1 | R117: 0 | S117: None
A118: Sidereal | B118: Privacy-Enhancing Gesture | C118: зеленый | F118: =VLOOKUP(O118,pearl!$B:$E,4,0) -> ♃ | G118: =VLOOKUP(IF(F118="Дом",H118,F118),pearl!$D$28:$F$32,3,0) -> Юпитер | H118: =VLOOKUP(O118,pearl!$B:$E,3,0) -> Маска♃ | I118: 10m, 1wp | J118: Reflexive | K118: Mute, | L118: One day | N118: Sid 283 | O118: Stealth | P118: 3 | Q118: 1 | R118: 0 | S118: None
A119: Sidereal | B119: Unfettered by Law | C119: зеленый | F119: =VLOOKUP(O119,pearl!$B:$E,4,0) -> ♃ | G119: =VLOOKUP(IF(F119="Дом",H119,F119),pearl!$D$28:$F$32,3,0) -> Юпитер | H119: =VLOOKUP(O119,pearl!$B:$E,3,0) -> Маска♃ | I119: 10m, 1wp | J119: Reflexive | K119: Mute, Psyche | L119: One day | N119: Sid 285 | O119: Stealth | P119: 5 | Q119: 4 | R119: 0 | S119: Blinding the Boar, Privacy-Enhancing Gesture, Walking Outside Fate
A120: Sidereal | B120: Unwritten Words Revelation | C120: оранж | F120: =VLOOKUP(O120,pearl!$B:$E,4,0) -> ♃ | G120: =VLOOKUP(IF(F120="Дом",H120,F120),pearl!$D$28:$F$32,3,0) -> Юпитер | H120: =VLOOKUP(O120,pearl!$B:$E,3,0) -> Ключ♃ | I120: 5m | J120: Reflexive | K120: Mute | L120: Instant | N120: Sid 260 | O120: Investigate | P120: 3 | Q120: 1 | R120: 0 | S120: Marvelous Inclusion of Details
... A134: Sidereal | B134: Enticing Puzzle Exculpation | C134: синий | F134: =VLOOKUP(O134,pearl!$B:$E,4,0) -> Дом | G134: =VLOOKUP(IF(F134="Дом",H134,F134),pearl!$D$28:$F$32,3,0) -> Юпитер | H134: =VLOOKUP(O134,pearl!$B:$E,3,0) -> ♃ | I134: 6m | J134: Supplemental | K134: Mute | L134: Instant | N134: Sid 257 | O134: Secrets | P134: 3 | Q134: 1 | R134: 0 | S134: Any three Secrets Charms
A135: Sidereal | B135: Cosmos-Sustaining Demiurge | F135: =VLOOKUP(O135,pearl!$B:$E,4,0) -> ♀ | G135: =VLOOKUP(IF(F135="Дом",H135,F135),pearl!$D$28:$F$32,3,0) -> Венера | H135: =VLOOKUP(O135,pearl!$B:$E,3,0) -> ♀Павлин | I135: 20m, 1wp | J135: Simple | K135: Mute | L135: Instant | N135: Sid 197 | O135: Craft | P135: 5 | Q135: 3 | R135: 0 | S135: Mending Warped Designs
A136: Sidereal | B136: Excellent Implementation of Objectives | F136: =VLOOKUP(O136,pearl!$B:$E,4,0) -> ♀ | G136: =VLOOKUP(IF(F136="Дом",H136,F136),pearl!$D$28:$F$32,3,0) -> Венера | H136: =VLOOKUP(O136,pearl!$B:$E,3,0) -> ♀Павлин | I136: 8m | J136: Simple | K136: Mute | L136: Instant | N136: Sid 194 | O136: Craft | P136: 3 | Q136: 1 | R136: 0 | S136: None
A137: Sidereal | B137: Forge-and-Spindle Marriage | F137: =VLOOKUP(O137,pearl!$B:$E,4,0) -> ♀ | G137: =VLOOKUP(IF(F137="Дом",H137,F137),pearl!$D$28:$F$32,3,0) -> Венера | H137: =VLOOKUP(O137,pearl!$B:$E,3,0) -> ♀Павлин | I137: - | J137: Permanent | K137: None | L137: Permanent | N137: Sid 192 | O137: Craft | P137: 1 | Q137: 1 | R137: 0 | S137: None
A138: Sidereal | B138: Fortuitous Fellowship | F138: =VLOOKUP(O138,pearl!$B:$E,4,0) -> ♀ | G138: =VLOOKUP(IF(F138="Дом",H138,F138),pearl!$D$28:$F$32,3,0) -> Венера | H138: =VLOOKUP(O138,pearl!$B:$E,3,0) -> ♀Павлин | I138: 10m, 1wp | J138: Simple | K138: Mute, Shaping (Fate) | L138: Instant | N138: Sid 198 | O138: Craft | P138: 5 | Q138: 3 | R138: 0 | S138: Swan-and-Duckling Parable
A139: Sidereal | B139: Heaven-and-Hell Embassy | F139: =VLOOKUP(O139,pearl!$B:$E,4,0) -> ♀ | G139: =VLOOKUP(IF(F139="Дом",H139,F139),pearl!$D$28:$F$32,3,0) -> Венера | H139: =VLOOKUP(O139,pearl!$B:$E,3,0) -> ♀Павлин | I139: 5m, 1wp | J139: Simple | K139: None | L139: One day | N139: Sid 196 | O139: Craft | P139: 5 | Q139: 2 | R139: 0 | S139: Untangling Snarled Strands
A140: Sidereal | B140: Implicit Construction Methodology | F140: =VLOOKUP(O140,pearl!$B:$E,4,0) -> ♀ | G140: =VLOOKUP(IF(F140="Дом",H140,F140),pearl!$D$28:$F$32,3,0) -> Венера | H140: =VLOOKUP(O140,pearl!$B:$E,3,0) -> ♀Павлин | I140: 10m, 1wp, 1wxp per dot | J140: Simple | K140: None | L140: One project | N140: Sid 199 | O140: Craft | P140: 5 | Q140: 5 | R140: 0 | S140: Any ten Craft Charms
A141: Sidereal | B141: Proper Plumage | F141: =VLOOKUP(O141,pearl!$B:$E,4,0) -> ♀ | G141: =VLOOKUP(IF(F141="Дом",H141,F141),pearl!$D$28:$F$32,3,0) -> Венера | H141: =VLOOKUP(O141,pearl!$B:$E,3,0) -> ♀Павлин | I141: 5m, 1wp | J141: Simple | K141: None | L141: Until the Sidereal removes her outfit | N141: Sid 197 | O141: Craft | P141: 5 | Q141: 2 | R141: 0 | S141: Wife-Procuring Tailfeathers
A142: Sidereal | B142: Swan-and-Duckling Parable | F142: =VLOOKUP(O142,pearl!$B:$E,4,0) -> ♀ | G142: =VLOOKUP(IF(F142="Дом",H142,F142),pearl!$D$28:$F$32,3,0) -> Венера | H142: =VLOOKUP(O142,pearl!$B:$E,3,0) -> ♀Павлин | I142: - | J142: Permanent | K142: Stackable | L142: Permanent | N142: Sid 197 | O142: Craft | P142: 5 | Q142: 2 | R142: 0 | S142: Proper Plumage
A143: Sidereal | B143: Unassuming Vizier Wisdom | F143: =VLOOKUP(O143,pearl!$B:$E,4,0) -> ♀ | G143: =VLOOKUP(IF(F143="Дом",H143,F143),pearl!$D$28:$F$32,3,0) -> Венера | H143: =VLOOKUP(O143,pearl!$B:$E,3,0) -> ♀Павлин | I143: 10m, 1wp | J143: Simple | K143: None | L143: Indefinite | N143: Sid 198 | O143: Craft | P143: 5 | Q143: 4 | R143: 0 | S143: Fortuitous Fellowship
A144: Sidereal | B144: Unraveled Skein Insight | F144: =VLOOKUP(O144,pearl!$B:$E,4,0) -> ♀ | G144: =VLOOKUP(IF(F144="Дом",H144,F144),pearl!$D$28:$F$32,3,0) -> Венера | H144: =VLOOKUP(O144,pearl!$B:$E,3,0) -> ♀Павлин | I144: 6m | J144: Simple | K144: Mute | L144: Instant | N144: Sid 197 | O144: Craft | P144: 5 | Q144: 2 | R144: 0 | S144: Elegant Patterns of Fate
A145: Sidereal | B145: Wife-Procuring Tailfeathers | F145: =VLOOKUP(O145,pearl!$B:$E,4,0) -> ♀ | G145: =VLOOKUP(IF(F145="Дом",H145,F145),pearl!$D$28:$F$32,3,0) -> Венера | H145: =VLOOKUP(O145,pearl!$B:$E,3,0) -> ♀Павлин | I145: 4m, 1wp | J145: Simple | K145: Mute, Shaping (Fate) | L145: Indefinite | N145: Sid 193 | O145: Craft | P145: 4 | Q145: 1 | R145: 0 | S145: Atelier-and-Embassy Auspice
A146: Sidereal | B146: Delighted Maiden Mien | F146: =VLOOKUP(O146,pearl!$B:$E,4,0) -> ♀ | G146: =VLOOKUP(IF(F146="Дом",H146,F146),pearl!$D$28:$F$32,3,0) -> Венера | H146: =VLOOKUP(O146,pearl!$B:$E,3,0) -> ♀Кувшин | I146: - | J146: Permanent | K146: Mute | L146: Permanent | N146: Sid 200 | O146: Dodge | P146: 1 | Q146: 1 | R146: 0 | S146: None
... A165: Sidereal | B165: Beauty in Misfortune | F165: =VLOOKUP(O165,pearl!$B:$E,4,0) -> ♀ | G165: =VLOOKUP(IF(F165="Дом",H165,F165),pearl!$D$28:$F$32,3,0) -> Венера | H165: =VLOOKUP(O165,pearl!$B:$E,3,0) -> ♀Музыкант | I165: - | J165: Permanent | K165: None | L165: Permanent | N165: Sid 211 | O165: Performance | P165: 3 | Q165: 1 | R165: 0 | S165: None
A166: Sidereal | B166: Beauty in Misfortune (x2) | F166: =VLOOKUP(O166,pearl!$B:$E,4,0) -> ♀ | G166: =VLOOKUP(IF(F166="Дом",H166,F166),pearl!$D$28:$F$32,3,0) -> Венера | H166: =VLOOKUP(O166,pearl!$B:$E,3,0) -> ♀Музыкант | I166: 10m, 1wp | J166: Permanent | K166: None | L166: Permanent | M166: 1/story when sidereal fulfills an auspicious prospect according to charm requirements, end a Psyche effect she suffers | N166: Sid 211 | O166: Performance | P166: 5 | Q166: 3 | R166: 0 | S166: Beauty in Misfortune
...

Sheet pearl
A1: C/F | B1: Ability | C1: Навык | D1: Дом/Созвездие | E1: Дом | F1: зел | G1: син | H1: оранж | J1: Type | K1: Sidereal | P1: Type | Q1: Sidereal | X1: Type | Y1: Sidereal
A2: C | B2: Martial Arts | C2: Боевые искусства | D2: - | E2: все | X2: Abil. Min | Y2: 5
B3: Resistance | C3: Сопротивление | D3: ☿Мачта | E3: ☿ | F3: 1 | J3: Количество по полю Выбор | K3: Названия столбцов | P3: Количество по полю Выбор | Q3: Названия столбцов
B4: Ride | C4: Верховая езда | D4: ☿Посланник | E4: ☿ | J4: Названия строк | K4: зеленый | L4: синий | M4: оранж | N4: Общий итог | P4: Названия строк | Q4: зеленый | R4: синий | S4: оранж | T4: Общий итог | X4: Количество по полю Выбор | Y4: Названия столбцов
B5: Sail | C5: Парус. плавание | D5: ☿Капитан | E5: ☿ | J5: ☿ | K5: 5 | L5: 2 | N5: 7 | P5: вполне | Q5: 0.2 | R5: 0.083333333 | S5: 0 | T5: 0.28333333 | X5: Названия строк | Y5: зеленый | Z5: синий | AA5: оранж | AB5: Общий итог
B6: Survival | C6: Выживание | D6: ☿Штурвал | E6: ☿ | J6: Resistance | K6: 1 | N6: 1 | P6: возможно | Q6: 0.1 | R6: 0.18333333 | S6: 0 | T6: 0.28333333 | X6: ☿ | Z6: 1 | AB6: 1
A7: mb | B7: Thrown | C7: Метание | D7: ☿Чайка | E7: ☿ | F7: 2 | G7: 4 | J7: Thrown | K7: 4 | L7: 2 | N7: 6 | P7: проблемы с гороскопами | Q7: 0.05 | R7: 0.033333333 | S7: 0.016666667 | T7: 0.1 | X7: Thrown | Z7: 1 | AB7: 1
A8: C | B8: Craft | C8: Ремесло | D8: ♀Павлин | E8: ♀ | F8: 8 | G8: 2 | H8: 1 | J8: ♀ | K8: 29 | L8: 11 | M8: 2 | N8: 42 | P8: вряд ли | Q8: 0.05 | R8: 0.05 | S8: 0 | T8: 0.1 | X8: ♀ | Y8: 2 | Z8: 5 | AA8: 1 | AB8: 8
A9: C | B9: Dodge | C9: Уклонение | D9: ♀Кувшин | E9: ♀ | F9: 6 | G9: 3 | J9: Craft | K9: 8 | L9: 2 | M9: 1 | N9: 11 | P9: тема не та | Q9: 0 | R9: 0.13333333 | S9: 0.05 | T9: 0.18333333 | X9: Craft | Y9: 1 | Z9: 1 | AB9: 2
A10: C | B10: Linguistics | C10: Лингвистика | D10: ♀Колонна | E10: ♀ | F10: 4 | G10: 2 | J10: Dodge | K10: 6 | L10: 3 | N10: 9 | P10: скучно | Q10: 0.033333333 | R10: 0.016666667 | S10: 0 | T10: 0.05 | X10: Dodge | Y10: 1 | Z10: 2 | AB10: 3
A11: C | B11: Performance | C11: Выступление | D11: ♀Музыкант | E11: ♀ | F11: 4 | G11: 2 | J11: Linguistics | K11: 4 | L11: 2 | N11: 6 | P11: Общий итог | Q11: 0.43333333 | R11: 0.5 | S11: 0.066666667 | T11: 1 | X11: Linguistics | Z11: 1 | AB11: 1
A12: C | B12: Socialize | C12: Социализация | D12: ♀Любовники | E12: ♀ | F12: 7 | G12: 2 | H12: 1 | J12: Performance | K12: 4 | L12: 2 | N12: 6 | X12: Socialize | Z12: 1 | AA12: 1 | AB12: 2
B13: Archery | C13: Стрельба | D13: Колчан♂ | E13: ♂ | J13: Socialize | K13: 7 | L13: 2 | M13: 1 | N13: 10 | X13: ♂ | Z13: 4 | AA13: 1 | AB13: 5
B14: Brawl | C14: Драка | D14: Перчатка♂ | E14: ♂ | J14: ♂ | K14: 4 | L14: 10 | M14: 1 | N14: 15 | X14: Melee | AA14: 1 | AB14: 1
B15: Melee | C15: Ближний бой | D15: Копье♂ | E15: ♂ | F15: 0 | G15: 2 | H15: 1 | J15: Melee | L15: 2 | M15: 1 | N15: 3 | X15: Presence | Z15: 4 | AB15: 4
A16: F | B16: Presence | C16: Присутствие | D16: Щит♂ | E16: ♂ | F16: 4 | G16: 8 | J16: Presence | K16: 4 | L16: 8 | N16: 12 | P16: Type | Q16: Sidereal | X16: ♃ | Y16: 1 | Z16: 3 | AB16: 4
B17: War | C17: Война | D17: Знамя♂ | E17: ♂ | J17: ♃ | K17: 11 | L17: 7 | M17: 6 | N17: 24 | Q17: =SUM(Q20:Q22)/GETPIVOTDATA("Выбор",$P$18,"Дева",Q19) -> 0.72727273 | R17: =SUM(R20:R22)/GETPIVOTDATA("Выбор",$P$18,"Дева",R19) -> 0.040816327 | S17: =SUM(S20:S22)/GETPIVOTDATA("Выбор",$P$18,"Дева",S19) -> 0.52941176 | T17: =SUM(T20:T22)/GETPIVOTDATA("Выбор",$P$18,"Дева",T19) -> 0.037037037 | U17: =SUM(U20:U22)/GETPIVOTDATA("Выбор",$P$18,"Дева",U19) -> 0.68965517 | X17: Occult | Z17: 1 | AB17: 1
B18: Investigate | C18: Расследование | D18: Ключ♃ | E18: ♃ | F18: 0 | G18: 1 | H18: 1 | J18: Investigate | L18: 1 | M18: 1 | N18: 2 | P18: Количество по полю Выбор | Q18: Названия столбцов | X18: Stealth | Y18: 1 | Z18: 2 | AB18: 3
B19: Larceny | C19: Кража | D19: Стражи♃ | E19: ♃ | F19: 0 | G19: 0 | H19: 3 | J19: Larceny | M19: 3 | N19: 3 | P19: Названия строк | Q19: Меркурий | R19: Венера | S19: Марс | T19: Юпитер | U19: Сатурн | V19: Общий итог | X19: ♄ | Z19: 5 | AB19: 5
A20: mb | B20: Lore | C20: Знания | D20: Сокровищница♃ | E20: ♃ | F20: 1 | G20: 2 | H20: 1 | J20: Lore | K20: 1 | L20: 2 | M20: 1 | N20: 4 | P20: вполне | Q20: 5 | S20: 4 | U20: 8 | V20: 17 | X20: Awareness | Z20: 3 | AB20: 3
A21: F | B21: Occult | C21: Оккультизм | D21: Чародей♃ | E21: ♃ | F21: 7 | G21: 2 | H21: 1 | J21: Occult | K21: 7 | L21: 2 | M21: 1 | N21: 10 | P21: возможно | Q21: 1 | S21: 5 | U21: 11 | V21: 17 | X21: Integrity | Z21: 1 | AB21: 1
B22: Stealth | C22: Скрытность | D22: Маска♃ | E22: ♃ | F22: 3 | G22: 2 | J22: Stealth | K22: 3 | L22: 2 | N22: 5 | P22: проблемы с гороскопами | Q22: 2 | R22: 2 | T22: 1 | U22: 1 | V22: 6 | X22: Medicine | Z22: 1 | AB22: 1
B23: Athletics | C23: Атлетика | D23: ♄Восходящий Дым | E23: ♄ | F23: 1 | G23: 0 | H23: 2 | J23: ♄ | K23: 10 | L23: 14 | M23: 2 | N23: 26 | P23: вряд ли | Q23: 2 | S23: 3 | U23: 1 | V23: 6 | X23: Дом | Y23: 1 | Z23: 1 | AB23: 2
B24: Awareness | C24: Бдительность | D24: ♄Ворон | E24: ♄ | F24: 7 | G24: 3 | J24: Athletics | K24: 1 | M24: 2 | N24: 3 | P24: (пусто) | R24: 47 | T24: 26 | V24: 73 | X24: Serenities | Y24: 1 | Z24: 1 | AB24: 2
A25: mb | B25: Bureaucracy | C25: Бюрократия | D25: ♄Телега с сеном | E25: ♄ | F25: 2 | J25: Awareness | K25: 7 | L25: 4 | N25: 11 | P25: тема не та | S25: 3 | U25: 8 | V25: 11 | X25: Общий итог | Y25: 4 | Z25: 19 | AA25: 2 | AB25: 25
A26: mb | B26: Integrity | C26: Целостность | D26: ♄Меч | E26: ♄ | F26: 0 | G26: 4 | J26: Bureaucracy | K26: 2 | N26: 2 | P26: скучно | Q26: 1 | S26: 2 | V26: 3
B27: Medicine | C27: Медицина | D27: ♄Труп | E27: ♄ | F27: 0 | G27: 6 | J27: Integrity | L27: 4 | N27: 4 | P27: Общий итог | Q27: 11 | R27: 49 | S27: 17 | T27: 27 | U27: 29 | V27: 133
B28: Battles | D28: ♂ | E28: Дом | F28: Марс | J28: Medicine | L28: 6 | N28: 6
B29: Endings | D29: ♄ | E29: Дом | F29: Сатурн | J29: Дом | K29: 9 | L29: 7 | M29: 3 | N29: 19
B30: Journeys | D30: ☿ | E30: Дом | F30: Меркурий | J30: Journeys | K30: 2 | L30: 2 | N30: 4
B31: Secrets | D31: ♃ | E31: Дом | F31: Юпитер | J31: Serenities | K31: 4 | L31: 2 | M31: 1 | N31: 7
B32: Serenities | D32: ♀ | E32: Дом | F32: Венера | J32: Battles | L32: 2 | N32: 2
J33: Secrets | L33: 1 | M33: 2 | N33: 3
J34: Endings | K34: 3 | N34: 3
J35: Общий итог | K35: 68 | L35: 51 | M35: 14 | N35: 133

Sheet Лист1
A1: Skill 1 | B1: Skill 1 | C1: Skill 2 | D1: ы | E1: Skill 3 | F1: 123 | L1: Code | M1: Ability | N1: Группы | O1: Solar Castes | P1: Siderial Castes
A2: 0 | C2: =CHAR(63+D2) -> A | D2: 2 | E2: A | F2: =A2&C2&E2 -> 0AA | H2: =CHAR(63+ROW()) -> A | L2: A | M2: Archery | N2: Dawn | O2: dawn | P2: Марс
A3: 1 | C3: =C2 -> A | D3: =D2 -> 2 | E3: B | F3: =A3&C3&E3 -> 1AB | I3: =26*25*24 -> 15600 | L3: B | M3: Athletics | N3: Bang | O3: zenith, night | P3: Сатурн
A4: 2 | C4: =C3 -> A | D4: =D3 -> 2 | E4: C | F4: =A4&C4&E4 -> 2AC | I4: =I3/6 -> 2600 | L4: C | M4: Awareness | N4: Dawn | O4: dawn, night | P4: Сатурн
A5: 3 | C5: =C4 -> A | D5: =D4 -> 2 | E5: D | F5: =A5&C5&E5 -> 3AD | L5: D | M5: Brawl | N5: Dawn | O5: dawn | P5: Марс
A6: 4 | C6: =C5 -> A | D6: =D5 -> 2 | E6: E | F6: =A6&C6&E6 -> 4AE | L6: E | M6: Bureaucracy | N6: - | O6: twilight, eclipse | P6: Сатурн
A7: 5 | C7: =C6 -> A | D7: =D6 -> 2 | E7: F | F7: =A7&C7&E7 -> 5AF | L7: F | M7: Craft | N7: Venus | O7: twilight | P7: Венера
A8: 6 | C8: =C7 -> A | D8: =D7 -> 2 | E8: G | F8: =A8&C8&E8 -> 6AG | L8: G | M8: Dodge | N8: siblings | O8: dawn, night | P8: Венера
A9: 7 | C9: =C8 -> A | D9: =D8 -> 2 | E9: H | F9: =A9&C9&E9 -> 7AH | L9: H | M9: Integrity | N9: Bang | O9: zenith, twilight | P9: Сатурн
A10: 8 | C10: =C9 -> A | D10: =D9 -> 2 | E10: I | F10: =A10&C10&E10 -> 8AI | L10: I | M10: Investigate | N10: - | O10: twilight, night | P10: Юпитер
A11: 9 | C11: =C10 -> A | D11: =D10 -> 2 | E11: J | F11: =A11&C11&E11 -> 9AJ | L11: J | M11: Larceny | N11: - | O11: night, eclipse | P11: Юпитер
A12: 10 | C12: =C11 -> A | D12: =D11 -> 2 | E12: K | F12: =A12&C12&E12 -> 10AK | L12: K | M12: Linguistics | N12: Venus | O12: twilight, eclipse | P12: Венера
A13: 11 | C13: =C12 -> A | D13: =D12 -> 2 | E13: L | F13: =A13&C13&E13 -> 11AL | L13: L | M13: Lore | N13: - | O13: zenith, twilight | P13: Юпитер
A14: 12 | C14: =C13 -> A | D14: =D13 -> 2 | E14: M | F14: =A14&C14&E14 -> 12AM | L14: M | M14: Martial Arts | N14: siblings | O14: - | P14: все
A15: 13 | C15: =C14 -> A | D15: =D14 -> 2 | E15: N | F15: =A15&C15&E15 -> 13AN | L15: N | M15: Medicine | N15: - | O15: twilight | P15: Сатурн
A16: 14 | C16: =C15 -> A | D16: =D15 -> 2 | E16: O | F16: =A16&C16&E16 -> 14AO | L16: O | M16: Melee | N16: Dawn | O16: dawn | P16: Марс
... A27: 25 | C27: =C26 -> A | D27: =D26 -> 2 | E27: Z | F27: =A27&C27&E27 -> 25AZ | L27: Z | M27: War | N27: Dawn | O27: dawn, zenith | P27: Марс
A28: 0 | C28: =CHAR(63+D28) -> B | D28: =D2+1 -> 3 | E28: =E2 -> A | F28: =A28&C28&E28 -> 0BA
A29: 1 | C29: =C28 -> B | D29: =D28 -> 3 | E29: =E3 -> B | F29: =A29&C29&E29 -> 1BB
A30: 2 | C30: =C29 -> B | D30: =D29 -> 3 | E30: =E4 -> C | F30: =A30&C30&E30 -> 2BC
A31: 3 | C31: =C30 -> B | D31: =D30 -> 3 | E31: =E5 -> D | F31: =A31&C31&E31 -> 3BD
A32: 4 | C32: =C31 -> B | D32: =D31 -> 3 | E32: =E6 -> E | F32: =A32&C32&E32 -> 4BE
A33: 5 | C33: =C32 -> B | D33: =D32 -> 3 | E33: =E7 -> F | F33: =A33&C33&E33 -> 5BF
A34: 6 | C34: =C33 -> B | D34: =D33 -> 3 | E34: =E8 -> G | F34: =A34&C34&E34 -> 6BG
A35: 7 | C35: =C34 -> B | D35: =D34 -> 3 | E35: =E9 -> H | F35: =A35&C35&E35 -> 7BH
A36: 8 | C36: =C35 -> B | D36: =D35 -> 3 | E36: =E10 -> I | F36: =A36&C36&E36 -> 8BI
A37: 9 | C37: =C36 -> B | D37: =D36 -> 3 | E37: =E11 -> J | F37: =A37&C37&E37 -> 9BJ
A38: 10 | C38: =C37 -> B | D38: =D37 -> 3 | E38: =E12 -> K | F38: =A38&C38&E38 -> 10BK
A39: 11 | C39: =C38 -> B | D39: =D38 -> 3 | E39: =E13 -> L | F39: =A39&C39&E39 -> 11BL
A40: 12 | C40: =C39 -> B | D40: =D39 -> 3 | E40: =E14 -> M | F40: =A40&C40&E40 -> 12BM
... A53: 25 | C53: =C52 -> B | D53: =D52 -> 3 | E53: =E27 -> Z | F53: =A53&C53&E53 -> 25BZ
A54: 0 | C54: =CHAR(63+D54) -> B | D54: =D53 -> 3 | E54: =E28 -> A | F54: =A54&C54&E54 -> 0BA
A55: 1 | C55: =C54 -> B | D55: =D54 -> 3 | E55: =E29 -> B | F55: =A55&C55&E55 -> 1BB
A56: 2 | C56: =C55 -> B | D56: =D55 -> 3 | E56: =E30 -> C | F56: =A56&C56&E56 -> 2BC
A57: 3 | C57: =C56 -> B | D57: =D56 -> 3 | E57: =E31 -> D | F57: =A57&C57&E57 -> 3BD
A58: 4 | C58: =C57 -> B | D58: =D57 -> 3 | E58: =E32 -> E | F58: =A58&C58&E58 -> 4BE
A59: 5 | C59: =C58 -> B | D59: =D58 -> 3 | E59: =E33 -> F | F59: =A59&C59&E59 -> 5BF
A60: 6 | C60: =C59 -> B | D60: =D59 -> 3 | E60: =E34 -> G | F60: =A60&C60&E60 -> 6BG
A61: 7 | C61: =C60 -> B | D61: =D60 -> 3 | E61: =E35 -> H | F61: =A61&C61&E61 -> 7BH
A62: 8 | C62: =C61 -> B | D62: =D61 -> 3 | E62: =E36 -> I | F62: =A62&C62&E62 -> 8BI
A63: 9 | C63: =C62 -> B | D63: =D62 -> 3 | E63: =E37 -> J | F63: =A63&C63&E63 -> 9BJ
A64: 10 | C64: =C63 -> B | D64: =D63 -> 3 | E64: =E38 -> K | F64: =A64&C64&E64 -> 10BK
A65: 11 | C65: =C64 -> B | D65: =D64 -> 3 | E65: =E39 -> L | F65: =A65&C65&E65 -> 11BL
A66: 12 | C66: =C65 -> B | D66: =D65 -> 3 | E66: =E40 -> M | F66: =A66&C66&E66 -> 12BM
... A79: 25 | C79: =C78 -> B | D79: =D78 -> 3 | E79: =E53 -> Z | F79: =A79&C79&E79 -> 25BZ
A80: 0 | C80: =CHAR(63+D80) -> B | D80: =D79 -> 3 | E80: =E54 -> A | F80: =A80&C80&E80 -> 0BA
A81: 1 | C81: =C80 -> B | D81: =D80 -> 3 | E81: =E55 -> B | F81: =A81&C81&E81 -> 1BB
A82: 2 | C82: =C81 -> B | D82: =D81 -> 3 | E82: =E56 -> C | F82: =A82&C82&E82 -> 2BC
A83: 3 | C83: =C82 -> B | D83: =D82 -> 3 | E83: =E57 -> D | F83: =A83&C83&E83 -> 3BD
A84: 4 | C84: =C83 -> B | D84: =D83 -> 3 | E84: =E58 -> E | F84: =A84&C84&E84 -> 4BE
A85: 5 | C85: =C84 -> B | D85: =D84 -> 3 | E85: =E59 -> F | F85: =A85&C85&E85 -> 5BF
A86: 6 | C86: =C85 -> B | D86: =D85 -> 3 | E86: =E60 -> G | F86: =A86&C86&E86 -> 6BG
A87: 7 | C87: =C86 -> B | D87: =D86 -> 3 | E87: =E61 -> H | F87: =A87&C87&E87 -> 7BH
A88: 8 | C88: =C87 -> B | D88: =D87 -> 3 | E88: =E62 -> I | F88: =A88&C88&E88 -> 8BI
A89: 9 | C89: =C88 -> B | D89: =D88 -> 3 | E89: =E63 -> J | F89: =A89&C89&E89 -> 9BJ
A90: 10 | C90: =C89 -> B | D90: =D89 -> 3 | E90: =E64 -> K | F90: =A90&C90&E90 -> 10BK
A91: 11 | C91: =C90 -> B | D91: =D90 -> 3 | E91: =E65 -> L | F91: =A91&C91&E91 -> 11BL
A92: 12 | C92: =C91 -> B | D92: =D91 -> 3 | E92: =E66 -> M | F92: =A92&C92&E92 -> 12BM
... A105: 25 | C105: =C104 -> B | D105: =D104 -> 3 | E105: =E79 -> Z | F105: =A105&C105&E105 -> 25BZ
A106: 0 | C106: =CHAR(63+D106) -> B | D106: =D105 -> 3 | E106: =E80 -> A | F106: =A106&C106&E106 -> 0BA
A107: 1 | C107: =C106 -> B | D107: =D106 -> 3 | E107: =E81 -> B | F107: =A107&C107&E107 -> 1BB
A108: 2 | C108: =C107 -> B | D108: =D107 -> 3 | E108: =E82 -> C | F108: =A108&C108&E108 -> 2BC
A109: 3 | C109: =C108 -> B | D109: =D108 -> 3 | E109: =E83 -> D | F109: =A109&C109&E109 -> 3BD
A110: 4 | C110: =C109 -> B | D110: =D109 -> 3 | E110: =E84 -> E | F110: =A110&C110&E110 -> 4BE
A111: 5 | C111: =C110 -> B | D111: =D110 -> 3 | E111: =E85 -> F | F111: =A111&C111&E111 -> 5BF
A112: 6 | C112: =C111 -> B | D112: =D111 -> 3 | E112: =E86 -> G | F112: =A112&C112&E112 -> 6BG
A113: 7 | C113: =C112 -> B | D113: =D112 -> 3 | E113: =E87 -> H | F113: =A113&C113&E113 -> 7BH
A114: 8 | C114: =C113 -> B | D114: =D113 -> 3 | E114: =E88 -> I | F114: =A114&C114&E114 -> 8BI
A115: 9 | C115: =C114 -> B | D115: =D114 -> 3 | E115: =E89 -> J | F115: =A115&C115&E115 -> 9BJ
A116: 10 | C116: =C115 -> B | D116: =D115 -> 3 | E116: =E90 -> K | F116: =A116&C116&E116 -> 10BK
A117: 11 | C117: =C116 -> B | D117: =D116 -> 3 | E117: =E91 -> L | F117: =A117&C117&E117 -> 11BL
A118: 12 | C118: =C117 -> B | D118: =D117 -> 3 | E118: =E92 -> M | F118: =A118&C118&E118 -> 12BM
... A131: 25 | C131: =C130 -> B | D131: =D130 -> 3 | E131: =E105 -> Z | F131: =A131&C131&E131 -> 25BZ
A132: 0 | C132: =CHAR(63+D132) -> B | D132: =D131 -> 3 | E132: =E106 -> A | F132: =A132&C132&E132 -> 0BA
A133: 1 | C133: =C132 -> B | D133: =D132 -> 3 | E133: =E107 -> B | F133: =A133&C133&E133 -> 1BB
A134: 2 | C134: =C133 -> B | D134: =D133 -> 3 | E134: =E108 -> C | F134: =A134&C134&E134 -> 2BC
A135: 3 | C135: =C134 -> B | D135: =D134 -> 3 | E135: =E109 -> D | F135: =A135&C135&E135 -> 3BD
A136: 4 | C136: =C135 -> B | D136: =D135 -> 3 | E136: =E110 -> E | F136: =A136&C136&E136 -> 4BE
A137: 5 | C137: =C136 -> B | D137: =D136 -> 3 | E137: =E111 -> F | F137: =A137&C137&E137 -> 5BF
A138: 6 | C138: =C137 -> B | D138: =D137 -> 3 | E138: =E112 -> G | F138: =A138&C138&E138 -> 6BG
A139: 7 | C139: =C138 -> B | D139: =D138 -> 3 | E139: =E113 -> H | F139: =A139&C139&E139 -> 7BH
A140: 8 | C140: =C139 -> B | D140: =D139 -> 3 | E140: =E114 -> I | F140: =A140&C140&E140 -> 8BI
A141: 9 | C141: =C140 -> B | D141: =D140 -> 3 | E141: =E115 -> J | F141: =A141&C141&E141 -> 9BJ
A142: 10 | C142: =C141 -> B | D142: =D141 -> 3 | E142: =E116 -> K | F142: =A142&C142&E142 -> 10BK
A143: 11 | C143: =C142 -> B | D143: =D142 -> 3 | E143: =E117 -> L | F143: =A143&C143&E143 -> 11BL
A144: 12 | C144: =C143 -> B | D144: =D143 -> 3 | E144: =E118 -> M | F144: =A144&C144&E144 -> 12BM
... A157: 25 | C157: =C156 -> B | D157: =D156 -> 3 | E157: =E131 -> Z | F157: =A157&C157&E157 -> 25BZ
A158: 0 | D158: =D157 -> 3 | E158: =E132 -> A | F158: =A158&C158&E158 -> 0A
A159: 1 | D159: =D158 -> 3 | E159: =E133 -> B | F159: =A159&C159&E159 -> 1B
A160: 2 | D160: =D159 -> 3 | E160: =E134 -> C | F160: =A160&C160&E160 -> 2C
A161: 3 | D161: =D160 -> 3 | E161: =E135 -> D | F161: =A161&C161&E161 -> 3D
A162: 4 | D162: =D161 -> 3 | E162: =E136 -> E | F162: =A162&C162&E162 -> 4E
A163: 5 | D163: =D162 -> 3 | E163: =E137 -> F | F163: =A163&C163&E163 -> 5F
A164: 6 | D164: =D163 -> 3 | E164: =E138 -> G | F164: =A164&C164&E164 -> 6G
A165: 7 | D165: =D164 -> 3 | E165: =E139 -> H | F165: =A165&C165&E165 -> 7H
A166: 8 | D166: =D165 -> 3 | E166: =E140 -> I | F166: =A166&C166&E166 -> 8I
A167: 9 | D167: =D166 -> 3 | E167: =E141 -> J | F167: =A167&C167&E167 -> 9J
A168: 10 | D168: =D167 -> 3 | E168: =E142 -> K | F168: =A168&C168&E168 -> 10K
A169: 11 | D169: =D168 -> 3 | E169: =E143 -> L | F169: =A169&C169&E169 -> 11L
... A700: 22 | D700: =D699 -> 3 | E700: =E674 -> W | F700: =A700&C700&E700 -> 22W
...

Sheet trials
A1: q | B1: color | C1: испытание | D1: блок | E1: Камни | F1: счет камня | G1: комментарий | H1: навык 1 | I1: навык 2 | J1: навык 3 | K1: н1 | L1: н2 | M1: н3 | N1: дева 1 | O1: дева 2 | P1: дева 3 | S1: блок | T1: (несколько элементов)
A2: 1 | B2: -1 | C2: 1. «Тень Героя» | D2: 45889 | E2: топаз | F2: =COUNTIF(N2:P2,E2) -> 0 | G2: неее | H2: Integrity | I2: Lore | J2: Presence | K2: =VLOOKUP(H2,Лист2!$A:$F,2,FALSE) -> 3 | L2: =VLOOKUP(I2,Лист2!$A:$F,2,FALSE) -> 0 | M2: =VLOOKUP(J2,Лист2!$A:$F,2,FALSE) -> 3 | N2: =VLOOKUP(H2,Лист2!$A:$F,6,FALSE) -> аметист | O2: =VLOOKUP(I2,Лист2!$A:$F,6,FALSE) -> изумруд | P2: =VLOOKUP(J2,Лист2!$A:$F,6,FALSE) -> рубин
A3: 4 | B3: -1 | C3: 4. «Судья и Палач» | D3: 45889 | E3: рубин | F3: =COUNTIF(N3:P3,E3) -> 2 | G3: перебор для 1 из5 испытания | H3: Socialize | I3: War | J3: Melee | K3: =VLOOKUP(H3,Лист2!$A:$F,2,FALSE) -> 0 | L3: =VLOOKUP(I3,Лист2!$A:$F,2,FALSE) -> 2 | M3: =VLOOKUP(J3,Лист2!$A:$F,2,FALSE) -> 0 | N3: =VLOOKUP(H3,Лист2!$A:$F,6,FALSE) -> сапфир | O3: =VLOOKUP(I3,Лист2!$A:$F,6,FALSE) -> рубин | P3: =VLOOKUP(J3,Лист2!$A:$F,6,FALSE) -> рубин | S3: Количество по полю испытание | T3: Названия столбцов
A4: 12 | B4: -1 | C4: 12. «Гонка на Краю» | D4: 45889 | F4: =COUNTIF(N4:P4,E4) -> 0 | G4: неее | H4: Ride | I4: Athletics | J4: Survival | K4: =VLOOKUP(H4,Лист2!$A:$F,2,FALSE) -> 0 | L4: =VLOOKUP(I4,Лист2!$A:$F,2,FALSE) -> 3 | M4: =VLOOKUP(J4,Лист2!$A:$F,2,FALSE) -> 1 | N4: =VLOOKUP(H4,Лист2!$A:$F,6,FALSE) -> топаз | O4: =VLOOKUP(I4,Лист2!$A:$F,6,FALSE) -> аметист | P4: =VLOOKUP(J4,Лист2!$A:$F,6,FALSE) -> топаз | S4: Названия строк | T4: -1 | U4: 0 | V4: 1 | W4: Общий итог
A5: 13 | B5: -1 | C5: 13. «Театр Теней» | D5: 45889 | E5: сапфир | F5: =COUNTIF(N5:P5,E5) -> 2 | G5: неее | H5: Performance | I5: Occult | J5: Socialize | K5: =VLOOKUP(H5,Лист2!$A:$F,2,FALSE) -> 0 | L5: =VLOOKUP(I5,Лист2!$A:$F,2,FALSE) -> 0 | M5: =VLOOKUP(J5,Лист2!$A:$F,2,FALSE) -> 0 | N5: =VLOOKUP(H5,Лист2!$A:$F,6,FALSE) -> сапфир | O5: =VLOOKUP(I5,Лист2!$A:$F,6,FALSE) -> изумруд | P5: =VLOOKUP(J5,Лист2!$A:$F,6,FALSE) -> сапфир | S5: (пусто) | T5: 4 | U5: 3 | W5: 7
A6: 15 | B6: -1 | C6: 15. «Пламя Лукши» | D6: 45889 | F6: =COUNTIF(N6:P6,E6) -> 0 | G6: неее | H6: Brawl | I6: Survival | J6: War | K6: =VLOOKUP(H6,Лист2!$A:$F,2,FALSE) -> 1 | L6: =VLOOKUP(I6,Лист2!$A:$F,2,FALSE) -> 1 | M6: =VLOOKUP(J6,Лист2!$A:$F,2,FALSE) -> 2 | N6: =VLOOKUP(H6,Лист2!$A:$F,6,FALSE) -> рубин | O6: =VLOOKUP(I6,Лист2!$A:$F,6,FALSE) -> топаз | P6: =VLOOKUP(J6,Лист2!$A:$F,6,FALSE) -> рубин | S6: топаз | T6: 4 | U6: 1 | V6: 3 | W6: 8
A7: 16 | B7: -1 | C7: 16. «Тень Отца» | D7: 45889 | E7: изумруд | F7: =COUNTIF(N7:P7,E7) -> 1 | G7: неее | H7: Stealth | I7: Presence | J7: Integrity | K7: =VLOOKUP(H7,Лист2!$A:$F,2,FALSE) -> 3 | L7: =VLOOKUP(I7,Лист2!$A:$F,2,FALSE) -> 3 | M7: =VLOOKUP(J7,Лист2!$A:$F,2,FALSE) -> 3 | N7: =VLOOKUP(H7,Лист2!$A:$F,6,FALSE) -> изумруд | O7: =VLOOKUP(I7,Лист2!$A:$F,6,FALSE) -> рубин | P7: =VLOOKUP(J7,Лист2!$A:$F,6,FALSE) -> аметист | S7: сапфир | T7: 2 | U7: 2 | V7: 3 | W7: 7
A8: 17 | B8: -1 | C8: 17. «Цена Свободы» | D8: 45889 | F8: =COUNTIF(N8:P8,E8) -> 0 | G8: неее | H8: Larceny | I8: Athletics | J8: Socialize | K8: =VLOOKUP(H8,Лист2!$A:$F,2,FALSE) -> 0 | L8: =VLOOKUP(I8,Лист2!$A:$F,2,FALSE) -> 3 | M8: =VLOOKUP(J8,Лист2!$A:$F,2,FALSE) -> 0 | N8: =VLOOKUP(H8,Лист2!$A:$F,6,FALSE) -> изумруд | O8: =VLOOKUP(I8,Лист2!$A:$F,6,FALSE) -> аметист | P8: =VLOOKUP(J8,Лист2!$A:$F,6,FALSE) -> сапфир | S8: рубин | T8: 4 | U8: 1 | V8: 1 | W8: 6
A9: 19 | B9: -1 | C9: 19. «Судьба Бунтаря» | D9: 45889 | F9: =COUNTIF(N9:P9,E9) -> 0 | G9: неее | H9: Investigation | I9: Occult | J9: Linguistics | K9: =VLOOKUP(H9,Лист2!$A:$F,2,FALSE) -> 0 | L9: =VLOOKUP(I9,Лист2!$A:$F,2,FALSE) -> 0 | M9: =VLOOKUP(J9,Лист2!$A:$F,2,FALSE) -> 0 | N9: =VLOOKUP(H9,Лист2!$A:$F,6,FALSE) -> изумруд | O9: =VLOOKUP(I9,Лист2!$A:$F,6,FALSE) -> изумруд | P9: =VLOOKUP(J9,Лист2!$A:$F,6,FALSE) -> сапфир | S9: изумруд | T9: 4 | U9: 2 | V9: 4 | W9: 10
A10: 20 | B10: -1 | C10: Хроники Забвения | D10: 45892 | E10: топаз | F10: =COUNTIF(N10:P10,E10) -> 0 | G10: интересно, но не для 1/5 испытаний | K10: =VLOOKUP(H10,Лист2!$A:$F,2,FALSE) -> #N/A | L10: =VLOOKUP(I10,Лист2!$A:$F,2,FALSE) -> #N/A | M10: =VLOOKUP(J10,Лист2!$A:$F,2,FALSE) -> #N/A | N10: =VLOOKUP(H10,Лист2!$A:$F,6,FALSE) -> #N/A | O10: =VLOOKUP(I10,Лист2!$A:$F,6,FALSE) -> #N/A | P10: =VLOOKUP(J10,Лист2!$A:$F,6,FALSE) -> #N/A | S10: аметист | U10: 3 | V10: 5 | W10: 8
A11: 21 | B11: -1 | C11: Симфония Безмолвия | D11: 45892 | E11: сапфир | F11: =COUNTIF(N11:P11,E11) -> 0 | G11: сложно для того, чтобы угадать | K11: =VLOOKUP(H11,Лист2!$A:$F,2,FALSE) -> #N/A | L11: =VLOOKUP(I11,Лист2!$A:$F,2,FALSE) -> #N/A | M11: =VLOOKUP(J11,Лист2!$A:$F,2,FALSE) -> #N/A | N11: =VLOOKUP(H11,Лист2!$A:$F,6,FALSE) -> #N/A | O11: =VLOOKUP(I11,Лист2!$A:$F,6,FALSE) -> #N/A | P11: =VLOOKUP(J11,Лист2!$A:$F,6,FALSE) -> #N/A | S11: Общий итог | T11: 18 | U11: 12 | V11: 16 | W11: 46
A12: 26 | B12: -1 | C12: 2. Немой Свидетель** | D12: 45894 | E12: топаз | F12: =COUNTIF(N12:P12,E12) -> 0 | G12: не | H12: Awareness | I12: Occult | J12: Linguistics | K12: =VLOOKUP(H12,Лист2!$A:$F,2,FALSE) -> 3 | L12: =VLOOKUP(I12,Лист2!$A:$F,2,FALSE) -> 0 | M12: =VLOOKUP(J12,Лист2!$A:$F,2,FALSE) -> 0 | N12: =VLOOKUP(H12,Лист2!$A:$F,6,FALSE) -> аметист | O12: =VLOOKUP(I12,Лист2!$A:$F,6,FALSE) -> изумруд | P12: =VLOOKUP(J12,Лист2!$A:$F,6,FALSE) -> сапфир
A13: 27 | B13: -1 | C13: 3. Суд Мёртвых Героев** | D13: 45894 | E13: топаз | F13: =COUNTIF(N13:P13,E13) -> 0 | G13: не.скучно | H13: Socialize | I13: Lore | J13: Integrity | K13: =VLOOKUP(H13,Лист2!$A:$F,2,FALSE) -> 0 | L13: =VLOOKUP(I13,Лист2!$A:$F,2,FALSE) -> 0 | M13: =VLOOKUP(J13,Лист2!$A:$F,2,FALSE) -> 3 | N13: =VLOOKUP(H13,Лист2!$A:$F,6,FALSE) -> сапфир | O13: =VLOOKUP(I13,Лист2!$A:$F,6,FALSE) -> изумруд | P13: =VLOOKUP(J13,Лист2!$A:$F,6,FALSE) -> аметист
A14: 34 | B14: -1 | C14: 2. Несломленный Монах (Испытание Линя)** | D14: 45894 | E14: рубин | F14: =COUNTIF(N14:P14,E14) -> 1 | G14: не, не лорно | H14: Integrity | I14: Medicine | J14: War | K14: =VLOOKUP(H14,Лист2!$A:$F,2,FALSE) -> 3 | L14: =VLOOKUP(I14,Лист2!$A:$F,2,FALSE) -> 0 | M14: =VLOOKUP(J14,Лист2!$A:$F,2,FALSE) -> 2 | N14: =VLOOKUP(H14,Лист2!$A:$F,6,FALSE) -> аметист | O14: =VLOOKUP(I14,Лист2!$A:$F,6,FALSE) -> аметист | P14: =VLOOKUP(J14,Лист2!$A:$F,6,FALSE) -> рубин
A15: 35 | B15: -1 | C15: 3. Три Удара Судьбы** | D15: 45894 | E15: рубин | F15: =COUNTIF(N15:P15,E15) -> 0 | G15: не, не лорно | H15: Resistance | I15: Integrity | J15: Linguistics | K15: =VLOOKUP(H15,Лист2!$A:$F,2,FALSE) -> 3 | L15: =VLOOKUP(I15,Лист2!$A:$F,2,FALSE) -> 3 | M15: =VLOOKUP(J15,Лист2!$A:$F,2,FALSE) -> 0 | N15: =VLOOKUP(H15,Лист2!$A:$F,6,FALSE) -> топаз | O15: =VLOOKUP(I15,Лист2!$A:$F,6,FALSE) -> аметист | P15: =VLOOKUP(J15,Лист2!$A:$F,6,FALSE) -> сапфир | S15: color | T15: 1
A16: 36 | B16: -1 | C16: Мост Трёх Шансов | D16: 45894 | E16: рубин | F16: =COUNTIF(N16:P16,E16) -> 0 | G16: не, не лорно | H16: Athletics | I16: Martial Arts | J16: Dodge | K16: =VLOOKUP(H16,Лист2!$A:$F,2,FALSE) -> 3 | L16: =VLOOKUP(I16,Лист2!$A:$F,2,FALSE) -> 5 | M16: =VLOOKUP(J16,Лист2!$A:$F,2,FALSE) -> 3 | N16: =VLOOKUP(H16,Лист2!$A:$F,6,FALSE) -> аметист | O16: =VLOOKUP(I16,Лист2!$A:$F,6,FALSE) -> все | P16: =VLOOKUP(J16,Лист2!$A:$F,6,FALSE) -> сапфир
A17: 37 | B17: -1 | C17: 1. Источник Воспоминаний** | D17: 45894 | E17: изумруд | F17: =COUNTIF(N17:P17,E17) -> 0 | G17: интересно, но не лорно!! | H17: Resistance | I17: Integrity | J17: Medicine | K17: =VLOOKUP(H17,Лист2!$A:$F,2,FALSE) -> 3 | L17: =VLOOKUP(I17,Лист2!$A:$F,2,FALSE) -> 3 | M17: =VLOOKUP(J17,Лист2!$A:$F,2,FALSE) -> 0 | N17: =VLOOKUP(H17,Лист2!$A:$F,6,FALSE) -> топаз | O17: =VLOOKUP(I17,Лист2!$A:$F,6,FALSE) -> аметист | P17: =VLOOKUP(J17,Лист2!$A:$F,6,FALSE) -> аметист | S17: Количество по полю испытание | T17: Названия столбцов
A18: 38 | B18: -1 | C18: 2. Сердце Храма** | D18: 45894 | E18: изумруд | F18: =COUNTIF(N18:P18,E18) -> 2 | G18: интересно, но не лорно!! | H18: Medicine | I18: Occult | J18: Larceny | K18: =VLOOKUP(H18,Лист2!$A:$F,2,FALSE) -> 0 | L18: =VLOOKUP(I18,Лист2!$A:$F,2,FALSE) -> 0 | M18: =VLOOKUP(J18,Лист2!$A:$F,2,FALSE) -> 0 | N18: =VLOOKUP(H18,Лист2!$A:$F,6,FALSE) -> аметист | O18: =VLOOKUP(I18,Лист2!$A:$F,6,FALSE) -> изумруд | P18: =VLOOKUP(J18,Лист2!$A:$F,6,FALSE) -> изумруд | S18: Названия строк | T18: 45889 | U18: 45892 | V18: 45894 | W18: Общий итог
A19: 39 | B19: -1 | C19: 3. Судья и Преступник** | D19: 45894 | E19: изумруд | F19: =COUNTIF(N19:P19,E19) -> 1 | G19: интересно, но не лорно!! | H19: Investigation | I19: Bureaucracy | J19: Presence | K19: =VLOOKUP(H19,Лист2!$A:$F,2,FALSE) -> 0 | L19: =VLOOKUP(I19,Лист2!$A:$F,2,FALSE) -> 0 | M19: =VLOOKUP(J19,Лист2!$A:$F,2,FALSE) -> 3 | N19: =VLOOKUP(H19,Лист2!$A:$F,6,FALSE) -> изумруд | O19: =VLOOKUP(I19,Лист2!$A:$F,6,FALSE) -> аметист | P19: =VLOOKUP(J19,Лист2!$A:$F,6,FALSE) -> рубин | S19: топаз | T19: 1 | V19: 2 | W19: 3
A20: 2 | B20: 0 | C20: 2. «Ловец Слов» | D20: 45889 | F20: =COUNTIF(N20:P20,E20) -> 0 | G20: слабо по навыкам Банга | H20: Linguistics | I20: Investigation | J20: Dodge | K20: =VLOOKUP(H20,Лист2!$A:$F,2,FALSE) -> 0 | L20: =VLOOKUP(I20,Лист2!$A:$F,2,FALSE) -> 0 | M20: =VLOOKUP(J20,Лист2!$A:$F,2,FALSE) -> 3 | N20: =VLOOKUP(H20,Лист2!$A:$F,6,FALSE) -> сапфир | O20: =VLOOKUP(I20,Лист2!$A:$F,6,FALSE) -> изумруд | P20: =VLOOKUP(J20,Лист2!$A:$F,6,FALSE) -> сапфир | S20: 1. Лабиринт Зеркальных Воспоминаний** | V20: 1 | W20: 1
A21: 3 | B21: 0 | C21: 3. «Кулаки Рассвета» | D21: 45889 | F21: =COUNTIF(N21:P21,E21) -> 0 | G21: классика, но скучно поставлено | H21: Martial Arts | I21: Brawl | J21: Resistance | K21: =VLOOKUP(H21,Лист2!$A:$F,2,FALSE) -> 5 | L21: =VLOOKUP(I21,Лист2!$A:$F,2,FALSE) -> 1 | M21: =VLOOKUP(J21,Лист2!$A:$F,2,FALSE) -> 3 | N21: =VLOOKUP(H21,Лист2!$A:$F,6,FALSE) -> все | O21: =VLOOKUP(I21,Лист2!$A:$F,6,FALSE) -> рубин | P21: =VLOOKUP(J21,Лист2!$A:$F,6,FALSE) -> топаз | S21: 1 и бегство немного перемешать | V21: 1 | W21: 1
A22: 7 | B22: 0 | C22: 7. «Кровь и Чернила» | D22: 45889 | E22: изумруд | F22: =COUNTIF(N22:P22,E22) -> 0 | G22: круто.. Но 0 навыков.. | H22: Linguistics | I22: Craft | J22: Medicine | K22: =VLOOKUP(H22,Лист2!$A:$F,2,FALSE) -> 0 | L22: =VLOOKUP(I22,Лист2!$A:$F,2,FALSE) -> 0 | M22: =VLOOKUP(J22,Лист2!$A:$F,2,FALSE) -> 0 | N22: =VLOOKUP(H22,Лист2!$A:$F,6,FALSE) -> сапфир | O22: =VLOOKUP(I22,Лист2!$A:$F,6,FALSE) -> сапфир | P22: =VLOOKUP(J22,Лист2!$A:$F,6,FALSE) -> аметист | S22: 8. «Бегство от Судьбы» | T22: 1 | W22: 1
A23: 10 | B23: 0 | C23: 10. «Последний Шепот» | D23: 45889 | F23: =COUNTIF(N23:P23,E23) -> 0 | G23: круто.. Но мало навыков.. | H23: Occult | I23: Bureaucracy | J23: Thrown | K23: =VLOOKUP(H23,Лист2!$A:$F,2,FALSE) -> 0 | L23: =VLOOKUP(I23,Лист2!$A:$F,2,FALSE) -> 0 | M23: =VLOOKUP(J23,Лист2!$A:$F,2,FALSE) -> 2 | N23: =VLOOKUP(H23,Лист2!$A:$F,6,FALSE) -> изумруд | O23: =VLOOKUP(I23,Лист2!$A:$F,6,FALSE) -> аметист | P23: =VLOOKUP(J23,Лист2!$A:$F,6,FALSE) -> топаз | S23: круто. Чуть подрихтовать | T23: 1 | W23: 1
A24: 11 | B24: 0 | C24: 11. «Суд Молчания» | D24: 45889 | E24: топаз | F24: =COUNTIF(N24:P24,E24) -> 0 | G24: может объединить с 10 | H24: Bureaucracy | I24: Presence | J24: Integrity | K24: =VLOOKUP(H24,Лист2!$A:$F,2,FALSE) -> 0 | L24: =VLOOKUP(I24,Лист2!$A:$F,2,FALSE) -> 3 | M24: =VLOOKUP(J24,Лист2!$A:$F,2,FALSE) -> 3 | N24: =VLOOKUP(H24,Лист2!$A:$F,6,FALSE) -> аметист | O24: =VLOOKUP(I24,Лист2!$A:$F,6,FALSE) -> рубин | P24: =VLOOKUP(J24,Лист2!$A:$F,6,FALSE) -> аметист | S24: Бегство из Лабиринта Воспоминаний | V24: 1 | W24: 1
A25: 14 | B25: 0 | C25: 14. «Раны Мира» | D25: 45889 | E25: аметист | F25: =COUNTIF(N25:P25,E25) -> 1 | G25: круто.. Но 0 навыков.. | H25: Medicine | I25: Resistance | J25: Craft | K25: =VLOOKUP(H25,Лист2!$A:$F,2,FALSE) -> 0 | L25: =VLOOKUP(I25,Лист2!$A:$F,2,FALSE) -> 3 | M25: =VLOOKUP(J25,Лист2!$A:$F,2,FALSE) -> 0 | N25: =VLOOKUP(H25,Лист2!$A:$F,6,FALSE) -> аметист | O25: =VLOOKUP(I25,Лист2!$A:$F,6,FALSE) -> топаз | P25: =VLOOKUP(J25,Лист2!$A:$F,6,FALSE) -> сапфир | S25: 1 и бегство немного перемешать | V25: 1 | W25: 1
A26: 22 | B26: 0 | C26: Испытание Трех Зеркал | D26: 45892 | E26: рубин | F26: =COUNTIF(N26:P26,E26) -> 0 | G26: интересно, но не слишком буквально? | K26: =VLOOKUP(H26,Лист2!$A:$F,2,FALSE) -> #N/A | L26: =VLOOKUP(I26,Лист2!$A:$F,2,FALSE) -> #N/A | M26: =VLOOKUP(J26,Лист2!$A:$F,2,FALSE) -> #N/A | N26: =VLOOKUP(H26,Лист2!$A:$F,6,FALSE) -> #N/A | O26: =VLOOKUP(I26,Лист2!$A:$F,6,FALSE) -> #N/A | P26: =VLOOKUP(J26,Лист2!$A:$F,6,FALSE) -> #N/A | S26: сапфир | T26: 1 | V26: 2 | W26: 3
A27: 23 | B27: 0 | C27: Сожжённые письма | D27: 45892 | E27: изумруд | F27: =COUNTIF(N27:P27,E27) -> 0 | G27: это не испытание, а просто сцена | K27: =VLOOKUP(H27,Лист2!$A:$F,2,FALSE) -> #N/A | L27: =VLOOKUP(I27,Лист2!$A:$F,2,FALSE) -> #N/A | M27: =VLOOKUP(J27,Лист2!$A:$F,2,FALSE) -> #N/A | N27: =VLOOKUP(H27,Лист2!$A:$F,6,FALSE) -> #N/A | O27: =VLOOKUP(I27,Лист2!$A:$F,6,FALSE) -> #N/A | P27: =VLOOKUP(J27,Лист2!$A:$F,6,FALSE) -> #N/A | S27: 3. Дуэль с Тенью Раэда Дахика** | V27: 1 | W27: 1
A28: 29 | B28: 0 | C28: 1. Испорченная Симфония** | D28: 45894 | E28: сапфир | F28: =COUNTIF(N28:P28,E28) -> 2 | G28: интересно, но не те люди | H28: Performance | I28: Craft | J28: Medicine | K28: =VLOOKUP(H28,Лист2!$A:$F,2,FALSE) -> 0 | L28: =VLOOKUP(I28,Лист2!$A:$F,2,FALSE) -> 0 | M28: =VLOOKUP(J28,Лист2!$A:$F,2,FALSE) -> 0 | N28: =VLOOKUP(H28,Лист2!$A:$F,6,FALSE) -> сапфир | O28: =VLOOKUP(I28,Лист2!$A:$F,6,FALSE) -> сапфир | P28: =VLOOKUP(J28,Лист2!$A:$F,6,FALSE) -> аметист | S28: ритм-гейм! | V28: 1 | W28: 1
A29: 30 | B29: 0 | C29: 2. Сад Камней и Клинков** | D29: 45894 | E29: сапфир | F29: =COUNTIF(N29:P29,E29) -> 1 | G29: интересно, но не те люди | H29: Awareness | I29: Craft | J29: Larceny | K29: =VLOOKUP(H29,Лист2!$A:$F,2,FALSE) -> 3 | L29: =VLOOKUP(I29,Лист2!$A:$F,2,FALSE) -> 0 | M29: =VLOOKUP(J29,Лист2!$A:$F,2,FALSE) -> 0 | N29: =VLOOKUP(H29,Лист2!$A:$F,6,FALSE) -> аметист | O29: =VLOOKUP(I29,Лист2!$A:$F,6,FALSE) -> сапфир | P29: =VLOOKUP(J29,Лист2!$A:$F,6,FALSE) -> изумруд | S29: 5. «Песня Безмятежности» | T29: 1 | W29: 1
A30: 43 | B30: 0 | C30: 1. Угасание Солнца** | D30: 45894 | E30: аметист | F30: =COUNTIF(N30:P30,E30) -> 1 | G30: интересно, но не те люди | H30: Integrity | I30: Occult | J30: Presence | K30: =VLOOKUP(H30,Лист2!$A:$F,2,FALSE) -> 3 | L30: =VLOOKUP(I30,Лист2!$A:$F,2,FALSE) -> 0 | M30: =VLOOKUP(J30,Лист2!$A:$F,2,FALSE) -> 3 | N30: =VLOOKUP(H30,Лист2!$A:$F,6,FALSE) -> аметист | O30: =VLOOKUP(I30,Лист2!$A:$F,6,FALSE) -> изумруд | P30: =VLOOKUP(J30,Лист2!$A:$F,6,FALSE) -> рубин | S30: норм, но перекроить? | T30: 1 | W30: 1
A31: 44 | B31: 0 | C31: 2. Ковчег Последней Надежды** | D31: 45894 | E31: аметист | F31: =COUNTIF(N31:P31,E31) -> 1 | G31: интересно, но не те люди | H31: Bureaucracy | I31: Lore | J31: Presence | K31: =VLOOKUP(H31,Лист2!$A:$F,2,FALSE) -> 0 | L31: =VLOOKUP(I31,Лист2!$A:$F,2,FALSE) -> 0 | M31: =VLOOKUP(J31,Лист2!$A:$F,2,FALSE) -> 3 | N31: =VLOOKUP(H31,Лист2!$A:$F,6,FALSE) -> аметист | O31: =VLOOKUP(I31,Лист2!$A:$F,6,FALSE) -> изумруд | P31: =VLOOKUP(J31,Лист2!$A:$F,6,FALSE) -> рубин | S31: Танец Застывших Струн* | V31: 1 | W31: 1
A32: 9 | B32: 1 | C32: 9. «Море Сомнений» | D32: 45889 | E32: аметист | F32: =COUNTIF(N32:P32,E32) -> 0 | G32: норм, но перекроить? | H32: Sail | I32: Archery | J32: War | K32: =VLOOKUP(H32,Лист2!$A:$F,2,FALSE) -> 0 | L32: =VLOOKUP(I32,Лист2!$A:$F,2,FALSE) -> 0 | M32: =VLOOKUP(J32,Лист2!$A:$F,2,FALSE) -> 2 | N32: =VLOOKUP(H32,Лист2!$A:$F,6,FALSE) -> топаз | O32: =VLOOKUP(I32,Лист2!$A:$F,6,FALSE) -> рубин | P32: =VLOOKUP(J32,Лист2!$A:$F,6,FALSE) -> рубин | S32: ритм-гейм! | V32: 1 | W32: 1
A33: 18 | B33: 1 | C33: 18. «Последний Рубеж» | D33: 45889 | E33: АМЕТИСТ | F33: =COUNTIF(N33:P33,E33) -> 1 | G33: круто. Чуть подрихтовать | H33: Resistance | I33: Melee | J33: Medicine | K33: =VLOOKUP(H33,Лист2!$A:$F,2,FALSE) -> 3 | L33: =VLOOKUP(I33,Лист2!$A:$F,2,FALSE) -> 0 | M33: =VLOOKUP(J33,Лист2!$A:$F,2,FALSE) -> 0 | N33: =VLOOKUP(H33,Лист2!$A:$F,6,FALSE) -> топаз | O33: =VLOOKUP(I33,Лист2!$A:$F,6,FALSE) -> рубин | P33: =VLOOKUP(J33,Лист2!$A:$F,6,FALSE) -> аметист | S33: рубин | V33: 1 | W33: 1
A34: 24 | B34: 1 | C34: Сад каменных Цветов | D34: 45892 | E34: аметист | F34: =COUNTIF(N34:P34,E34) -> 0 | G34: норм, но перекроить? | K34: =VLOOKUP(H34,Лист2!$A:$F,2,FALSE) -> #N/A | L34: =VLOOKUP(I34,Лист2!$A:$F,2,FALSE) -> #N/A | M34: =VLOOKUP(J34,Лист2!$A:$F,2,FALSE) -> #N/A | N34: =VLOOKUP(H34,Лист2!$A:$F,6,FALSE) -> #N/A | O34: =VLOOKUP(I34,Лист2!$A:$F,6,FALSE) -> #N/A | P34: =VLOOKUP(J34,Лист2!$A:$F,6,FALSE) -> #N/A | S34: 1. Осада Лукши** | V34: 1 | W34: 1
A35: 6 | B35: 1 | C35: 6. «Сеть Лжи» | D35: 45889 | E35: изумруд | F35: =COUNTIF(N35:P35,E35) -> 2 | G35: немного запутанно, но норм | H35: Stealth | I35: Larceny | J35: Awareness | K35: =VLOOKUP(H35,Лист2!$A:$F,2,FALSE) -> 3 | L35: =VLOOKUP(I35,Лист2!$A:$F,2,FALSE) -> 0 | M35: =VLOOKUP(J35,Лист2!$A:$F,2,FALSE) -> 3 | N35: =VLOOKUP(H35,Лист2!$A:$F,6,FALSE) -> изумруд | O35: =VLOOKUP(I35,Лист2!$A:$F,6,FALSE) -> изумруд | P35: =VLOOKUP(J35,Лист2!$A:$F,6,FALSE) -> аметист | S35: гуд | V35: 1 | W35: 1
A36: 41 | B36: 1 | C36: 5. Ритуал Рассечённого Шёлка** | D36: 45894 | E36: изумруд | F36: =COUNTIF(N36:P36,E36) -> 1 | G36: гуд | H36: Martial Arts | I36: Stealth | J36: Awareness | K36: =VLOOKUP(H36,Лист2!$A:$F,2,FALSE) -> 5 | L36: =VLOOKUP(I36,Лист2!$A:$F,2,FALSE) -> 3 | M36: =VLOOKUP(J36,Лист2!$A:$F,2,FALSE) -> 3 | N36: =VLOOKUP(H36,Лист2!$A:$F,6,FALSE) -> все | O36: =VLOOKUP(I36,Лист2!$A:$F,6,FALSE) -> изумруд | P36: =VLOOKUP(J36,Лист2!$A:$F,6,FALSE) -> аметист | S36: изумруд | T36: 1 | V36: 3 | W36: 4
A37: 5 | B37: 1 | C37: 5. «Песня Безмятежности» | D37: 45889 | E37: сапфир | F37: =COUNTIF(N37:P37,E37) -> 1 | G37: норм, но перекроить? | H37: Performance | I37: Occult | J37: Integrity | K37: =VLOOKUP(H37,Лист2!$A:$F,2,FALSE) -> 0 | L37: =VLOOKUP(I37,Лист2!$A:$F,2,FALSE) -> 0 | M37: =VLOOKUP(J37,Лист2!$A:$F,2,FALSE) -> 3 | N37: =VLOOKUP(H37,Лист2!$A:$F,6,FALSE) -> сапфир | O37: =VLOOKUP(I37,Лист2!$A:$F,6,FALSE) -> изумруд | P37: =VLOOKUP(J37,Лист2!$A:$F,6,FALSE) -> аметист | S37: 4. Поток Обжигающей Правды** | V37: 1 | W37: 1
A38: 46 | B38: 2 | C38: Восход в Бездне | D38: 45894 | E38: аметист | F38: =COUNTIF(N38:P38,E38) -> 2 | G38: о да | H38: Martial Arts | I38: Athletics | J38: Integrity | K38: =VLOOKUP(H38,Лист2!$A:$F,2,FALSE) -> 5 | L38: =VLOOKUP(I38,Лист2!$A:$F,2,FALSE) -> 3 | M38: =VLOOKUP(J38,Лист2!$A:$F,2,FALSE) -> 3 | N38: =VLOOKUP(H38,Лист2!$A:$F,6,FALSE) -> все | O38: =VLOOKUP(I38,Лист2!$A:$F,6,FALSE) -> аметист | P38: =VLOOKUP(J38,Лист2!$A:$F,6,FALSE) -> аметист | S38: гуд | V38: 1 | W38: 1
A39: 42 | B39: 2 | C39: 6. Исповедь в Зеркальном Дожде** | D39: 45894 | E39: изумруд | F39: =COUNTIF(N39:P39,E39) -> 0 | G39: гуд | H39: Dodge | I39: Athletics | J39: Integrity | K39: =VLOOKUP(H39,Лист2!$A:$F,2,FALSE) -> 3 | L39: =VLOOKUP(I39,Лист2!$A:$F,2,FALSE) -> 3 | M39: =VLOOKUP(J39,Лист2!$A:$F,2,FALSE) -> 3 | N39: =VLOOKUP(H39,Лист2!$A:$F,6,FALSE) -> сапфир | O39: =VLOOKUP(I39,Лист2!$A:$F,6,FALSE) -> аметист | P39: =VLOOKUP(J39,Лист2!$A:$F,6,FALSE) -> аметист | S39: 5. Ритуал Рассечённого Шёлка** | V39: 1 | W39: 1
A40: 31 | B40: 2 | C40: 3. Дуэль с Тенью Раэда Дахика** | D40: 45894 | E40: сапфир | F40: =COUNTIF(N40:P40,E40) -> 2 | G40: ритм-гейм! | H40: Brawl | I40: Dodge | J40: Performance | K40: =VLOOKUP(H40,Лист2!$A:$F,2,FALSE) -> 1 | L40: =VLOOKUP(I40,Лист2!$A:$F,2,FALSE) -> 3 | M40: =VLOOKUP(J40,Лист2!$A:$F,2,FALSE) -> 0 | N40: =VLOOKUP(H40,Лист2!$A:$F,6,FALSE) -> рубин | O40: =VLOOKUP(I40,Лист2!$A:$F,6,FALSE) -> сапфир | P40: =VLOOKUP(J40,Лист2!$A:$F,6,FALSE) -> сапфир | S40: гуд | V40: 1 | W40: 1
A41: 25 | B41: 2 | C41: 1. Лабиринт Зеркальных Воспоминаний** | D41: 45894 | E41: топаз | F41: =COUNTIF(N41:P41,E41) -> 0 | G41: 1 и бегство немного перемешать | H41: Investigation | I41: Lore | J41: Integrity | K41: =VLOOKUP(H41,Лист2!$A:$F,2,FALSE) -> 0 | L41: =VLOOKUP(I41,Лист2!$A:$F,2,FALSE) -> 0 | M41: =VLOOKUP(J41,Лист2!$A:$F,2,FALSE) -> 3 | N41: =VLOOKUP(H41,Лист2!$A:$F,6,FALSE) -> изумруд | O41: =VLOOKUP(I41,Лист2!$A:$F,6,FALSE) -> изумруд | P41: =VLOOKUP(J41,Лист2!$A:$F,6,FALSE) -> аметист | S41: 6. «Сеть Лжи» | T41: 1 | W41: 1
A42: 45 | B42: 3 | C42: 3. Наследник Рассвета** | D42: 45894 | E42: аметист | F42: =COUNTIF(N42:P42,E42) -> 0 | G42: клево | H42: Linguistics | I42: Performance | J42: Craft | K42: =VLOOKUP(H42,Лист2!$A:$F,2,FALSE) -> 0 | L42: =VLOOKUP(I42,Лист2!$A:$F,2,FALSE) -> 0 | M42: =VLOOKUP(J42,Лист2!$A:$F,2,FALSE) -> 0 | N42: =VLOOKUP(H42,Лист2!$A:$F,6,FALSE) -> сапфир | O42: =VLOOKUP(I42,Лист2!$A:$F,6,FALSE) -> сапфир | P42: =VLOOKUP(J42,Лист2!$A:$F,6,FALSE) -> сапфир | S42: немного запутанно, но норм | T42: 1 | W42: 1
A43: 40 | B43: 3 | C43: 4. Поток Обжигающей Правды** | D43: 45894 | E43: изумруд | F43: =COUNTIF(N43:P43,E43) -> 0 | G43: гуд | H43: Athletics | I43: Dodge | J43: Integrity | K43: =VLOOKUP(H43,Лист2!$A:$F,2,FALSE) -> 3 | L43: =VLOOKUP(I43,Лист2!$A:$F,2,FALSE) -> 3 | M43: =VLOOKUP(J43,Лист2!$A:$F,2,FALSE) -> 3 | N43: =VLOOKUP(H43,Лист2!$A:$F,6,FALSE) -> аметист | O43: =VLOOKUP(I43,Лист2!$A:$F,6,FALSE) -> сапфир | P43: =VLOOKUP(J43,Лист2!$A:$F,6,FALSE) -> аметист | S43: 6. Исповедь в Зеркальном Дожде** | V43: 1 | W43: 1
A44: 33 | B44: 3 | C44: 1. Осада Лукши** | D44: 45894 | E44: рубин | F44: =COUNTIF(N44:P44,E44) -> 1 | G44: гуд | H44: Brawl | I44: Awareness | J44: Larceny | K44: =VLOOKUP(H44,Лист2!$A:$F,2,FALSE) -> 1 | L44: =VLOOKUP(I44,Лист2!$A:$F,2,FALSE) -> 3 | M44: =VLOOKUP(J44,Лист2!$A:$F,2,FALSE) -> 0 | N44: =VLOOKUP(H44,Лист2!$A:$F,6,FALSE) -> рубин | O44: =VLOOKUP(I44,Лист2!$A:$F,6,FALSE) -> аметист | P44: =VLOOKUP(J44,Лист2!$A:$F,6,FALSE) -> изумруд | S44: гуд | V44: 1 | W44: 1
A45: 32 | B45: 3 | C45: Танец Застывших Струн* | D45: 45894 | E45: сапфир | F45: =COUNTIF(N45:P45,E45) -> 1 | G45: ритм-гейм! | H45: Martial Arts | I45: Dodge | J45: Awareness | K45: =VLOOKUP(H45,Лист2!$A:$F,2,FALSE) -> 5 | L45: =VLOOKUP(I45,Лист2!$A:$F,2,FALSE) -> 3 | M45: =VLOOKUP(J45,Лист2!$A:$F,2,FALSE) -> 3 | N45: =VLOOKUP(H45,Лист2!$A:$F,6,FALSE) -> все | O45: =VLOOKUP(I45,Лист2!$A:$F,6,FALSE) -> сапфир | P45: =VLOOKUP(J45,Лист2!$A:$F,6,FALSE) -> аметист | S45: аметист | T45: 2 | U45: 1 | V45: 2 | W45: 5
A46: 8 | B46: 3 | C46: 8. «Бегство от Судьбы» | D46: 45889 | E46: топаз | F46: =COUNTIF(N46:P46,E46) -> 2 | G46: круто. Чуть подрихтовать | H46: Athletics | I46: Ride | J46: Survival | K46: =VLOOKUP(H46,Лист2!$A:$F,2,FALSE) -> 3 | L46: =VLOOKUP(I46,Лист2!$A:$F,2,FALSE) -> 0 | M46: =VLOOKUP(J46,Лист2!$A:$F,2,FALSE) -> 1 | N46: =VLOOKUP(H46,Лист2!$A:$F,6,FALSE) -> аметист | O46: =VLOOKUP(I46,Лист2!$A:$F,6,FALSE) -> топаз | P46: =VLOOKUP(J46,Лист2!$A:$F,6,FALSE) -> топаз | S46: 18. «Последний Рубеж» | T46: 1 | W46: 1
A47: 28 | B47: 3 | C47: Бегство из Лабиринта Воспоминаний | D47: 45894 | E47: топаз | F47: =COUNTIF(N47:P47,E47) -> 0 | G47: 1 и бегство немного перемешать | H47: Athletics | I47: Dodge | J47: Awareness | K47: =VLOOKUP(H47,Лист2!$A:$F,2,FALSE) -> 3 | L47: =VLOOKUP(I47,Лист2!$A:$F,2,FALSE) -> 3 | M47: =VLOOKUP(J47,Лист2!$A:$F,2,FALSE) -> 3 | N47: =VLOOKUP(H47,Лист2!$A:$F,6,FALSE) -> аметист | O47: =VLOOKUP(I47,Лист2!$A:$F,6,FALSE) -> сапфир | P47: =VLOOKUP(J47,Лист2!$A:$F,6,FALSE) -> аметист | S47: круто. Чуть подрихтовать | T47: 1 | W47: 1
S48: 3. Наследник Рассвета** | V48: 1 | W48: 1
S49: клево | V49: 1 | W49: 1
S50: 9. «Море Сомнений» | T50: 1 | W50: 1
S51: норм, но перекроить? | T51: 1 | W51: 1
S52: Восход в Бездне | V52: 1 | W52: 1
S53: о да | V53: 1 | W53: 1
S54: Сад каменных Цветов | U54: 1 | W54: 1
S55: норм, но перекроить? | U55: 1 | W55: 1
S56: Общий итог | T56: 5 | U56: 1 | V56: 10 | W56: 16

Sheet Лист2
A2: Ability | B2: у банга | C2: Группы | D2: Solar Castes | E2: Siderial Castes | F2: камень девы | G2: топаз | H2: сапфир | I2: рубин | J2: изумруд | K2: аметист | L2: прочих | M2: всего
A3: Archery | C3: Dawn | D3: dawn | E3: Марс | F3: рубин | G3: =COUNTIFS(trials!$H:$H,$A3,trials!$E:$E,G$2)+COUNTIFS(trials!$I:$I,$A3,trials!$E:$E,G$2)+COUNTIFS(trials!$J:$J,$A3,trials!$E:$E,G$2) -> 0 | H3: =COUNTIFS(trials!$H:$H,$A3,trials!$E:$E,H$2)+COUNTIFS(trials!$I:$I,$A3,trials!$E:$E,H$2)+COUNTIFS(trials!$J:$J,$A3,trials!$E:$E,H$2) -> 0 | I3: =COUNTIFS(trials!$H:$H,$A3,trials!$E:$E,I$2)+COUNTIFS(trials!$I:$I,$A3,trials!$E:$E,I$2)+COUNTIFS(trials!$J:$J,$A3,trials!$E:$E,I$2) -> 0 | J3: =COUNTIFS(trials!$H:$H,$A3,trials!$E:$E,J$2)+COUNTIFS(trials!$I:$I,$A3,trials!$E:$E,J$2)+COUNTIFS(trials!$J:$J,$A3,trials!$E:$E,J$2) -> 0 | K3: =COUNTIFS(trials!$H:$H,$A3,trials!$E:$E,K$2)+COUNTIFS(trials!$I:$I,$A3,trials!$E:$E,K$2)+COUNTIFS(trials!$J:$J,$A3,trials!$E:$E,K$2) -> 1 | L3: =COUNTIF(trials!$H:$H,$A3)+COUNTIF(trials!$I:$I,$A3)+COUNTIF(trials!$J:$J,$A3)-SUM(G3:K3) -> 0 | M3: =COUNTIF(trials!H:J,A3) -> 1
A4: Athletics | B4: 3 | C4: Bang | D4: zenith, night | E4: Сатурн | F4: аметист | G4: =COUNTIFS(trials!$H:$H,$A4,trials!$E:$E,G$2)+COUNTIFS(trials!$I:$I,$A4,trials!$E:$E,G$2)+COUNTIFS(trials!$J:$J,$A4,trials!$E:$E,G$2) -> 2 | H4: =COUNTIFS(trials!$H:$H,$A4,trials!$E:$E,H$2)+COUNTIFS(trials!$I:$I,$A4,trials!$E:$E,H$2)+COUNTIFS(trials!$J:$J,$A4,trials!$E:$E,H$2) -> 0 | I4: =COUNTIFS(trials!$H:$H,$A4,trials!$E:$E,I$2)+COUNTIFS(trials!$I:$I,$A4,trials!$E:$E,I$2)+COUNTIFS(trials!$J:$J,$A4,trials!$E:$E,I$2) -> 1 | J4: =COUNTIFS(trials!$H:$H,$A4,trials!$E:$E,J$2)+COUNTIFS(trials!$I:$I,$A4,trials!$E:$E,J$2)+COUNTIFS(trials!$J:$J,$A4,trials!$E:$E,J$2) -> 2 | K4: =COUNTIFS(trials!$H:$H,$A4,trials!$E:$E,K$2)+COUNTIFS(trials!$I:$I,$A4,trials!$E:$E,K$2)+COUNTIFS(trials!$J:$J,$A4,trials!$E:$E,K$2) -> 1 | L4: =COUNTIF(trials!$H:$H,$A4)+COUNTIF(trials!$I:$I,$A4)+COUNTIF(trials!$J:$J,$A4)-SUM(G4:K4) -> 2 | M4: =COUNTIF(trials!H:J,A4) -> 8
A5: Awareness | B5: 3 | C5: Dawn | D5: dawn, night | E5: Сатурн | F5: аметист | G5: =COUNTIFS(trials!$H:$H,$A5,trials!$E:$E,G$2)+COUNTIFS(trials!$I:$I,$A5,trials!$E:$E,G$2)+COUNTIFS(trials!$J:$J,$A5,trials!$E:$E,G$2) -> 2 | H5: =COUNTIFS(trials!$H:$H,$A5,trials!$E:$E,H$2)+COUNTIFS(trials!$I:$I,$A5,trials!$E:$E,H$2)+COUNTIFS(trials!$J:$J,$A5,trials!$E:$E,H$2) -> 2 | I5: =COUNTIFS(trials!$H:$H,$A5,trials!$E:$E,I$2)+COUNTIFS(trials!$I:$I,$A5,trials!$E:$E,I$2)+COUNTIFS(trials!$J:$J,$A5,trials!$E:$E,I$2) -> 1 | J5: =COUNTIFS(trials!$H:$H,$A5,trials!$E:$E,J$2)+COUNTIFS(trials!$I:$I,$A5,trials!$E:$E,J$2)+COUNTIFS(trials!$J:$J,$A5,trials!$E:$E,J$2) -> 2 | K5: =COUNTIFS(trials!$H:$H,$A5,trials!$E:$E,K$2)+COUNTIFS(trials!$I:$I,$A5,trials!$E:$E,K$2)+COUNTIFS(trials!$J:$J,$A5,trials!$E:$E,K$2) -> 0 | L5: =COUNTIF(trials!$H:$H,$A5)+COUNTIF(trials!$I:$I,$A5)+COUNTIF(trials!$J:$J,$A5)-SUM(G5:K5) -> 0 | M5: =COUNTIF(trials!H:J,A5) -> 7
A6: Brawl | B6: 1 | C6: Dawn | D6: dawn | E6: Марс | F6: рубин | G6: =COUNTIFS(trials!$H:$H,$A6,trials!$E:$E,G$2)+COUNTIFS(trials!$I:$I,$A6,trials!$E:$E,G$2)+COUNTIFS(trials!$J:$J,$A6,trials!$E:$E,G$2) -> 0 | H6: =COUNTIFS(trials!$H:$H,$A6,trials!$E:$E,H$2)+COUNTIFS(trials!$I:$I,$A6,trials!$E:$E,H$2)+COUNTIFS(trials!$J:$J,$A6,trials!$E:$E,H$2) -> 1 | I6: =COUNTIFS(trials!$H:$H,$A6,trials!$E:$E,I$2)+COUNTIFS(trials!$I:$I,$A6,trials!$E:$E,I$2)+COUNTIFS(trials!$J:$J,$A6,trials!$E:$E,I$2) -> 1 | J6: =COUNTIFS(trials!$H:$H,$A6,trials!$E:$E,J$2)+COUNTIFS(trials!$I:$I,$A6,trials!$E:$E,J$2)+COUNTIFS(trials!$J:$J,$A6,trials!$E:$E,J$2) -> 0 | K6: =COUNTIFS(trials!$H:$H,$A6,trials!$E:$E,K$2)+COUNTIFS(trials!$I:$I,$A6,trials!$E:$E,K$2)+COUNTIFS(trials!$J:$J,$A6,trials!$E:$E,K$2) -> 0 | L6: =COUNTIF(trials!$H:$H,$A6)+COUNTIF(trials!$I:$I,$A6)+COUNTIF(trials!$J:$J,$A6)-SUM(G6:K6) -> 2 | M6: =COUNTIF(trials!H:J,A6) -> 4
A7: Bureaucracy | C7: - | D7: twilight, eclipse | E7: Сатурн | F7: аметист | G7: =COUNTIFS(trials!$H:$H,$A7,trials!$E:$E,G$2)+COUNTIFS(trials!$I:$I,$A7,trials!$E:$E,G$2)+COUNTIFS(trials!$J:$J,$A7,trials!$E:$E,G$2) -> 1 | H7: =COUNTIFS(trials!$H:$H,$A7,trials!$E:$E,H$2)+COUNTIFS(trials!$I:$I,$A7,trials!$E:$E,H$2)+COUNTIFS(trials!$J:$J,$A7,trials!$E:$E,H$2) -> 0 | I7: =COUNTIFS(trials!$H:$H,$A7,trials!$E:$E,I$2)+COUNTIFS(trials!$I:$I,$A7,trials!$E:$E,I$2)+COUNTIFS(trials!$J:$J,$A7,trials!$E:$E,I$2) -> 0 | J7: =COUNTIFS(trials!$H:$H,$A7,trials!$E:$E,J$2)+COUNTIFS(trials!$I:$I,$A7,trials!$E:$E,J$2)+COUNTIFS(trials!$J:$J,$A7,trials!$E:$E,J$2) -> 1 | K7: =COUNTIFS(trials!$H:$H,$A7,trials!$E:$E,K$2)+COUNTIFS(trials!$I:$I,$A7,trials!$E:$E,K$2)+COUNTIFS(trials!$J:$J,$A7,trials!$E:$E,K$2) -> 1 | L7: =COUNTIF(trials!$H:$H,$A7)+COUNTIF(trials!$I:$I,$A7)+COUNTIF(trials!$J:$J,$A7)-SUM(G7:K7) -> 1 | M7: =COUNTIF(trials!H:J,A7) -> 4
A8: Craft | C8: Venus | D8: twilight | E8: Венера | F8: сапфир | G8: =COUNTIFS(trials!$H:$H,$A8,trials!$E:$E,G$2)+COUNTIFS(trials!$I:$I,$A8,trials!$E:$E,G$2)+COUNTIFS(trials!$J:$J,$A8,trials!$E:$E,G$2) -> 0 | H8: =COUNTIFS(trials!$H:$H,$A8,trials!$E:$E,H$2)+COUNTIFS(trials!$I:$I,$A8,trials!$E:$E,H$2)+COUNTIFS(trials!$J:$J,$A8,trials!$E:$E,H$2) -> 2 | I8: =COUNTIFS(trials!$H:$H,$A8,trials!$E:$E,I$2)+COUNTIFS(trials!$I:$I,$A8,trials!$E:$E,I$2)+COUNTIFS(trials!$J:$J,$A8,trials!$E:$E,I$2) -> 0 | J8: =COUNTIFS(trials!$H:$H,$A8,trials!$E:$E,J$2)+COUNTIFS(trials!$I:$I,$A8,trials!$E:$E,J$2)+COUNTIFS(trials!$J:$J,$A8,trials!$E:$E,J$2) -> 1 | K8: =COUNTIFS(trials!$H:$H,$A8,trials!$E:$E,K$2)+COUNTIFS(trials!$I:$I,$A8,trials!$E:$E,K$2)+COUNTIFS(trials!$J:$J,$A8,trials!$E:$E,K$2) -> 2 | L8: =COUNTIF(trials!$H:$H,$A8)+COUNTIF(trials!$I:$I,$A8)+COUNTIF(trials!$J:$J,$A8)-SUM(G8:K8) -> 0 | M8: =COUNTIF(trials!H:J,A8) -> 5
A9: Dodge | B9: 3 | C9: siblings | D9: dawn, night | E9: Венера | F9: сапфир | G9: =COUNTIFS(trials!$H:$H,$A9,trials!$E:$E,G$2)+COUNTIFS(trials!$I:$I,$A9,trials!$E:$E,G$2)+COUNTIFS(trials!$J:$J,$A9,trials!$E:$E,G$2) -> 1 | H9: =COUNTIFS(trials!$H:$H,$A9,trials!$E:$E,H$2)+COUNTIFS(trials!$I:$I,$A9,trials!$E:$E,H$2)+COUNTIFS(trials!$J:$J,$A9,trials!$E:$E,H$2) -> 2 | I9: =COUNTIFS(trials!$H:$H,$A9,trials!$E:$E,I$2)+COUNTIFS(trials!$I:$I,$A9,trials!$E:$E,I$2)+COUNTIFS(trials!$J:$J,$A9,trials!$E:$E,I$2) -> 1 | J9: =COUNTIFS(trials!$H:$H,$A9,trials!$E:$E,J$2)+COUNTIFS(trials!$I:$I,$A9,trials!$E:$E,J$2)+COUNTIFS(trials!$J:$J,$A9,trials!$E:$E,J$2) -> 2 | K9: =COUNTIFS(trials!$H:$H,$A9,trials!$E:$E,K$2)+COUNTIFS(trials!$I:$I,$A9,trials!$E:$E,K$2)+COUNTIFS(trials!$J:$J,$A9,trials!$E:$E,K$2) -> 0 | L9: =COUNTIF(trials!$H:$H,$A9)+COUNTIF(trials!$I:$I,$A9)+COUNTIF(trials!$J:$J,$A9)-SUM(G9:K9) -> 1 | M9: =COUNTIF(trials!H:J,A9) -> 7
A10: Integrity | B10: 3 | C10: Bang | D10: zenith, twilight | E10: Сатурн | F10: аметист | G10: =COUNTIFS(trials!$H:$H,$A10,trials!$E:$E,G$2)+COUNTIFS(trials!$I:$I,$A10,trials!$E:$E,G$2)+COUNTIFS(trials!$J:$J,$A10,trials!$E:$E,G$2) -> 4 | H10: =COUNTIFS(trials!$H:$H,$A10,trials!$E:$E,H$2)+COUNTIFS(trials!$I:$I,$A10,trials!$E:$E,H$2)+COUNTIFS(trials!$J:$J,$A10,trials!$E:$E,H$2) -> 1 | I10: =COUNTIFS(trials!$H:$H,$A10,trials!$E:$E,I$2)+COUNTIFS(trials!$I:$I,$A10,trials!$E:$E,I$2)+COUNTIFS(trials!$J:$J,$A10,trials!$E:$E,I$2) -> 2 | J10: =COUNTIFS(trials!$H:$H,$A10,trials!$E:$E,J$2)+COUNTIFS(trials!$I:$I,$A10,trials!$E:$E,J$2)+COUNTIFS(trials!$J:$J,$A10,trials!$E:$E,J$2) -> 4 | K10: =COUNTIFS(trials!$H:$H,$A10,trials!$E:$E,K$2)+COUNTIFS(trials!$I:$I,$A10,trials!$E:$E,K$2)+COUNTIFS(trials!$J:$J,$A10,trials!$E:$E,K$2) -> 2 | L10: =COUNTIF(trials!$H:$H,$A10)+COUNTIF(trials!$I:$I,$A10)+COUNTIF(trials!$J:$J,$A10)-SUM(G10:K10) -> 0 | M10: =COUNTIF(trials!H:J,A10) -> 13
A11: Investigation | C11: - | D11: twilight, night | E11: Юпитер | F11: изумруд | G11: =COUNTIFS(trials!$H:$H,$A11,trials!$E:$E,G$2)+COUNTIFS(trials!$I:$I,$A11,trials!$E:$E,G$2)+COUNTIFS(trials!$J:$J,$A11,trials!$E:$E,G$2) -> 1 | H11: =COUNTIFS(trials!$H:$H,$A11,trials!$E:$E,H$2)+COUNTIFS(trials!$I:$I,$A11,trials!$E:$E,H$2)+COUNTIFS(trials!$J:$J,$A11,trials!$E:$E,H$2) -> 0 | I11: =COUNTIFS(trials!$H:$H,$A11,trials!$E:$E,I$2)+COUNTIFS(trials!$I:$I,$A11,trials!$E:$E,I$2)+COUNTIFS(trials!$J:$J,$A11,trials!$E:$E,I$2) -> 0 | J11: =COUNTIFS(trials!$H:$H,$A11,trials!$E:$E,J$2)+COUNTIFS(trials!$I:$I,$A11,trials!$E:$E,J$2)+COUNTIFS(trials!$J:$J,$A11,trials!$E:$E,J$2) -> 1 | K11: =COUNTIFS(trials!$H:$H,$A11,trials!$E:$E,K$2)+COUNTIFS(trials!$I:$I,$A11,trials!$E:$E,K$2)+COUNTIFS(trials!$J:$J,$A11,trials!$E:$E,K$2) -> 0 | L11: =COUNTIF(trials!$H:$H,$A11)+COUNTIF(trials!$I:$I,$A11)+COUNTIF(trials!$J:$J,$A11)-SUM(G11:K11) -> 2 | M11: =COUNTIF(trials!H:J,A11) -> 4
A12: Larceny | C12: - | D12: night, eclipse | E12: Юпитер | F12: изумруд | G12: =COUNTIFS(trials!$H:$H,$A12,trials!$E:$E,G$2)+COUNTIFS(trials!$I:$I,$A12,trials!$E:$E,G$2)+COUNTIFS(trials!$J:$J,$A12,trials!$E:$E,G$2) -> 0 | H12: =COUNTIFS(trials!$H:$H,$A12,trials!$E:$E,H$2)+COUNTIFS(trials!$I:$I,$A12,trials!$E:$E,H$2)+COUNTIFS(trials!$J:$J,$A12,trials!$E:$E,H$2) -> 1 | I12: =COUNTIFS(trials!$H:$H,$A12,trials!$E:$E,I$2)+COUNTIFS(trials!$I:$I,$A12,trials!$E:$E,I$2)+COUNTIFS(trials!$J:$J,$A12,trials!$E:$E,I$2) -> 1 | J12: =COUNTIFS(trials!$H:$H,$A12,trials!$E:$E,J$2)+COUNTIFS(trials!$I:$I,$A12,trials!$E:$E,J$2)+COUNTIFS(trials!$J:$J,$A12,trials!$E:$E,J$2) -> 2 | K12: =COUNTIFS(trials!$H:$H,$A12,trials!$E:$E,K$2)+COUNTIFS(trials!$I:$I,$A12,trials!$E:$E,K$2)+COUNTIFS(trials!$J:$J,$A12,trials!$E:$E,K$2) -> 0 | L12: =COUNTIF(trials!$H:$H,$A12)+COUNTIF(trials!$I:$I,$A12)+COUNTIF(trials!$J:$J,$A12)-SUM(G12:K12) -> 1 | M12: =COUNTIF(trials!H:J,A12) -> 5
A13: Linguistics | C13: Venus | D13: twilight, eclipse | E13: Венера | F13: сапфир | G13: =COUNTIFS(trials!$H:$H,$A13,trials!$E:$E,G$2)+COUNTIFS(trials!$I:$I,$A13,trials!$E:$E,G$2)+COUNTIFS(trials!$J:$J,$A13,trials!$E:$E,G$2) -> 1 | H13: =COUNTIFS(trials!$H:$H,$A13,trials!$E:$E,H$2)+COUNTIFS(trials!$I:$I,$A13,trials!$E:$E,H$2)+COUNTIFS(trials!$J:$J,$A13,trials!$E:$E,H$2) -> 0 | I13: =COUNTIFS(trials!$H:$H,$A13,trials!$E:$E,I$2)+COUNTIFS(trials!$I:$I,$A13,trials!$E:$E,I$2)+COUNTIFS(trials!$J:$J,$A13,trials!$E:$E,I$2) -> 1 | J13: =COUNTIFS(trials!$H:$H,$A13,trials!$E:$E,J$2)+COUNTIFS(trials!$I:$I,$A13,trials!$E:$E,J$2)+COUNTIFS(trials!$J:$J,$A13,trials!$E:$E,J$2) -> 1 | K13: =COUNTIFS(trials!$H:$H,$A13,trials!$E:$E,K$2)+COUNTIFS(trials!$I:$I,$A13,trials!$E:$E,K$2)+COUNTIFS(trials!$J:$J,$A13,trials!$E:$E,K$2) -> 1 | L13: =COUNTIF(trials!$H:$H,$A13)+COUNTIF(trials!$I:$I,$A13)+COUNTIF(trials!$J:$J,$A13)-SUM(G13:K13) -> 2 | M13: =COUNTIF(trials!H:J,A13) -> 6
A14: Lore | C14: - | D14: zenith, twilight | E14: Юпитер | F14: изумруд | G14: =COUNTIFS(trials!$H:$H,$A14,trials!$E:$E,G$2)+COUNTIFS(trials!$I:$I,$A14,trials!$E:$E,G$2)+COUNTIFS(trials!$J:$J,$A14,trials!$E:$E,G$2) -> 3 | H14: =COUNTIFS(trials!$H:$H,$A14,trials!$E:$E,H$2)+COUNTIFS(trials!$I:$I,$A14,trials!$E:$E,H$2)+COUNTIFS(trials!$J:$J,$A14,trials!$E:$E,H$2) -> 0 | I14: =COUNTIFS(trials!$H:$H,$A14,trials!$E:$E,I$2)+COUNTIFS(trials!$I:$I,$A14,trials!$E:$E,I$2)+COUNTIFS(trials!$J:$J,$A14,trials!$E:$E,I$2) -> 0 | J14: =COUNTIFS(trials!$H:$H,$A14,trials!$E:$E,J$2)+COUNTIFS(trials!$I:$I,$A14,trials!$E:$E,J$2)+COUNTIFS(trials!$J:$J,$A14,trials!$E:$E,J$2) -> 0 | K14: =COUNTIFS(trials!$H:$H,$A14,trials!$E:$E,K$2)+COUNTIFS(trials!$I:$I,$A14,trials!$E:$E,K$2)+COUNTIFS(trials!$J:$J,$A14,trials!$E:$E,K$2) -> 1 | L14: =COUNTIF(trials!$H:$H,$A14)+COUNTIF(trials!$I:$I,$A14)+COUNTIF(trials!$J:$J,$A14)-SUM(G14:K14) -> 0 | M14: =COUNTIF(trials!H:J,A14) -> 4
A15: Martial Arts | B15: 5 | C15: siblings | D15: - | E15: все | F15: все | G15: =COUNTIFS(trials!$H:$H,$A15,trials!$E:$E,G$2)+COUNTIFS(trials!$I:$I,$A15,trials!$E:$E,G$2)+COUNTIFS(trials!$J:$J,$A15,trials!$E:$E,G$2) -> 0 | H15: =COUNTIFS(trials!$H:$H,$A15,trials!$E:$E,H$2)+COUNTIFS(trials!$I:$I,$A15,trials!$E:$E,H$2)+COUNTIFS(trials!$J:$J,$A15,trials!$E:$E,H$2) -> 1 | I15: =COUNTIFS(trials!$H:$H,$A15,trials!$E:$E,I$2)+COUNTIFS(trials!$I:$I,$A15,trials!$E:$E,I$2)+COUNTIFS(trials!$J:$J,$A15,trials!$E:$E,I$2) -> 1 | J15: =COUNTIFS(trials!$H:$H,$A15,trials!$E:$E,J$2)+COUNTIFS(trials!$I:$I,$A15,trials!$E:$E,J$2)+COUNTIFS(trials!$J:$J,$A15,trials!$E:$E,J$2) -> 1 | K15: =COUNTIFS(trials!$H:$H,$A15,trials!$E:$E,K$2)+COUNTIFS(trials!$I:$I,$A15,trials!$E:$E,K$2)+COUNTIFS(trials!$J:$J,$A15,trials!$E:$E,K$2) -> 1 | L15: =COUNTIF(trials!$H:$H,$A15)+COUNTIF(trials!$I:$I,$A15)+COUNTIF(trials!$J:$J,$A15)-SUM(G15:K15) -> 1 | M15: =COUNTIF(trials!H:J,A15) -> 5
A16: Medicine | C16: - | D16: twilight | E16: Сатурн | F16: аметист | G16: =COUNTIFS(trials!$H:$H,$A16,trials!$E:$E,G$2)+COUNTIFS(trials!$I:$I,$A16,trials!$E:$E,G$2)+COUNTIFS(trials!$J:$J,$A16,trials!$E:$E,G$2) -> 0 | H16: =COUNTIFS(trials!$H:$H,$A16,trials!$E:$E,H$2)+COUNTIFS(trials!$I:$I,$A16,trials!$E:$E,H$2)+COUNTIFS(trials!$J:$J,$A16,trials!$E:$E,H$2) -> 1 | I16: =COUNTIFS(trials!$H:$H,$A16,trials!$E:$E,I$2)+COUNTIFS(trials!$I:$I,$A16,trials!$E:$E,I$2)+COUNTIFS(trials!$J:$J,$A16,trials!$E:$E,I$2) -> 1 | J16: =COUNTIFS(trials!$H:$H,$A16,trials!$E:$E,J$2)+COUNTIFS(trials!$I:$I,$A16,trials!$E:$E,J$2)+COUNTIFS(trials!$J:$J,$A16,trials!$E:$E,J$2) -> 3 | K16: =COUNTIFS(trials!$H:$H,$A16,trials!$E:$E,K$2)+COUNTIFS(trials!$I:$I,$A16,trials!$E:$E,K$2)+COUNTIFS(trials!$J:$J,$A16,trials!$E:$E,K$2) -> 2 | L16: =COUNTIF(trials!$H:$H,$A16)+COUNTIF(trials!$I:$I,$A16)+COUNTIF(trials!$J:$J,$A16)-SUM(G16:K16) -> 0 | M16: =COUNTIF(trials!H:J,A16) -> 7
A17: Melee | C17: Dawn | D17: dawn | E17: Марс | F17: рубин | G17: =COUNTIFS(trials!$H:$H,$A17,trials!$E:$E,G$2)+COUNTIFS(trials!$I:$I,$A17,trials!$E:$E,G$2)+COUNTIFS(trials!$J:$J,$A17,trials!$E:$E,G$2) -> 0 | H17: =COUNTIFS(trials!$H:$H,$A17,trials!$E:$E,H$2)+COUNTIFS(trials!$I:$I,$A17,trials!$E:$E,H$2)+COUNTIFS(trials!$J:$J,$A17,trials!$E:$E,H$2) -> 0 | I17: =COUNTIFS(trials!$H:$H,$A17,trials!$E:$E,I$2)+COUNTIFS(trials!$I:$I,$A17,trials!$E:$E,I$2)+COUNTIFS(trials!$J:$J,$A17,trials!$E:$E,I$2) -> 1 | J17: =COUNTIFS(trials!$H:$H,$A17,trials!$E:$E,J$2)+COUNTIFS(trials!$I:$I,$A17,trials!$E:$E,J$2)+COUNTIFS(trials!$J:$J,$A17,trials!$E:$E,J$2) -> 0 | K17: =COUNTIFS(trials!$H:$H,$A17,trials!$E:$E,K$2)+COUNTIFS(trials!$I:$I,$A17,trials!$E:$E,K$2)+COUNTIFS(trials!$J:$J,$A17,trials!$E:$E,K$2) -> 1 | L17: =COUNTIF(trials!$H:$H,$A17)+COUNTIF(trials!$I:$I,$A17)+COUNTIF(trials!$J:$J,$A17)-SUM(G17:K17) -> 0 | M17: =COUNTIF(trials!H:J,A17) -> 2
A18: Occult | C18: - | D18: twilight, eclipse | E18: Юпитер | F18: изумруд | G18: =COUNTIFS(trials!$H:$H,$A18,trials!$E:$E,G$2)+COUNTIFS(trials!$I:$I,$A18,trials!$E:$E,G$2)+COUNTIFS(trials!$J:$J,$A18,trials!$E:$E,G$2) -> 1 | H18: =COUNTIFS(trials!$H:$H,$A18,trials!$E:$E,H$2)+COUNTIFS(trials!$I:$I,$A18,trials!$E:$E,H$2)+COUNTIFS(trials!$J:$J,$A18,trials!$E:$E,H$2) -> 2 | I18: =COUNTIFS(trials!$H:$H,$A18,trials!$E:$E,I$2)+COUNTIFS(trials!$I:$I,$A18,trials!$E:$E,I$2)+COUNTIFS(trials!$J:$J,$A18,trials!$E:$E,I$2) -> 0 | J18: =COUNTIFS(trials!$H:$H,$A18,trials!$E:$E,J$2)+COUNTIFS(trials!$I:$I,$A18,trials!$E:$E,J$2)+COUNTIFS(trials!$J:$J,$A18,trials!$E:$E,J$2) -> 1 | K18: =COUNTIFS(trials!$H:$H,$A18,trials!$E:$E,K$2)+COUNTIFS(trials!$I:$I,$A18,trials!$E:$E,K$2)+COUNTIFS(trials!$J:$J,$A18,trials!$E:$E,K$2) -> 1 | L18: =COUNTIF(trials!$H:$H,$A18)+COUNTIF(trials!$I:$I,$A18)+COUNTIF(trials!$J:$J,$A18)-SUM(G18:K18) -> 2 | M18: =COUNTIF(trials!H:J,A18) -> 7
A19: Performance | C19: Venus | D19: zenith | E19: Венера | F19: сапфир | G19: =COUNTIFS(trials!$H:$H,$A19,trials!$E:$E,G$2)+COUNTIFS(trials!$I:$I,$A19,trials!$E:$E,G$2)+COUNTIFS(trials!$J:$J,$A19,trials!$E:$E,G$2) -> 0 | H19: =COUNTIFS(trials!$H:$H,$A19,trials!$E:$E,H$2)+COUNTIFS(trials!$I:$I,$A19,trials!$E:$E,H$2)+COUNTIFS(trials!$J:$J,$A19,trials!$E:$E,H$2) -> 4 | I19: =COUNTIFS(trials!$H:$H,$A19,trials!$E:$E,I$2)+COUNTIFS(trials!$I:$I,$A19,trials!$E:$E,I$2)+COUNTIFS(trials!$J:$J,$A19,trials!$E:$E,I$2) -> 0 | J19: =COUNTIFS(trials!$H:$H,$A19,trials!$E:$E,J$2)+COUNTIFS(trials!$I:$I,$A19,trials!$E:$E,J$2)+COUNTIFS(trials!$J:$J,$A19,trials!$E:$E,J$2) -> 0 | K19: =COUNTIFS(trials!$H:$H,$A19,trials!$E:$E,K$2)+COUNTIFS(trials!$I:$I,$A19,trials!$E:$E,K$2)+COUNTIFS(trials!$J:$J,$A19,trials!$E:$E,K$2) -> 1 | L19: =COUNTIF(trials!$H:$H,$A19)+COUNTIF(trials!$I:$I,$A19)+COUNTIF(trials!$J:$J,$A19)-SUM(G19:K19) -> 0 | M19: =COUNTIF(trials!H:J,A19) -> 5
A20: Presence | B20: 3 | C20: Bang | D20: zenith, eclipse | E20: Марс | F20: рубин | G20: =COUNTIFS(trials!$H:$H,$A20,trials!$E:$E,G$2)+COUNTIFS(trials!$I:$I,$A20,trials!$E:$E,G$2)+COUNTIFS(trials!$J:$J,$A20,trials!$E:$E,G$2) -> 2 | H20: =COUNTIFS(trials!$H:$H,$A20,trials!$E:$E,H$2)+COUNTIFS(trials!$I:$I,$A20,trials!$E:$E,H$2)+COUNTIFS(trials!$J:$J,$A20,trials!$E:$E,H$2) -> 0 | I20: =COUNTIFS(trials!$H:$H,$A20,trials!$E:$E,I$2)+COUNTIFS(trials!$I:$I,$A20,trials!$E:$E,I$2)+COUNTIFS(trials!$J:$J,$A20,trials!$E:$E,I$2) -> 0 | J20: =COUNTIFS(trials!$H:$H,$A20,trials!$E:$E,J$2)+COUNTIFS(trials!$I:$I,$A20,trials!$E:$E,J$2)+COUNTIFS(trials!$J:$J,$A20,trials!$E:$E,J$2) -> 2 | K20: =COUNTIFS(trials!$H:$H,$A20,trials!$E:$E,K$2)+COUNTIFS(trials!$I:$I,$A20,trials!$E:$E,K$2)+COUNTIFS(trials!$J:$J,$A20,trials!$E:$E,K$2) -> 2 | L20: =COUNTIF(trials!$H:$H,$A20)+COUNTIF(trials!$I:$I,$A20)+COUNTIF(trials!$J:$J,$A20)-SUM(G20:K20) -> 0 | M20: =COUNTIF(trials!H:J,A20) -> 6
A21: Resistance | B21: 3 | C21: Dawn | D21: dawn, zenith | E21: Меркурий | F21: топаз | G21: =COUNTIFS(trials!$H:$H,$A21,trials!$E:$E,G$2)+COUNTIFS(trials!$I:$I,$A21,trials!$E:$E,G$2)+COUNTIFS(trials!$J:$J,$A21,trials!$E:$E,G$2) -> 0 | H21: =COUNTIFS(trials!$H:$H,$A21,trials!$E:$E,H$2)+COUNTIFS(trials!$I:$I,$A21,trials!$E:$E,H$2)+COUNTIFS(trials!$J:$J,$A21,trials!$E:$E,H$2) -> 0 | I21: =COUNTIFS(trials!$H:$H,$A21,trials!$E:$E,I$2)+COUNTIFS(trials!$I:$I,$A21,trials!$E:$E,I$2)+COUNTIFS(trials!$J:$J,$A21,trials!$E:$E,I$2) -> 1 | J21: =COUNTIFS(trials!$H:$H,$A21,trials!$E:$E,J$2)+COUNTIFS(trials!$I:$I,$A21,trials!$E:$E,J$2)+COUNTIFS(trials!$J:$J,$A21,trials!$E:$E,J$2) -> 1 | K21: =COUNTIFS(trials!$H:$H,$A21,trials!$E:$E,K$2)+COUNTIFS(trials!$I:$I,$A21,trials!$E:$E,K$2)+COUNTIFS(trials!$J:$J,$A21,trials!$E:$E,K$2) -> 2 | L21: =COUNTIF(trials!$H:$H,$A21)+COUNTIF(trials!$I:$I,$A21)+COUNTIF(trials!$J:$J,$A21)-SUM(G21:K21) -> 1 | M21: =COUNTIF(trials!H:J,A21) -> 5
A22: Ride | C22: - | D22: night, eclipse | E22: Меркурий | F22: топаз | G22: =COUNTIFS(trials!$H:$H,$A22,trials!$E:$E,G$2)+COUNTIFS(trials!$I:$I,$A22,trials!$E:$E,G$2)+COUNTIFS(trials!$J:$J,$A22,trials!$E:$E,G$2) -> 1 | H22: =COUNTIFS(trials!$H:$H,$A22,trials!$E:$E,H$2)+COUNTIFS(trials!$I:$I,$A22,trials!$E:$E,H$2)+COUNTIFS(trials!$J:$J,$A22,trials!$E:$E,H$2) -> 0 | I22: =COUNTIFS(trials!$H:$H,$A22,trials!$E:$E,I$2)+COUNTIFS(trials!$I:$I,$A22,trials!$E:$E,I$2)+COUNTIFS(trials!$J:$J,$A22,trials!$E:$E,I$2) -> 0 | J22: =COUNTIFS(trials!$H:$H,$A22,trials!$E:$E,J$2)+COUNTIFS(trials!$I:$I,$A22,trials!$E:$E,J$2)+COUNTIFS(trials!$J:$J,$A22,trials!$E:$E,J$2) -> 0 | K22: =COUNTIFS(trials!$H:$H,$A22,trials!$E:$E,K$2)+COUNTIFS(trials!$I:$I,$A22,trials!$E:$E,K$2)+COUNTIFS(trials!$J:$J,$A22,trials!$E:$E,K$2) -> 0 | L22: =COUNTIF(trials!$H:$H,$A22)+COUNTIF(trials!$I:$I,$A22)+COUNTIF(trials!$J:$J,$A22)-SUM(G22:K22) -> 1 | M22: =COUNTIF(trials!H:J,A22) -> 2
A23: Sail | C23: - | D23: eclipse | E23: Меркурий | F23: топаз | G23: =COUNTIFS(trials!$H:$H,$A23,trials!$E:$E,G$2)+COUNTIFS(trials!$I:$I,$A23,trials!$E:$E,G$2)+COUNTIFS(trials!$J:$J,$A23,trials!$E:$E,G$2) -> 0 | H23: =COUNTIFS(trials!$H:$H,$A23,trials!$E:$E,H$2)+COUNTIFS(trials!$I:$I,$A23,trials!$E:$E,H$2)+COUNTIFS(trials!$J:$J,$A23,trials!$E:$E,H$2) -> 0 | I23: =COUNTIFS(trials!$H:$H,$A23,trials!$E:$E,I$2)+COUNTIFS(trials!$I:$I,$A23,trials!$E:$E,I$2)+COUNTIFS(trials!$J:$J,$A23,trials!$E:$E,I$2) -> 0 | J23: =COUNTIFS(trials!$H:$H,$A23,trials!$E:$E,J$2)+COUNTIFS(trials!$I:$I,$A23,trials!$E:$E,J$2)+COUNTIFS(trials!$J:$J,$A23,trials!$E:$E,J$2) -> 0 | K23: =COUNTIFS(trials!$H:$H,$A23,trials!$E:$E,K$2)+COUNTIFS(trials!$I:$I,$A23,trials!$E:$E,K$2)+COUNTIFS(trials!$J:$J,$A23,trials!$E:$E,K$2) -> 1 | L23: =COUNTIF(trials!$H:$H,$A23)+COUNTIF(trials!$I:$I,$A23)+COUNTIF(trials!$J:$J,$A23)-SUM(G23:K23) -> 0 | M23: =COUNTIF(trials!H:J,A23) -> 1
A24: Socialize | C24: Venus | D24: night, eclipse | E24: Венера | F24: сапфир | G24: =COUNTIFS(trials!$H:$H,$A24,trials!$E:$E,G$2)+COUNTIFS(trials!$I:$I,$A24,trials!$E:$E,G$2)+COUNTIFS(trials!$J:$J,$A24,trials!$E:$E,G$2) -> 1 | H24: =COUNTIFS(trials!$H:$H,$A24,trials!$E:$E,H$2)+COUNTIFS(trials!$I:$I,$A24,trials!$E:$E,H$2)+COUNTIFS(trials!$J:$J,$A24,trials!$E:$E,H$2) -> 1 | I24: =COUNTIFS(trials!$H:$H,$A24,trials!$E:$E,I$2)+COUNTIFS(trials!$I:$I,$A24,trials!$E:$E,I$2)+COUNTIFS(trials!$J:$J,$A24,trials!$E:$E,I$2) -> 1 | J24: =COUNTIFS(trials!$H:$H,$A24,trials!$E:$E,J$2)+COUNTIFS(trials!$I:$I,$A24,trials!$E:$E,J$2)+COUNTIFS(trials!$J:$J,$A24,trials!$E:$E,J$2) -> 0 | K24: =COUNTIFS(trials!$H:$H,$A24,trials!$E:$E,K$2)+COUNTIFS(trials!$I:$I,$A24,trials!$E:$E,K$2)+COUNTIFS(trials!$J:$J,$A24,trials!$E:$E,K$2) -> 0 | L24: =COUNTIF(trials!$H:$H,$A24)+COUNTIF(trials!$I:$I,$A24)+COUNTIF(trials!$J:$J,$A24)-SUM(G24:K24) -> 1 | M24: =COUNTIF(trials!H:J,A24) -> 4
A25: Stealth | B25: 3 | C25: Bang | D25: night | E25: Юпитер | F25: изумруд | G25: =COUNTIFS(trials!$H:$H,$A25,trials!$E:$E,G$2)+COUNTIFS(trials!$I:$I,$A25,trials!$E:$E,G$2)+COUNTIFS(trials!$J:$J,$A25,trials!$E:$E,G$2) -> 0 | H25: =COUNTIFS(trials!$H:$H,$A25,trials!$E:$E,H$2)+COUNTIFS(trials!$I:$I,$A25,trials!$E:$E,H$2)+COUNTIFS(trials!$J:$J,$A25,trials!$E:$E,H$2) -> 0 | I25: =COUNTIFS(trials!$H:$H,$A25,trials!$E:$E,I$2)+COUNTIFS(trials!$I:$I,$A25,trials!$E:$E,I$2)+COUNTIFS(trials!$J:$J,$A25,trials!$E:$E,I$2) -> 0 | J25: =COUNTIFS(trials!$H:$H,$A25,trials!$E:$E,J$2)+COUNTIFS(trials!$I:$I,$A25,trials!$E:$E,J$2)+COUNTIFS(trials!$J:$J,$A25,trials!$E:$E,J$2) -> 3 | K25: =COUNTIFS(trials!$H:$H,$A25,trials!$E:$E,K$2)+COUNTIFS(trials!$I:$I,$A25,trials!$E:$E,K$2)+COUNTIFS(trials!$J:$J,$A25,trials!$E:$E,K$2) -> 0 | L25: =COUNTIF(trials!$H:$H,$A25)+COUNTIF(trials!$I:$I,$A25)+COUNTIF(trials!$J:$J,$A25)-SUM(G25:K25) -> 0 | M25: =COUNTIF(trials!H:J,A25) -> 3
A26: Survival | B26: 1 | C26: - | D26: zenith | E26: Меркурий | F26: топаз | G26: =COUNTIFS(trials!$H:$H,$A26,trials!$E:$E,G$2)+COUNTIFS(trials!$I:$I,$A26,trials!$E:$E,G$2)+COUNTIFS(trials!$J:$J,$A26,trials!$E:$E,G$2) -> 1 | H26: =COUNTIFS(trials!$H:$H,$A26,trials!$E:$E,H$2)+COUNTIFS(trials!$I:$I,$A26,trials!$E:$E,H$2)+COUNTIFS(trials!$J:$J,$A26,trials!$E:$E,H$2) -> 0 | I26: =COUNTIFS(trials!$H:$H,$A26,trials!$E:$E,I$2)+COUNTIFS(trials!$I:$I,$A26,trials!$E:$E,I$2)+COUNTIFS(trials!$J:$J,$A26,trials!$E:$E,I$2) -> 0 | J26: =COUNTIFS(trials!$H:$H,$A26,trials!$E:$E,J$2)+COUNTIFS(trials!$I:$I,$A26,trials!$E:$E,J$2)+COUNTIFS(trials!$J:$J,$A26,trials!$E:$E,J$2) -> 0 | K26: =COUNTIFS(trials!$H:$H,$A26,trials!$E:$E,K$2)+COUNTIFS(trials!$I:$I,$A26,trials!$E:$E,K$2)+COUNTIFS(trials!$J:$J,$A26,trials!$E:$E,K$2) -> 0 | L26: =COUNTIF(trials!$H:$H,$A26)+COUNTIF(trials!$I:$I,$A26)+COUNTIF(trials!$J:$J,$A26)-SUM(G26:K26) -> 2 | M26: =COUNTIF(trials!H:J,A26) -> 3
A27: Thrown | B27: 2 | C27: Dawn | D27: dawn | E27: Меркурий | F27: топаз | G27: =COUNTIFS(trials!$H:$H,$A27,trials!$E:$E,G$2)+COUNTIFS(trials!$I:$I,$A27,trials!$E:$E,G$2)+COUNTIFS(trials!$J:$J,$A27,trials!$E:$E,G$2) -> 0 | H27: =COUNTIFS(trials!$H:$H,$A27,trials!$E:$E,H$2)+COUNTIFS(trials!$I:$I,$A27,trials!$E:$E,H$2)+COUNTIFS(trials!$J:$J,$A27,trials!$E:$E,H$2) -> 0 | I27: =COUNTIFS(trials!$H:$H,$A27,trials!$E:$E,I$2)+COUNTIFS(trials!$I:$I,$A27,trials!$E:$E,I$2)+COUNTIFS(trials!$J:$J,$A27,trials!$E:$E,I$2) -> 0 | J27: =COUNTIFS(trials!$H:$H,$A27,trials!$E:$E,J$2)+COUNTIFS(trials!$I:$I,$A27,trials!$E:$E,J$2)+COUNTIFS(trials!$J:$J,$A27,trials!$E:$E,J$2) -> 0 | K27: =COUNTIFS(trials!$H:$H,$A27,trials!$E:$E,K$2)+COUNTIFS(trials!$I:$I,$A27,trials!$E:$E,K$2)+COUNTIFS(trials!$J:$J,$A27,trials!$E:$E,K$2) -> 0 | L27: =COUNTIF(trials!$H:$H,$A27)+COUNTIF(trials!$I:$I,$A27)+COUNTIF(trials!$J:$J,$A27)-SUM(G27:K27) -> 1 | M27: =COUNTIF(trials!H:J,A27) -> 1
A28: War | B28: 2 | C28: Dawn | D28: dawn, zenith | E28: Марс | F28: рубин | G28: =COUNTIFS(trials!$H:$H,$A28,trials!$E:$E,G$2)+COUNTIFS(trials!$I:$I,$A28,trials!$E:$E,G$2)+COUNTIFS(trials!$J:$J,$A28,trials!$E:$E,G$2) -> 0 | H28: =COUNTIFS(trials!$H:$H,$A28,trials!$E:$E,H$2)+COUNTIFS(trials!$I:$I,$A28,trials!$E:$E,H$2)+COUNTIFS(trials!$J:$J,$A28,trials!$E:$E,H$2) -> 0 | I28: =COUNTIFS(trials!$H:$H,$A28,trials!$E:$E,I$2)+COUNTIFS(trials!$I:$I,$A28,trials!$E:$E,I$2)+COUNTIFS(trials!$J:$J,$A28,trials!$E:$E,I$2) -> 2 | J28: =COUNTIFS(trials!$H:$H,$A28,trials!$E:$E,J$2)+COUNTIFS(trials!$I:$I,$A28,trials!$E:$E,J$2)+COUNTIFS(trials!$J:$J,$A28,trials!$E:$E,J$2) -> 0 | K28: =COUNTIFS(trials!$H:$H,$A28,trials!$E:$E,K$2)+COUNTIFS(trials!$I:$I,$A28,trials!$E:$E,K$2)+COUNTIFS(trials!$J:$J,$A28,trials!$E:$E,K$2) -> 1 | L28: =COUNTIF(trials!$H:$H,$A28)+COUNTIF(trials!$I:$I,$A28)+COUNTIF(trials!$J:$J,$A28)-SUM(G28:K28) -> 1 | M28: =COUNTIF(trials!H:J,A28) -> 4
